Workbook
Name округл: #REF!
Name округл: #REF!
Name округл: #REF!

Sheet 1M
B1: ПОСТАВЩИК: ООО ФИРМА "СИГНАЛ"
B2: адрес: 364031, Чеченская Республика, г.Грозный, ул. Жуковского, д. 18
C4: Заказ-наряд № 100528 от 08.06.2026
B6: Заказчик: Общество с ограниченной ответственностью «Концепт» | H6: адрес заказчика : 364024, ЧР г.Грозный, ул.Назарбаева, д.92, оф. 6-05
B7: Автомобиль : УАЗ Патриот г/н О 201 МК/126
B9: Цена автомототранспортного средства, определяемая по соглашению сторон __________________
B11: Плательщик: Общество с ограниченной ответственностью «Концепт»
B12: ИНН 2014030866 адрес: телефоны: +7 (989) 9002252
N14: в валюте
N15: Руб
C17: Выполненные работы по заказ-наряду № 100528 от 08.06.2026
B19: № | C19: № кат. | D19: Наименование | I19: Кол. оп. | J19: Цена | K19: Норма | L19: н/ч | M19: Всего | N19: в т.ч. НДС
B20: 1 | C20: 2 | D20: 3 | I20: 4 | J20: 5 | K20: 6 | L20: 7 | M20: 8 | N20: 9
B21: 1 | D21: Ремонт КПП со снятием и установкой | I21: 1 | J21: 15000 | K21: 1 | L21: Рубль | M21: =J21*I21 -> 15000 | N21: =M21*22/122 -> 2704.918
B22: Итого работ: | I22: 1 | J22: на сумму: | M22: =M21 -> 15000 | N22: =M22*22/122 -> 2704.918
B24: Пятнадцать тысяч рублей 00 копеек.
C26: Расходная накладная к заказ-наряду № 100528 от 08.06.2026
B28: № | C28: № кат. | D28: Наименование | J28: Кол-во | K28: Ед.изм. | L28: Цена | M28: Всего | N28: в т.ч. НДС
B29: 1 | C29: 2 | D29: 3 | J29: 4 | K29: 5 | L29: 6 | M29: 7 | N29: 8
B30: 1 | C30: 3590973 | D30: Масло трансмиссионное LUKOIL GEAR GL-4 75W-90 4л. | J30: 1 | K30: шт | L30: 3000 | M30: =L30*J30 -> 3000 | N30: =M30*22/122 -> 540.98361
B31: 2 | C31: 3590970 | D31: Масло трансмиссионное LUKOIL GEAR GL-4 75W-90 1л. | J31: 1 | K31: шт | L31: 800 | M31: =L31*J31 -> 800 | N31: =M31*22/122 -> 144.2623
B32: Итого материалов: | J32: 2 | K32: на сумму: | M32: =M30+M31 -> 3800 | N32: =M32*22/122 -> 685.2459
B34: Три тысячи восемьсот рублей 00 копеек
L36: Итого по заказ-наряду : | M36: =M22+M32 -> 18800 | N36: =M36*22/122 -> 3390.1639
B38: Всего по заказ-наряду: Восемнадцать тысяч восемьсот рублей 00 копеек, в т.ч. НДС 22%.
J41: Мастер _____________________ | K41: Механик СТО/
C43: Гарантии: Гарантия на работы: слесарные - 30 дней, электрические - 30 дней, оригинальные з/ч - 30 дней, з/ч, связанные с электрооборудованием, подачей топлива и системой впрыска - гарантии нет, неоригинальные з/ч - гарантии нет. Гарантийные обязательства на работы выполняются фирмой только при предъявлении акта приемки автомобиля и техпаспорта (доверенности).
B47: Дата: 08.06.2026 | J47: Заказчик ______________________ | K47: /ООО «Концепт»/
J49: Плательщик ______________________ | K49: /ООО «Концепт»/
B51: Причина обращения:

Sheet 001
A1: Общество с ограниченной ответственностью "КОНЦЕПТ"
A2: 364024, Чеченская Республика г. Грозный, ул. Назарбаева, д. 92, оф. 6-05
A4: Заказ-наряд № | D4: 001-20 | E4: от | F4: 46174 | I4: Дата начала работ | K4: 46174
A5: Основание Государственный контракт № 03101000048260000200001 | I5: Дата окончания | K5: 46174
A6: от 01.06.2026г. ИГК 2627188100202002632098795
A8: Заказчик: ЦОУ ВОГОиП МВД России ГУ МВД России по СКФО | I8: VIN № | J8: XTT316300R1000091
I9: Кузов №
A10: Адрес: 363751, Северная Осетия-Алания Респ, ул.Усанова стр.30. | I10: Гос.№ | J10: О201МК126
I11: Год выпуска | K11: 2023
A12: ИНН2632098795 | C12: КПП151043001 | I12: Марка, модель ТС | K12: УАЗ UAZ PATRIOT 3163
A13: Телефон 8-867-36-90-11-8 | I13: Пробег | J13: 4116
I14: Особые данные | K14: гараж.№ | L14: 106-81
A15: Выполненные работы по Заказ-наряду № | H15: 001-20 | I15: от | J15: 46174
A16: № | B16: Код операции | C16: Выполненные работы | G16: Кол-во н/ч | H16: Вид ремонта | I16: Кол-во оп. | J16: Цена н/ч | K16: Ед.изм. | L16: Сумма
A17: 1 | B17: 0000123 | C17: Коробка передач - проверка работы | G17: 0.8 | H17: Обычный | I17: 1 | J17: 2433.33 | K17: н/ч | L17: 1946.66
A18: 2 | B18: 0000210 | C18: Коробка передач - замена масла | G18: 0,25 | H18: Обычный | I18: 1 | J18: 2433.33 | K18: н/ч | L18: 608.33
A19: 3 | B19: 1700001 | C19: Коробка передач, раздаточная коробка и стояночный тормоз в сборе - снятие и установка | G19: 8.75 | H19: Обычный | I19: 1 | J19: 2433.33 | K19: н/ч | L19: 21291.64
A20: 4 | B20: 1700002 | C20: Рычаг переключения передач - снятие и установка | G20: 0.2 | H20: Обычный | I20: 1 | J20: 2433.33 | K20: н/ч | L20: 486.67
A21: 5 | B21: 1700003 | C21: Коробка передач - снятие и установка (при снятом агрегате) | G21: 2.04 | H21: Обычный | I21: 1 | J21: 2433.33 | K21: н/ч | L21: 4963.99
A22: 6 | B22: 1700004 | C22: Коробка передач - ремонт (без разборки вторичного вала) | G22: 3.9 | H22: Обычный | I22: 1 | J22: 2433.33 | K22: н/ч | L22: 9489.99
A23: 7 | B23: 1700009 | C23: Картер КП передний - снятие и установка | G23: 1.06 | H23: Обычный | I23: 1 | J23: 2433.33 | K23: н/ч | L23: 2579.33
A24: 8 | B24: 1700010 | C24: Вал вторичный - снятие и установка (при снятом переднем картере КП) | G24: 0.65 | H24: Обычный | I24: 1 | J24: 2433.33 | K24: н/ч | L24: 1581.66
A25: 9 | B25: 2800011 | C25: Брызговик КП и РК - снятие и установка. | G25: 0.4 | H25: Обычный | I25: 1 | J25: 2433.33 | K25: н/ч | L25: 973.33
A26: 10 | B26: 0 | C26: 0 | G26: 0 | H26: Обычный | I26: 0 | J26: 2433.33 | K26: н/ч | L26: 0
A27: 11 | B27: 0 | C27: 0 | G27: 0 | H27: Обычный | I27: 0 | J27: 2433.33 | K27: н/ч | L27: 0
A28: 12 | B28: 0 | C28: 0 | G28: 0 | H28: Обычный | I28: 0 | J28: 2433.33 | K28: н/ч | L28: 0
A29: 13 | B29: 0 | C29: 0 | G29: 0 | H29: Обычный | I29: 0 | J29: 0 | K29: н/ч | L29: 0
A30: 14 | B30: 0 | C30: 0 | G30: 0 | H30: Обычный | I30: 0 | J30: 0 | K30: н/ч | L30: 0
A31: 15 | B31: 0 | C31: 0 | G31: 0 | H31: Обычный | I31: 0 | J31: 0 | K31: н/ч | L31: 0
A32: 16 | B32: 0 | C32: 0 | G32: 0 | H32: Обычный | I32: 0 | J32: 0 | K32: н/ч | L32: 0
A33: 17 | B33: 0 | C33: 0 | G33: 0 | H33: Обычный | I33: 0 | J33: 0 | K33: н/ч | L33: 0
A34: 18 | B34: 0 | C34: 0 | G34: 0 | H34: Обычный | I34: 0 | J34: 0 | K34: н/ч | L34: 0
A35: 19 | B35: 0 | C35: 0 | G35: 0 | H35: Обычный | I35: 0 | J35: 0 | K35: н/ч | L35: 0
A36: 20 | B36: 0 | C36: 0 | G36: 0 | H36: Обычный | I36: 0 | J36: 0 | K36: н/ч | L36: 0
A37: 21 | B37: 0 | C37: 0 | G37: 0 | H37: Обычный | I37: 0 | J37: 0 | K37: н/ч | L37: 0
... A79: 63 | B79: 0 | C79: 0 | G79: 0 | H79: Обычный | I79: 0 | J79: 0 | K79: н/ч | L79: 0
A80: 64 | C80: 0 | G80: 0 | H80: Обычный | I80: 0 | J80: 0 | K80: н/ч | L80: 0
A81: 65 | C81: 0 | I81: 0 | J81: 0
A82: 66 | C82: 0 | I82: 0 | J82: 0
A83: 67 | C83: 0 | I83: 0 | J83: 0
A84: 68 | C84: 0 | I84: 0 | J84: 0
A85: 69 | C85: 0 | J85: 0
A86: 70 | C86: 0 | J86: 0
A87: 71 | C87: 0 | J87: 0
A88: 72 | C88: 0 | J88: 0
A89: 73 | C89: 0 | J89: 0
A90: 74 | C90: 0 | J90: 0
A91: 75 | C91: 0 | J91: 0
A92: 76 | C92: 0 | J92: 0
A93: 77 | C93: 0 | J93: 0
A94: 78 | C94: 0 | J94: 0
A95: 79 | C95: 0 | J95: 0
A96: 80 | C96: 0 | J96: 0
A97: 81 | C97: 0 | J97: 0
A98: 82 | J98: 0
A99: 83 | J99: 0
A100: 84 | J100: 0
A101: 85 | J101: 0
A102: 86 | J102: 0
A103: 87 | J103: 0
A104: 88 | J104: 0
A105: 89 | J105: 0
A106: 90 | J106: 0
A107: 91 | J107: 0
A108: 92 | J108: 0
A109: 93 | J109: 0
... A174: 158 | J174: 0
A175: 159
A176: 160
A177: 161
A178: 162
A179: 163
A180: 164
A181: 165
A182: 166
A183: 167
A184: 168
A185: 169
A186: 170
... A203: 187
A204: ИТОГО работ на сумму | L204: 43921.6
A207: Расходная Накладная к Заказ-наряду № | H207: 001-20 | I207: от | J207: 46174
A208: № | B208: Артикул | C208: Наименование | G208: Цена | I208: Кол-во | J208: Ед.изм | L208: Сумма
A209: 1 | B209: 53351 | C209: Масло трансмиссионное 75W90 1л, ТМ-4 (GL-4) (п/с) ЛУКОЙЛ | G209: 1535.59 | I209: 1 | J209: шт | L209: 1535.59
A210: 2 | B210: 53352 | C210: Масло трансмиссионное 75W90 4л, ТМ-4 GL-4 (п/с) ЛУКОЙЛ | G210: 5147.52 | I210: 1 | J210: шт | L210: 5147.52
A211: 3 | B211: 0 | C211: 0 | G211: 0 | I211: 0 | J211: шт | L211: 0
A212: 4 | B212: 0 | C212: 0 | G212: 0 | I212: 0 | J212: шт | L212: 0
A213: 5 | B213: 0 | C213: 0 | G213: 0 | I213: 0 | J213: шт | L213: 0
A214: 6 | B214: 0 | C214: 0 | G214: 0 | I214: 0 | J214: шт | L214: 0
A215: 7 | B215: 0 | C215: 0 | G215: 0 | I215: 0 | J215: шт | L215: 0
A216: 8 | B216: 0 | C216: 0 | G216: 0 | I216: 0 | J216: шт | L216: 0
A217: 9 | B217: 0 | C217: 0 | G217: 0 | I217: 0 | J217: шт | L217: 0
A218: 10 | B218: 0 | C218: 0 | G218: 0 | I218: 0 | J218: шт | L218: 0
A219: 11 | B219: 0 | C219: 0 | G219: 0 | I219: 0 | J219: шт | L219: 0
A220: 12 | B220: 0 | C220: 0 | G220: 0 | I220: 0 | J220: шт | L220: 0
A221: 13 | B221: 0 | C221: 0 | G221: 0 | I221: 0 | J221: шт | L221: 0
A222: 14 | B222: 0 | C222: 0 | G222: 0 | I222: 0 | J222: шт | L222: 0
... A253: 45 | B253: 0 | C253: 0 | G253: 0 | I253: 0 | J253: шт | L253: 0
A254: 46 | B254: 0 | C254: 0 | G254: 0 | J254: шт | L254: 0
A255: 47 | B255: 0 | C255: 0 | G255: 0 | J255: шт | L255: 0
...

Sheet 2M
B1: ПОСТАВЩИК: ООО ФИРМА "СИГНАЛ"
B2: адрес: 364031, Чеченская Республика, г.Грозный, ул. Жуковского, д. 18
C4: Заказ-наряд № 100517 от 05.06.2026
B6: Заказчик: Общество с ограниченной ответственностью «Концепт» | H6: адрес заказчика : 364024, ЧР г.Грозный, ул.Назарбаева, д.92, оф. 6-05
B7: Автомобиль : Лада Веста г/н Е 833 ОЕ/15
B9: Цена автомототранспортного средства, определяемая по соглашению сторон __________________
B11: Плательщик: Общество с ограниченной ответственностью «Концепт»
B12: ИНН 2014030866 адрес: телефоны: +7 (989) 9002252
N14: в валюте
N15: Руб
C17: Выполненные работы по заказ-наряду № 100517 от 05.06.2026
B19: № | C19: № кат. | D19: Наименование | I19: Кол. оп. | J19: Цена | K19: Норма | L19: н/ч | M19: Всего | N19: в т.ч. НДС
B20: 1 | C20: 2 | D20: 3 | I20: 4 | J20: 5 | K20: 6 | L20: 7 | M20: 8 | N20: 9
B21: 1 | D21: Ремонт ДВС | I21: 1 | J21: 25000 | K21: 1 | L21: Рубль | M21: =J21*I21 -> 25000 | N21: =M21*22/122 -> 4508.1967
B22: 2 | D22: Мойка ДВС в разобранном виде | I22: 1 | J22: 4000 | K22: 1 | L22: Рубль | M22: =J22*I22 -> 4000 | N22: =M22*22/122 -> 721.31148
B23: 3 | D23: Расточка блока цилиндров | I23: 1 | J23: 6000 | K23: 1 | L23: Рубль | M23: =J23*I23 -> 6000 | N23: =M23*22/122 -> 1081.9672
B24: 4 | D24: Ремонт ГБЦ | I24: 1 | J24: 4500 | K24: 1 | L24: Рубль | M24: =J24*I24 -> 4500 | N24: =M24*22/122 -> 811.47541
B25: 5 | D25: Замена подшипника опоры амортизатора | I25: 2 | J25: 1800 | K25: 1 | L25: Рубль | M25: =J25*I25 -> 3600 | N25: =M25*22/122 -> 649.18033
B26: 6 | D26: Замена пер-х торм-х колодок | I26: 1 | J26: 600 | K26: 1 | L26: Рубль | M26: =J26*I26 -> 600 | N26: =M26*22/122 -> 108.19672
B27: 7 | D27: Диагностика ДВС | I27: 1 | J27: 1500 | K27: 1 | L27: Рубль | M27: =J27*I27 -> 1500 | N27: =M27*22/122 -> 270.4918
B28: Итого работ: | I28: 8 | J28: на сумму: | M28: =M21+M22+M23+M24+M25+M26+M27 -> 45200 | N28: =M28*22/122 -> 8150.8197
B30: Сорок пять тысяч двести рублей 00 копеек.
C32: Расходная накладная к заказ-наряду № 100517 от 05.06.2026
B34: № | C34: № кат. | D34: Наименование | J34: Кол-во | K34: Ед.изм. | L34: Цена | M34: Всего | N34: в т.ч. НДС
B35: 1 | C35: 2 | D35: 3 | J35: 4 | K35: 5 | L35: 6 | M35: 7 | N35: 8
B36: 1 | C36: 21127.100401557.WPR01 | D36: Поршень ВАЗ 21126 Priora (82.5 A, 1.6L 16V) с пальцем Federal Reserve (кт 4 шт) | J36: 1 | K36: шт | L36: 4500 | M36: =L36*J36 -> 4500 | N36: =M36*22/122 -> 811.47541
B37: 2 | C37: 2112100702603 | D37: Колпачок маслосъемный ВАЗ 2110-12 (16V) Federal Reserve кт 16 шт. | J37: 1 | K37: шт | L37: 800 | M37: =L37*J37 -> 800 | N37: =M37*22/122 -> 144.2623
B38: 3 | C38: 813365310 | D38: Сальник распредвала/коленвала передний Lada/Лада Приора, 2170 Victor Reinz (28х42х7) | J38: 3 | K38: шт | L38: 150 | M38: =L38*J38 -> 450 | N38: =M38*22/122 -> 81.147541
B39: 4 | C39: 2108-1005160-01 | D39: Сальник коленвала дв.406 задний (80х100х10) (Rubena) | J39: 1 | K39: шт | L39: 500 | M39: =L39*J39 -> 500 | N39: =M39*22/122 -> 90.163934
B40: 5 | C40: 11226 | D40: Герметик-прокладка силиконовый АВТОСИЛ черный | J40: 1 | K40: шт | L40: 100 | M40: =L40*J40 -> 100 | N40: =M40*22/122 -> 18.032787
B41: 6 | D41: Опора ресивера ВАЗ 2112 16 кл. | J41: 2 | K41: шт | L41: 150 | M41: =L41*J41 -> 300 | N41: =M41*22/122 -> 54.098361
B42: 7 | C42: 21081010075Р | D42: Кольцо ВАЗ-2108 маслоприемника уплотнительное БРТ | J42: 1 | K42: шт | L42: 30 | M42: =L42*J42 -> 30 | N42: =M42*22/122 -> 5.4098361
B43: 8 | C43: 2112-1004081 | D43: Форсунки масляные на ВАЗ 2112-2170, (к-т 4 шт) | J43: 1 | K43: кт | L43: 500 | M43: =L43*J43 -> 500 | N43: =M43*22/122 -> 90.163934
B44: 9 | D44: Кольцо уплотнительное форсунок ВАЗ 106 л.с. (кт 8 шт) | J44: 1 | K44: кт | L44: 100 | M44: =L44*J44 -> 100 | N44: =M44*22/122 -> 18.032787
B45: 10 | D45: Вкладыши ВАЗ-11194,21116-21127 Приора шатунные d+0.00 ДАЙДО МЕТАЛЛ РУСЬ | J45: 1 | K45: кт | L45: 600 | M45: =L45*J45 -> 600 | N45: =M45*22/122 -> 108.19672
B46: 11 | C46: K015631XS | D46: Комплект ГРМ Приора, Лада Ларгус, Веста, Х Рей, GATES K015631XS (дв. ВАЗ, 16 клапанов) | J46: 1 | K46: кт | L46: 6900 | M46: =L46*J46 -> 6900 | N46: =M46*22/122 -> 1244.2623
B47: 12 | C47: FR518 | D47: Фланцевый герметик в шприце LOCTITE FR518 50 Federal Reserve | J47: 1 | K47: шт | L47: 300 | M47: =L47*J47 -> 300 | N47: =M47*22/122 -> 54.098361
B48: 13 | C48: 2112-1014056Р | D48: Шланг сапуна вытяжной ВАЗ-2112 вентиляции картера БРТ низ. | J48: 1 | K48: шт | L48: 270 | M48: =L48*J48 -> 270 | N48: =M48*22/122 -> 48.688525
B49: 14 | C49: EK.2.7 | D49: Прокладка приемной трубы ВАЗ 21114, 1118, 2170, 2190 металл с перфорацией (треугольник) | J49: 1 | K49: шт | L49: 100 | M49: =L49*J49 -> 100 | N49: =M49*22/122 -> 18.032787
B50: 15 | C50: 2108-012 М | D50: Набор прокладок на двигатель ВАЗ 2108 малый с герметиком "БЦМ" | J50: 1 | K50: шт | L50: 350 | M50: =L50*J50 -> 350 | N50: =M50*22/122 -> 63.114754
B51: 16 | C51: EK.2.2 | D51: Прокладка коллектора 2110-2170 дв1,6 16 кл, 1118 дв1,4 16 кл выпускн. металл Gallant | J51: 1 | K51: шт | L51: 250 | M51: =L51*J51 -> 250 | N51: =M51*22/122 -> 45.081967
B52: 17 | C52: GZ1015002 | D52: Прокладка ГБЦ метал. для а м ВАЗ 2170 1.6 (d 82 мм.) TRIALLI | J52: 1 | K52: шт | L52: 1050 | M52: =L52*J52 -> 1050 | N52: =M52*22/122 -> 189.34426
B53: 18 | C53: 20361 | D53: Прокладки ресивера и дроссельной заслонки ВАЗ 2170, 2190, Vesta двигатель 21127 ROSTECO | J53: 1 | K53: шт | L53: 350 | M53: =L53*J53 -> 350 | N53: =M53*22/122 -> 63.114754
B54: 19 | C54: 1376000 | D54: Подшипник опоры стойки KRAMME для а м LADA Vesta | J54: 2 | K54: шт | L54: 1625 | M54: =L54*J54 -> 3250 | N54: =M54*22/122 -> 586.06557
B55: 20 | C55: LF105 | D55: Фильтр масляный LADA 08-112 FINWHALE | J55: 1 | K55: шт | L55: 400 | M55: =L55*J55 -> 400 | N55: =M55*22/122 -> 72.131148
B56: 21 | C56: 3705304 | D56: Масло моторное Лукойл Люкс 10W-40 (4л) | J56: 1 | K56: шт | L56: 1150 | M56: =L56*J56 -> 1150 | N56: =M56*22/122 -> 207.37705
B57: 22 | C57: 614503 | D57: Антифриз Sintec LUXE G12+, 5 кг, красный | J57: 1 | K57: шт | L57: 1000 | M57: =L57*J57 -> 1000 | N57: =M57*22/122 -> 180.32787
B58: 23 | C58: 4008 | D58: Смазка многоцелевая RC-40, 210 мл BiBiCare | J58: 1 | K58: шт | L58: 250 | M58: =L58*J58 -> 250 | N58: =M58*22/122 -> 45.081967
B59: 24 | C59: 732805-50-4 | D59: Кольца поршневые SM 82,50 Priora TITANIUM | J59: 1 | K59: кт | L59: 6600 | M59: =L59*J59 -> 6600 | N59: =M59*22/122 -> 1190.1639
B60: 25 | C60: 2108-1000102-01 | D60: Вкладыши 2108 (коренные) 0,00 "ЗМЗ-Дайдо" | J60: 1 | K60: кт | L60: 850 | M60: =L60*J60 -> 850 | N60: =M60*22/122 -> 153.27869
B61: 26 | C61: SP1564 | D61: Колодки тормозные передние Lada Vesta SANGSIN (HI-Q) | J61: 1 | K61: кт | L61: 1650 | M61: =L61*J61 -> 1650 | N61: =M61*22/122 -> 297.54098
B62: Итого материалов: | J62: 28 | K62: на сумму: | M62: =M36+M37+M38+M39+M40+M42+M43+M44+M45+M46+M47+M48+M49++M50+M51+M52+M53++++M54+M55++M56+M57+M58+M59+M60+M61+M41 -> 32600 | N62: =M62*22/122 -> 5878.6885
B64: Тридцать две тысячи шестьсот рублей 00 копеек
L66: Итого по заказ-наряду : | M66: =M28+M62 -> 77800 | N66: =M66*22/122 -> 14029.508
B68: Всего по заказ-наряду: Семьдесят семь тысяч восемьсот рублей 00 копеек, в т.ч. НДС 22%.
J71: Мастер _____________________ | K71: Механик СТО/
C73: Гарантии: Гарантия на работы: слесарные - 30 дней, электрические - 30 дней, оригинальные з/ч - 30 дней, з/ч, связанные с электрооборудованием, подачей топлива и системой впрыска - гарантии нет, неоригинальные з/ч - гарантии нет. Гарантийные обязательства на работы выполняются фирмой только при предъявлении акта приемки автомобиля и техпаспорта (доверенности).
B77: Дата: 05.06.2026 | J77: Заказчик ______________________ | K77: /Общество с ограниченной ответственностью «Концепт»/
J79: Плательщик ______________________ | K79: /Общество с ограниченной ответственностью «Концепт»/
B81: Причина обращения:

Sheet report
A1: Номер п/п | B1: Цена н/ч | C1: Марка/Модель | D1: ГЗН | E1: VIN | F1: Пробег | G1: Год вып. | H1: Дата | I1: Гараж. Номер | J1: Номер/месяц | K1: Номер ЗН | L1: Номер/год | M1: Номер ММ | N1: РАБОТЫ | O1: З/Ч | P1: ИТОГО РАСХОД | Q1: РАБОТЫ | R1: З/Ч | S1: ИТОГО ВЫРУЧКА | T1: Рубль | U1: % | V1: Рубль | W1: % | X1: ВАЛОВАЯ ПРИБЫЛЬ | Y1: %
A2: 1 | C2: =spisok!B2 -> УАЗ UAZ PATRIOT 3163 | D2: =spisok!C2 -> О201МК126 | E2: =spisok!D2 -> XTT316300R1000091 | F2: =spisok!G2 -> 4116 | G2: =spisok!F2 -> 2023 | H2: =spisok!H2 -> 46174 | I2: =spisok!E2 -> 106-81 | J2: 1 | K2: 001-10 | L2: 1 | P2: =Таблица6[[#This Row],[Столбец11]]+Таблица6[[#This Row],[Столбец12]] -> 0 | S2: =Таблица6[[#This Row],[Столбец14]]+Таблица6[[#This Row],[Столбец15]] -> 0 | T2: =Таблица6[[#This Row],[Столбец14]]-Таблица6[[#This Row],[Столбец11]] -> 0 | U2: =Таблица6[[#This Row],[Столбец17]]/Таблица6[[#This Row],[Столбец11]] -> #DIV/0! | V2: =Таблица6[[#This Row],[Столбец15]]-Таблица6[[#This Row],[Столбец12]] -> 0 | W2: =Таблица6[[#This Row],[Столбец19]]/Таблица6[[#This Row],[Столбец12]] -> #DIV/0! | X2: =Таблица6[[#This Row],[Столбец16]]-Таблица6[[#This Row],[Столбец13]] -> 0 | Y2: =Таблица6[[#This Row],[Столбец21]]/Таблица6[[#This Row],[Столбец13]] -> #DIV/0!
A3: 2 | C3: =spisok!B3 -> LADA VESTA GFL110 | D3: =spisok!C3 -> Е833ОЕ15 | E3: =spisok!D3 -> XTAGFL110LY378838 | F3: =spisok!G3 -> 237856 | G3: =spisok!F3 -> 2019 | H3: =spisok!H3 -> 46175 | I3: =spisok!E3 -> 104-61 | J3: 2 | K3: 002-10 | L3: 2 | P3: =Таблица6[[#This Row],[Столбец11]]+Таблица6[[#This Row],[Столбец12]] -> 0 | X3: =Таблица6[[#This Row],[Столбец16]]-Таблица6[[#This Row],[Столбец13]] -> 0 | Y3: =Таблица6[[#This Row],[Столбец21]]/Таблица6[[#This Row],[Столбец13]] -> #DIV/0!
A4: 3 | C4: =spisok!B4 -> ЕСАУЛ 394511-03 | D4: =spisok!C4 -> В723УУ15 | E4: =spisok!D4 -> X8939451CG0AK5370 | F4: =spisok!G4 -> 142626 | G4: =spisok!F4 -> 2016 | H4: =spisok!H4 -> 46175 | I4: =spisok!E4 -> 103-30 | J4: 3 | K4: ="00"&TEXT($L4,"0")&"-10" -> 003-10 | L4: 3 | P4: =Таблица6[[#This Row],[Столбец11]]+Таблица6[[#This Row],[Столбец12]] -> 0 | X4: =Таблица6[[#This Row],[Столбец16]]-Таблица6[[#This Row],[Столбец13]] -> 0 | Y4: =Таблица6[[#This Row],[Столбец21]]/Таблица6[[#This Row],[Столбец13]] -> #DIV/0!
A5: 4 | C5: =spisok!B5 -> LADA VESTA GFL110 | D5: =spisok!C5 -> Е378ОУ15 | E5: =spisok!D5 -> XTAGFL110LY443715 | F5: =spisok!G5 -> 209733 | G5: =spisok!F5 -> 2020 | H5: =spisok!H5 -> 46176 | I5: =spisok!E5 -> 105-48 | J5: 4 | K5: ="00"&TEXT($L5,"0")&"-10" -> 004-10 | L5: 4 | P5: =Таблица6[[#This Row],[Столбец11]]+Таблица6[[#This Row],[Столбец12]] -> 0 | X5: =Таблица6[[#This Row],[Столбец16]]-Таблица6[[#This Row],[Столбец13]] -> 0 | Y5: =Таблица6[[#This Row],[Столбец21]]/Таблица6[[#This Row],[Столбец13]] -> #DIV/0!
A6: 5 | C6: =spisok!B6 -> ЕСАУЛ 394511-03 | D6: =spisok!C6 -> Е506НТ15 | E6: =spisok!D6 -> X8939451CK0AK5346 | F6: =spisok!G6 -> 138364 | G6: =spisok!F6 -> 2019 | H6: =spisok!H6 -> 46176 | I6: =spisok!E6 -> 104-91 | J6: 5 | K6: ="00"&TEXT($L6,"0")&"-10" -> 005-10 | L6: 5 | P6: =Таблица6[[#This Row],[Столбец11]]+Таблица6[[#This Row],[Столбец12]] -> 0 | X6: =Таблица6[[#This Row],[Столбец16]]-Таблица6[[#This Row],[Столбец13]] -> 0 | Y6: =Таблица6[[#This Row],[Столбец21]]/Таблица6[[#This Row],[Столбец13]] -> #DIV/0!
A7: 6 | C7: =spisok!B7 -> LADA VESTA GFL110 | D7: =spisok!C7 -> В211ОХ15 | E7: =spisok!D7 -> XTAGFL110JY197249 | F7: =spisok!G7 -> 320689 | G7: =spisok!F7 -> 2018 | H7: =spisok!H7 -> 46176 | I7: =spisok!E7 -> 103-75 | J7: 6 | K7: ="00"&TEXT($L7,"0")&"-10" -> 006-10 | L7: 6 | P7: =Таблица6[[#This Row],[Столбец11]]+Таблица6[[#This Row],[Столбец12]] -> 0 | X7: =Таблица6[[#This Row],[Столбец16]]-Таблица6[[#This Row],[Столбец13]] -> 0 | Y7: =Таблица6[[#This Row],[Столбец21]]/Таблица6[[#This Row],[Столбец13]] -> #DIV/0!
A8: 7 | C8: =spisok!B8 -> TOYOTA CAMRY ASV70L-RE | D8: =spisok!C8 -> Е778РА15 | E8: =spisok!D8 -> XW7BF4HK905167068 | F8: =spisok!G8 -> 40010 | G8: =spisok!F8 -> 2020 | H8: =spisok!H8 -> 46176 | I8: =spisok!E8 -> 106-39 | J8: 7 | K8: ="00"&TEXT($L8,"0")&"-10" -> 007-10 | L8: 7 | P8: =Таблица6[[#This Row],[Столбец11]]+Таблица6[[#This Row],[Столбец12]] -> 0 | X8: =Таблица6[[#This Row],[Столбец16]]-Таблица6[[#This Row],[Столбец13]] -> 0 | Y8: =Таблица6[[#This Row],[Столбец21]]/Таблица6[[#This Row],[Столбец13]] -> #DIV/0!
A9: 8 | C9: =spisok!B9 -> ЛАДА ГРАНТА 219010 | D9: =spisok!C9 -> А287АР126 | E9: =spisok!D9 -> XTA219010E0256411 | F9: =spisok!G9 -> 356419 | G9: =spisok!F9 -> 2014 | H9: =spisok!H9 -> 46177 | I9: =spisok!E9 -> 106-34 | J9: 8 | K9: ="00"&TEXT($L9,"0")&"-10" -> 008-10 | L9: 8 | P9: =Таблица6[[#This Row],[Столбец11]]+Таблица6[[#This Row],[Столбец12]] -> 0 | X9: =Таблица6[[#This Row],[Столбец16]]-Таблица6[[#This Row],[Столбец13]] -> 0 | Y9: =Таблица6[[#This Row],[Столбец21]]/Таблица6[[#This Row],[Столбец13]] -> #DIV/0!
A10: 9 | C10: =spisok!B10 -> LADA 4x4 213100 | D10: =spisok!C10 -> О 0708/15 | E10: =spisok!D10 -> XTA213100L0213886 | F10: =spisok!G10 -> 126256 | G10: =spisok!F10 -> 2019 | H10: =spisok!H10 -> 46177 | I10: =spisok!E10 -> 104-90 | J10: 9 | K10: ="00"&TEXT($L10,"0")&"-10" -> 009-10 | L10: 9 | P10: =Таблица6[[#This Row],[Столбец11]]+Таблица6[[#This Row],[Столбец12]] -> 0 | X10: =Таблица6[[#This Row],[Столбец16]]-Таблица6[[#This Row],[Столбец13]] -> 0 | Y10: =Таблица6[[#This Row],[Столбец21]]/Таблица6[[#This Row],[Столбец13]] -> #DIV/0!
A11: 10 | C11: =spisok!B11 -> LADA PRIORA 217050 | D11: =spisok!C11 -> Т158АЕ15 | E11: =spisok!D11 -> XTA217050G0529350 | F11: =spisok!G11 -> 275410 | G11: =spisok!F11 -> 2015 | H11: =spisok!H11 -> 46177 | I11: =spisok!E11 -> 102-89 | J11: 10 | K11: ="00"&TEXT($L11,"0")&"-10" -> 0010-10 | L11: 10 | P11: =Таблица6[[#This Row],[Столбец11]]+Таблица6[[#This Row],[Столбец12]] -> 0 | X11: =Таблица6[[#This Row],[Столбец16]]-Таблица6[[#This Row],[Столбец13]] -> 0 | Y11: =Таблица6[[#This Row],[Столбец21]]/Таблица6[[#This Row],[Столбец13]] -> #DIV/0!
A12: 11 | C12: =spisok!B12 -> ТОЙОТА КАМРИ | D12: =spisok!C12 -> Е898НТ15 | E12: =spisok!D12 -> XW7BF4FK10S155841 | F12: =spisok!G12 -> 176666 | G12: =spisok!F12 -> 2017 | H12: =spisok!H12 -> 46177 | I12: =spisok!E12 -> 103-69 | J12: 11 | K12: ="00"&TEXT($L12,"0")&"-10" -> 0011-10 | L12: 11 | P12: =Таблица6[[#This Row],[Столбец11]]+Таблица6[[#This Row],[Столбец12]] -> 0 | X12: =Таблица6[[#This Row],[Столбец16]]-Таблица6[[#This Row],[Столбец13]] -> 0 | Y12: =Таблица6[[#This Row],[Столбец21]]/Таблица6[[#This Row],[Столбец13]] -> #DIV/0!
A13: 12 | C13: =spisok!B13 -> УАЗ 396221 3163 | D13: =spisok!C13 -> Е312РА15 | E13: =spisok!D13 -> XTT316300M1002503 | F13: =spisok!G13 -> 108974 | G13: =spisok!F13 -> 2020 | H13: =spisok!H13 -> 46178 | I13: =spisok!E13 -> 105-57 | J13: 12 | K13: ="00"&TEXT($L13,"0")&"-10" -> 0012-10 | L13: 12 | P13: =Таблица6[[#This Row],[Столбец11]]+Таблица6[[#This Row],[Столбец12]] -> 0 | X13: =Таблица6[[#This Row],[Столбец16]]-Таблица6[[#This Row],[Столбец13]] -> 0 | Y13: =Таблица6[[#This Row],[Столбец21]]/Таблица6[[#This Row],[Столбец13]] -> #DIV/0!
A14: 13 | C14: =spisok!B14 -> ЕСАУЛ 394511-03 | D14: =spisok!C14 -> Е368НТ15 | E14: =spisok!D14 -> X8939451CK0AK5323 | F14: =spisok!G14 -> 138585 | G14: =spisok!F14 -> 2019 | H14: =spisok!H14 -> 46178 | I14: =spisok!E14 -> 104-95 | J14: 13 | K14: ="00"&TEXT($L14,"0")&"-10" -> 0013-10 | L14: 13 | P14: =Таблица6[[#This Row],[Столбец11]]+Таблица6[[#This Row],[Столбец12]] -> 0 | X14: =Таблица6[[#This Row],[Столбец16]]-Таблица6[[#This Row],[Столбец13]] -> 0 | Y14: =Таблица6[[#This Row],[Столбец21]]/Таблица6[[#This Row],[Столбец13]] -> #DIV/0!
A15: 14 | C15: =spisok!B15 -> ЕСАУЛ 394511-03 | D15: =spisok!C15 -> Е546НТ15 | E15: =spisok!D15 -> X8939451CK0AK5318 | F15: =spisok!G15 -> 132853 | G15: =spisok!F15 -> 2019 | H15: =spisok!H15 -> 46178 | I15: =spisok!E15 -> 104-96 | J15: 14 | K15: ="00"&TEXT($L15,"0")&"-10" -> 0014-10 | L15: 14 | P15: =Таблица6[[#This Row],[Столбец11]]+Таблица6[[#This Row],[Столбец12]] -> 0 | X15: =Таблица6[[#This Row],[Столбец16]]-Таблица6[[#This Row],[Столбец13]] -> 0 | Y15: =Таблица6[[#This Row],[Столбец21]]/Таблица6[[#This Row],[Столбец13]] -> #DIV/0!
... A31: 30 | C31: =spisok!B31 -> УАЗ ПАТРИОТ | D31: =spisok!C31 -> В787ОХ15 | E31: =spisok!D31 -> XTT316300J1023444 | F31: =spisok!G31 -> 232487 | G31: =spisok!F31 -> 2018 | H31: =spisok!H31 -> 46184 | I31: =spisok!E31 -> 103-91 | J31: 30 | K31: ="00"&TEXT($L31,"0")&"-10" -> 0030-10 | L31: 30 | P31: =Таблица6[[#This Row],[Столбец11]]+Таблица6[[#This Row],[Столбец12]] -> 0 | X31: =Таблица6[[#This Row],[Столбец16]]-Таблица6[[#This Row],[Столбец13]] -> 0 | Y31: =Таблица6[[#This Row],[Столбец21]]/Таблица6[[#This Row],[Столбец13]] -> #DIV/0!
A32: 31 | C32: =spisok!B32 -> ЛАДА 213100 4х4 | D32: =spisok!C32 -> В473ЕР126 | E32: =spisok!D32 -> XTA213100G0177506 | F32: =spisok!G32 -> 283293 | G32: =spisok!F32 -> 2015 | H32: =spisok!H32 -> 46184 | I32: =spisok!E32 -> 106-63 | J32: 31 | K32: ="00"&TEXT($L32,"0")&"-10" -> 0031-10 | L32: 31
A33: 32 | C33: =spisok!B33 -> VOLKSWAGEN MULTIVEN | D33: =spisok!C33 -> С488ВС15 | E33: =spisok!D33 -> XW8ZZZ7HZDG001346 | F33: =spisok!E33 -> 101-90 | G33: =spisok!F33 -> 2013 | H33: =spisok!G33 -> 302107 | I33: =spisok!H33 -> 46184 | J33: 32 | K33: ="00"&TEXT($L33,"0")&"-10" -> 0032-10 | L33: 32 | P33: =Таблица6[[#This Row],[Столбец11]]+Таблица6[[#This Row],[Столбец12]] -> 0 | X33: =Таблица6[[#This Row],[Столбец16]]-Таблица6[[#This Row],[Столбец13]] -> 0 | Y33: =Таблица6[[#This Row],[Столбец21]]/Таблица6[[#This Row],[Столбец13]] -> #DIV/0!
A34: 33 | C34: =spisok!B34 -> ЕСАУЛ 394511-03 | D34: =spisok!C34 -> Е368НТ15 | E34: =spisok!D34 -> X8939451CK0AK5323 | F34: =spisok!E34 -> 104-95 | G34: =spisok!F34 -> 2019 | H34: =spisok!G34 -> 139503 | I34: =spisok!H34 -> 46185 | J34: 33 | K34: ="00"&TEXT($L34,"0")&"-10" -> 0033-10 | L34: 33 | P34: =Таблица6[[#This Row],[Столбец11]]+Таблица6[[#This Row],[Столбец12]] -> 0 | X34: =Таблица6[[#This Row],[Столбец16]]-Таблица6[[#This Row],[Столбец13]] -> 0 | Y34: =Таблица6[[#This Row],[Столбец21]]/Таблица6[[#This Row],[Столбец13]] -> #DIV/0!
A35: 34 | J35: 34 | K35: ="00"&TEXT($L35,"0")&"-10" -> 0034-10 | L35: 34 | P35: =Таблица6[[#This Row],[Столбец11]]+Таблица6[[#This Row],[Столбец12]] -> 0 | X35: =Таблица6[[#This Row],[Столбец16]]-Таблица6[[#This Row],[Столбец13]] -> 0 | Y35: =Таблица6[[#This Row],[Столбец21]]/Таблица6[[#This Row],[Столбец13]] -> #DIV/0!
J36: 35 | K36: ="00"&TEXT($L36,"0")&"-10" -> 0035-10 | L36: 35 | P36: =Таблица6[[#This Row],[Столбец11]]+Таблица6[[#This Row],[Столбец12]] -> 0 | X36: =Таблица6[[#This Row],[Столбец16]]-Таблица6[[#This Row],[Столбец13]] -> 0 | Y36: =Таблица6[[#This Row],[Столбец21]]/Таблица6[[#This Row],[Столбец13]] -> #DIV/0!
A37: 36 | J37: 36 | K37: ="00"&TEXT($L37,"0")&"-10" -> 0036-10 | L37: 36 | P37: =Таблица6[[#This Row],[Столбец11]]+Таблица6[[#This Row],[Столбец12]] -> 0 | X37: =Таблица6[[#This Row],[Столбец16]]-Таблица6[[#This Row],[Столбец13]] -> 0 | Y37: =Таблица6[[#This Row],[Столбец21]]/Таблица6[[#This Row],[Столбец13]] -> #DIV/0!
A38: 37 | J38: 37 | K38: ="00"&TEXT($L38,"0")&"-10" -> 0037-10 | L38: 37 | P38: =Таблица6[[#This Row],[Столбец11]]+Таблица6[[#This Row],[Столбец12]] -> 0 | X38: =Таблица6[[#This Row],[Столбец16]]-Таблица6[[#This Row],[Столбец13]] -> 0 | Y38: =Таблица6[[#This Row],[Столбец21]]/Таблица6[[#This Row],[Столбец13]] -> #DIV/0!
A39: 38 | J39: 38 | K39: ="00"&TEXT($L39,"0")&"-10" -> 0038-10 | L39: 38 | P39: =Таблица6[[#This Row],[Столбец11]]+Таблица6[[#This Row],[Столбец12]] -> 0 | X39: =Таблица6[[#This Row],[Столбец16]]-Таблица6[[#This Row],[Столбец13]] -> 0 | Y39: =Таблица6[[#This Row],[Столбец21]]/Таблица6[[#This Row],[Столбец13]] -> #DIV/0!
A40: 39 | J40: 39 | K40: ="00"&TEXT($L40,"0")&"-10" -> 0039-10 | L40: 39 | P40: =Таблица6[[#This Row],[Столбец11]]+Таблица6[[#This Row],[Столбец12]] -> 0 | X40: =Таблица6[[#This Row],[Столбец16]]-Таблица6[[#This Row],[Столбец13]] -> 0 | Y40: =Таблица6[[#This Row],[Столбец21]]/Таблица6[[#This Row],[Столбец13]] -> #DIV/0!
A41: 40 | J41: 40 | K41: ="00"&TEXT($L41,"0")&"-10" -> 0040-10 | L41: 40 | P41: =Таблица6[[#This Row],[Столбец11]]+Таблица6[[#This Row],[Столбец12]] -> 0 | X41: =Таблица6[[#This Row],[Столбец16]]-Таблица6[[#This Row],[Столбец13]] -> 0 | Y41: =Таблица6[[#This Row],[Столбец21]]/Таблица6[[#This Row],[Столбец13]] -> #DIV/0!
A42: 41 | J42: 41 | K42: ="00"&TEXT($L42,"0")&"-10" -> 0041-10 | L42: 41 | P42: =Таблица6[[#This Row],[Столбец11]]+Таблица6[[#This Row],[Столбец12]] -> 0 | X42: =Таблица6[[#This Row],[Столбец16]]-Таблица6[[#This Row],[Столбец13]] -> 0 | Y42: =Таблица6[[#This Row],[Столбец21]]/Таблица6[[#This Row],[Столбец13]] -> #DIV/0!
A43: 42 | J43: 42 | K43: ="00"&TEXT($L43,"0")&"-10" -> 0042-10 | L43: 42 | P43: =Таблица6[[#This Row],[Столбец11]]+Таблица6[[#This Row],[Столбец12]] -> 0 | X43: =Таблица6[[#This Row],[Столбец16]]-Таблица6[[#This Row],[Столбец13]] -> 0 | Y43: =Таблица6[[#This Row],[Столбец21]]/Таблица6[[#This Row],[Столбец13]] -> #DIV/0!
A44: 43 | J44: 43 | K44: ="00"&TEXT($L44,"0")&"-10" -> 0043-10 | L44: 43 | P44: =Таблица6[[#This Row],[Столбец11]]+Таблица6[[#This Row],[Столбец12]] -> 0 | X44: =Таблица6[[#This Row],[Столбец16]]-Таблица6[[#This Row],[Столбец13]] -> 0 | Y44: =Таблица6[[#This Row],[Столбец21]]/Таблица6[[#This Row],[Столбец13]] -> #DIV/0!
A45: 44 | J45: 1 | K45: ="00"&TEXT($L45,"0")&"-10" -> 0044-10 | L45: 44 | P45: =Таблица6[[#This Row],[Столбец11]]+Таблица6[[#This Row],[Столбец12]] -> 0 | X45: =Таблица6[[#This Row],[Столбец16]]-Таблица6[[#This Row],[Столбец13]] -> 0 | Y45: =Таблица6[[#This Row],[Столбец21]]/Таблица6[[#This Row],[Столбец13]] -> #DIV/0!
A46: 45 | J46: 2 | K46: ="00"&TEXT($L46,"0")&"-10" -> 0045-10 | L46: 45 | P46: =Таблица6[[#This Row],[Столбец11]]+Таблица6[[#This Row],[Столбец12]] -> 0 | X46: =Таблица6[[#This Row],[Столбец16]]-Таблица6[[#This Row],[Столбец13]] -> 0 | Y46: =Таблица6[[#This Row],[Столбец21]]/Таблица6[[#This Row],[Столбец13]] -> #DIV/0!
A47: 46 | J47: 3 | K47: ="00"&TEXT($L47,"0")&"-10" -> 0046-10 | L47: 46 | P47: =Таблица6[[#This Row],[Столбец11]]+Таблица6[[#This Row],[Столбец12]] -> 0 | X47: =Таблица6[[#This Row],[Столбец16]]-Таблица6[[#This Row],[Столбец13]] -> 0 | Y47: =Таблица6[[#This Row],[Столбец21]]/Таблица6[[#This Row],[Столбец13]] -> #DIV/0!
A48: 47 | J48: 4 | K48: ="00"&TEXT($L48,"0")&"-10" -> 0047-10 | L48: 47 | P48: =Таблица6[[#This Row],[Столбец11]]+Таблица6[[#This Row],[Столбец12]] -> 0 | X48: =Таблица6[[#This Row],[Столбец16]]-Таблица6[[#This Row],[Столбец13]] -> 0 | Y48: =Таблица6[[#This Row],[Столбец21]]/Таблица6[[#This Row],[Столбец13]] -> #DIV/0!
... A91: 90 | J91: 16 | K91: ="00"&TEXT($L91,"0")&"-10" -> 0090-10 | L91: 90 | P91: =Таблица6[[#This Row],[Столбец11]]+Таблица6[[#This Row],[Столбец12]] -> 0 | X91: =Таблица6[[#This Row],[Столбец16]]-Таблица6[[#This Row],[Столбец13]] -> 0 | Y91: =Таблица6[[#This Row],[Столбец21]]/Таблица6[[#This Row],[Столбец13]] -> #DIV/0!
A92: 91 | J92: 17 | K92: ="00"&TEXT($L92,"0")&"-10" -> 0091-10 | L92: 91 | X92: =Таблица6[[#This Row],[Столбец16]]-Таблица6[[#This Row],[Столбец13]] -> 0
A93: 92 | J93: 18 | K93: ="00"&TEXT($L93,"0")&"-10" -> 0092-10 | L93: 92 | P93: =Таблица6[[#This Row],[Столбец11]]+Таблица6[[#This Row],[Столбец12]] -> 0 | X93: =Таблица6[[#This Row],[Столбец16]]-Таблица6[[#This Row],[Столбец13]] -> 0 | Y93: =Таблица6[[#This Row],[Столбец21]]/Таблица6[[#This Row],[Столбец13]] -> #DIV/0!
A94: 93 | J94: 19 | K94: ="00"&TEXT($L94,"0")&"-10" -> 0093-10 | L94: 93 | P94: =Таблица6[[#This Row],[Столбец11]]+Таблица6[[#This Row],[Столбец12]] -> 0 | X94: =Таблица6[[#This Row],[Столбец16]]-Таблица6[[#This Row],[Столбец13]] -> 0 | Y94: =Таблица6[[#This Row],[Столбец21]]/Таблица6[[#This Row],[Столбец13]] -> #DIV/0!
A95: 94 | J95: 20 | K95: ="00"&TEXT($L95,"0")&"-10" -> 0094-10 | L95: 94 | P95: =Таблица6[[#This Row],[Столбец11]]+Таблица6[[#This Row],[Столбец12]] -> 0 | X95: =Таблица6[[#This Row],[Столбец16]]-Таблица6[[#This Row],[Столбец13]] -> 0 | Y95: =Таблица6[[#This Row],[Столбец21]]/Таблица6[[#This Row],[Столбец13]] -> #DIV/0!
A96: 95 | J96: 21 | K96: ="00"&TEXT($L96,"0")&"-10" -> 0095-10 | L96: 95 | P96: =Таблица6[[#This Row],[Столбец11]]+Таблица6[[#This Row],[Столбец12]] -> 0 | X96: =Таблица6[[#This Row],[Столбец16]]-Таблица6[[#This Row],[Столбец13]] -> 0 | Y96: =Таблица6[[#This Row],[Столбец21]]/Таблица6[[#This Row],[Столбец13]] -> #DIV/0!
A97: 96 | J97: 22 | K97: ="00"&TEXT($L97,"0")&"-10" -> 0096-10 | L97: 96 | P97: =Таблица6[[#This Row],[Столбец11]]+Таблица6[[#This Row],[Столбец12]] -> 0 | X97: =Таблица6[[#This Row],[Столбец16]]-Таблица6[[#This Row],[Столбец13]] -> 0 | Y97: =Таблица6[[#This Row],[Столбец21]]/Таблица6[[#This Row],[Столбец13]] -> #DIV/0!
A98: 97 | J98: 23 | K98: ="00"&TEXT($L98,"0")&"-10" -> 0097-10 | L98: 97 | P98: =Таблица6[[#This Row],[Столбец11]]+Таблица6[[#This Row],[Столбец12]] -> 0 | X98: =Таблица6[[#This Row],[Столбец16]]-Таблица6[[#This Row],[Столбец13]] -> 0 | Y98: =Таблица6[[#This Row],[Столбец21]]/Таблица6[[#This Row],[Столбец13]] -> #DIV/0!
A99: 98 | J99: 24 | K99: ="00"&TEXT($L99,"0")&"-10" -> 0098-10 | L99: 98 | P99: =Таблица6[[#This Row],[Столбец11]]+Таблица6[[#This Row],[Столбец12]] -> 0 | X99: =Таблица6[[#This Row],[Столбец16]]-Таблица6[[#This Row],[Столбец13]] -> 0 | Y99: =Таблица6[[#This Row],[Столбец21]]/Таблица6[[#This Row],[Столбец13]] -> #DIV/0!
A100: 99 | J100: 25 | K100: ="00"&TEXT($L100,"0")&"-10" -> 0099-10 | L100: 99 | P100: =Таблица6[[#This Row],[Столбец11]]+Таблица6[[#This Row],[Столбец12]] -> 0 | X100: =Таблица6[[#This Row],[Столбец16]]-Таблица6[[#This Row],[Столбец13]] -> 0 | Y100: =Таблица6[[#This Row],[Столбец21]]/Таблица6[[#This Row],[Столбец13]] -> #DIV/0!
A101: 100 | J101: 26 | K101: ="00"&TEXT($L101,"0")&"-10" -> 00100-10 | L101: 100 | P101: =Таблица6[[#This Row],[Столбец11]]+Таблица6[[#This Row],[Столбец12]] -> 0 | X101: =Таблица6[[#This Row],[Столбец16]]-Таблица6[[#This Row],[Столбец13]] -> 0 | Y101: =Таблица6[[#This Row],[Столбец21]]/Таблица6[[#This Row],[Столбец13]] -> #DIV/0!
A102: 101 | J102: 27 | K102: ="00"&TEXT($L102,"0")&"-10" -> 00101-10 | L102: 101 | P102: =Таблица6[[#This Row],[Столбец11]]+Таблица6[[#This Row],[Столбец12]] -> 0 | X102: =Таблица6[[#This Row],[Столбец16]]-Таблица6[[#This Row],[Столбец13]] -> 0 | Y102: =Таблица6[[#This Row],[Столбец21]]/Таблица6[[#This Row],[Столбец13]] -> #DIV/0!
A103: 102 | J103: 28 | K103: ="00"&TEXT($L103,"0")&"-10" -> 00102-10 | L103: 102 | P103: =Таблица6[[#This Row],[Столбец11]]+Таблица6[[#This Row],[Столбец12]] -> 0 | X103: =Таблица6[[#This Row],[Столбец16]]-Таблица6[[#This Row],[Столбец13]] -> 0 | Y103: =Таблица6[[#This Row],[Столбец21]]/Таблица6[[#This Row],[Столбец13]] -> #DIV/0!
A104: 103 | J104: 29 | K104: ="00"&TEXT($L104,"0")&"-10" -> 00103-10 | L104: 103 | P104: =Таблица6[[#This Row],[Столбец11]]+Таблица6[[#This Row],[Столбец12]] -> 0 | X104: =Таблица6[[#This Row],[Столбец16]]-Таблица6[[#This Row],[Столбец13]] -> 0 | Y104: =Таблица6[[#This Row],[Столбец21]]/Таблица6[[#This Row],[Столбец13]] -> #DIV/0!
... A115: 114 | J115: 40 | K115: ="00"&TEXT($L115,"0")&"-10" -> 00114-10 | L115: 114 | P115: =Таблица6[[#This Row],[Столбец11]]+Таблица6[[#This Row],[Столбец12]] -> 0 | X115: =Таблица6[[#This Row],[Столбец16]]-Таблица6[[#This Row],[Столбец13]] -> 0 | Y115: =Таблица6[[#This Row],[Столбец21]]/Таблица6[[#This Row],[Столбец13]] -> #DIV/0!
A116: 115 | J116: 41 | K116: ="00"&TEXT($L116,"0")&"-10" -> 00115-10 | L116: 115
A117: 116 | J117: 42 | K117: ="00"&TEXT($L117,"0")&"-10" -> 00116-10 | L117: 116 | P117: =Таблица6[[#This Row],[Столбец11]]+Таблица6[[#This Row],[Столбец12]] -> 0 | X117: =Таблица6[[#This Row],[Столбец16]]-Таблица6[[#This Row],[Столбец13]] -> 0 | Y117: =Таблица6[[#This Row],[Столбец21]]/Таблица6[[#This Row],[Столбец13]] -> #DIV/0!
A118: 117 | J118: 43 | K118: ="00"&TEXT($L118,"0")&"-10" -> 00117-10 | L118: 117
A119: 118 | J119: 44 | K119: ="00"&TEXT($L119,"0")&"-10" -> 00118-10 | L119: 118
A120: 119
A121: 120
A122: 121 | P122: =SUM(P2:P103)+P105+P106+P108+P126 -> 5000 | S122: =SUM(S2:S103)+S105+S106+S108 -> 0 | X122: =Таблица6[[#This Row],[Столбец16]]-Таблица6[[#This Row],[Столбец13]] -> -5000 | Y122: =(Таблица6[[#This Row],[Столбец21]]-S32)/Таблица6[[#This Row],[Столбец13]] -> -1
A123: 122
A124: 123
A125: 124 | C125: TANK | D125: M083277 | P125: 74800
A126: 125 | C126: TANK | D126: M083277 | H126: 46075 | J126: 125 | M126: 100087 | N126: ='TANK M083277'!H9 -> 5 000,00 | P126: =Таблица6[[#This Row],[Столбец11]]+Таблица6[[#This Row],[Столбец12]] -> 5000
K127: ТРЕБУЕТ ВНИМАНИЯ | N127: =SUM( N2:N126) -> 0 | O127: =SUM(O2:O126) -> 0 | P127: =SUM(P2:P120)+P125+P126 -> 79800 | Q127: =SUM(Q2:Q126) -> 0 | R127: =SUM(R2:R126) -> 0 | S127: =SUM(S2:S120) -> 0 | T127: =Таблица6[[#This Row],[Столбец14]]-Таблица6[[#This Row],[Столбец11]] -> 0 | U127: =Таблица6[[#This Row],[Столбец17]]/Таблица6[[#This Row],[Столбец11]] -> #DIV/0! | V127: =Таблица6[[#This Row],[Столбец15]]-Таблица6[[#This Row],[Столбец12]] -> 0 | W127: =Таблица6[[#This Row],[Столбец19]]/Таблица6[[#This Row],[Столбец12]] -> #DIV/0! | X127: =Таблица6[[#This Row],[Столбец16]]-Таблица6[[#This Row],[Столбец13]] -> -79800 | Y127: =(Таблица6[[#This Row],[Столбец21]])/Таблица6[[#This Row],[Столбец13]] -> -1
K128: ЗАГРУЖЕНО
K129: ПОДПИСАНО
K130: ОПЛАЧЕНО
K131: сделано вне списка
K132: 10 ГК | L132: СДЕЛАНО | M132: ВЫГРУЖЕНО | N132: ПОДПИСАНО | O132: ОПЛАЧЕНО
K133: ЯНВ-ФЕВ | L133: 74 | M133: 71 | N133: 58
K134: НА 10.03.26 | M134: 3680305 | N134: 2775790.7
N135: =N134-M134 -> -904514.27
K136: 08 ГК | L136: СДЕЛАНО | M136: ВЫГРУЖЕНО | N136: ПОДПИСАНО | O136: ОПЛАЧЕНО
K137: ЯНВ-ФЕВ | L137: 24 | M137: 24 | N137: 22
K138: НА 10.03.26 | M138: 3587970.5 | N138: 3287119.7
N139: =N138-M138 -> -300850.77
K140: 08+10 ГК | L140: СДЕЛАНО | M140: ВЫГРУЖЕНО | N140: ПОДПИСАНО | O140: ОПЛАЧЕНО
K141: ЯНВ-ФЕВ | L141: 24+74 | M141: 24+71 | N141: 22+58
K142: НА 10.03.26 | M142: =M138+M134 -> 7268275.5 | N142: =N138+N134 -> 6062910.4
N143: =N142-M142 -> -1205365
K145: 10 ГК | L145: СДЕЛАНО | M145: ВЫГРУЖЕНО | N145: ПОДПИСАНО | O145: ОПЛАЧЕНО
K146: ЯНВ-МАРТ | L146: 93 | M146: 73 | N146: 71 | O146: 39
K147: НА 17.03.26 | M147: 3846022 | N147: 3680305 | O147: 1359053.3
N148: =N147-M147 -> -165717 | O148: =O147-N147 -> -2321251.7
K149: 08 ГК | L149: СДЕЛАНО | M149: ВЫГРУЖЕНО | N149: ПОДПИСАНО | O149: ОПЛАЧЕНО
K150: ЯНВ-МАРТ | L150: 29 | M150: 29 | N150: 24 | O150: 13
K151: НА 17.03.26 | M151: 4000889.4 | N151: 3587970.5 | O151: 1152812.7
N152: =N151-M151 -> -412918.91 | O152: =O151-N151 -> -2435157.7
K153: 08+10 ГК | L153: СДЕЛАНО | M153: ВЫГРУЖЕНО | N153: ПОДПИСАНО | O153: ОПЛАЧЕНО
K154: ЯНВ-МАРТ | L154: 29+93 | M154: 73+29 | N154: 71+24 | O154: 39+13
K155: НА 17.03.26 | M155: =M151+M147 -> 7846911.4 | N155: =N151+N147 -> 7268275.5 | O155: =(O151+O147) -> 2511866
N156: =N155-M155 -> -578635.91 | O156: =(O151+O147)-(N151+N147) -> -4756409.5
K158: 10 ГК | L158: СДЕЛАНО | M158: ВЫГРУЖЕНО | N158: ПОДПИСАНО | O158: ОПЛАЧЕНО
K159: ЯНВ-МАРТ | L159: 102 | M159: 96 | N159: 78 | O159: 39
K160: НА 26.03.26 | M160: 4717406.6 | N160: 4002699.4 | O160: 1359053.3
N161: =N160-M160 -> -714707.25 | O161: =O160-N160 -> -2643646.1
K162: 08 ГК | L162: СДЕЛАНО | M162: ВЫГРУЖЕНО | N162: ПОДПИСАНО | O162: ОПЛАЧЕНО
K163: ЯНВ-МАРТ | L163: 32 | M163: 29 | N163: 29 | O163: 13
K164: НА 26.03.26 | M164: 3986394.4 | N164: 3986394.4 | O164: 1152812.7
N165: =N164-M164 -> 0 | O165: =O164-N164 -> -2833581.7
K166: 08+10 ГК | L166: СДЕЛАНО | M166: ВЫГРУЖЕНО | N166: ПОДПИСАНО | O166: ОПЛАЧЕНО
K167: ЯНВ-МАРТ | L167: 32+102 | M167: 29+96 | N167: 29+78 | O167: 39+13
K168: НА 26.03.26 | M168: =M164+M160 -> 8703801 | N168: =N164+N160 -> 7989093.8 | O168: =(O164+O160) -> 2511866
N169: =N168-M168 -> -714707.25 | O169: =(O164+O160)-(N164+N160) -> -5477227.8

Sheet spisok
A1: № п/п | B1: Модель | C1: ГРЗ | D1: VIN | E1: гараж. № | F1: год вып. | G1: пробег | H1: дата | I1: № акта ЕИС | J1: сумма
A2: 1 | B2: УАЗ UAZ PATRIOT 3163 | C2: О201МК126 | D2: XTT316300R1000091 | E2: 106-81 | F2: 2023 | G2: 4116 | H2: 46174
A3: 2 | B3: LADA VESTA GFL110 | C3: Е833ОЕ15 | D3: XTAGFL110LY378838 | E3: 104-61 | F3: 2019 | G3: 237856 | H3: 46175
A4: 3 | B4: ЕСАУЛ 394511-03 | C4: В723УУ15 | D4: X8939451CG0AK5370 | E4: 103-30 | F4: 2016 | G4: 142626 | H4: 46175
A5: 4 | B5: LADA VESTA GFL110 | C5: Е378ОУ15 | D5: XTAGFL110LY443715 | E5: 105-48 | F5: 2020 | G5: 209733 | H5: 46176
A6: 5 | B6: ЕСАУЛ 394511-03 | C6: Е506НТ15 | D6: X8939451CK0AK5346 | E6: 104-91 | F6: 2019 | G6: 138364 | H6: 46176 | K6: ЕСАУЛ 394511-03 | L6: Е506НТ15 | O6: ГАЗ 221717 | P6: Е601РА15
A7: 6 | B7: LADA VESTA GFL110 | C7: В211ОХ15 | D7: XTAGFL110JY197249 | E7: 103-75 | F7: 2018 | G7: 320689 | H7: 46176 | O7: LADA GRANTA 219010 | P7: Е559НТ15
A8: 7 | B8: TOYOTA CAMRY ASV70L-RE | C8: Е778РА15 | D8: XW7BF4HK905167068 | E8: 106-39 | F8: 2020 | G8: 40010 | H8: 46176 | L8: TOYOTA CAMRY ASV70L-RE | M8: Е778РА15 | O8: УАЗ ПАТРИОТ | P8: В782ОХ15
A9: 8 | B9: ЛАДА ГРАНТА 219010 | C9: А287АР126 | D9: XTA219010E0256411 | E9: 106-34 | F9: 2014 | G9: 356419 | H9: 46177 | O9: ЛАДА 213100 4х4 | P9: В473ЕР126
A10: 9 | B10: LADA 4x4 213100 | C10: О 0708/15 | D10: XTA213100L0213886 | E10: 104-90 | F10: 2019 | G10: 126256 | H10: 46177
A11: 10 | B11: LADA PRIORA 217050 | C11: Т158АЕ15 | D11: XTA217050G0529350 | E11: 102-89 | F11: 2015 | G11: 275410 | H11: 46177 | K11: LADA PRIORA 217050 | L11: Т158АЕ15
A12: 11 | B12: ТОЙОТА КАМРИ | C12: Е898НТ15 | D12: XW7BF4FK10S155841 | E12: 103-69 | F12: 2017 | G12: 176666 | H12: 46177 | L12: ТОЙОТА КАМРИ | M12: Е898НТ15
A13: 12 | B13: УАЗ 396221 3163 | C13: Е312РА15 | D13: XTT316300M1002503 | E13: 105-57 | F13: 2020 | G13: 108974 | H13: 46178
A14: 13 | B14: ЕСАУЛ 394511-03 | C14: Е368НТ15 | D14: X8939451CK0AK5323 | E14: 104-95 | F14: 2019 | G14: 138585 | H14: 46178
A15: 14 | B15: ЕСАУЛ 394511-03 | C15: Е546НТ15 | D15: X8939451CK0AK5318 | E15: 104-96 | F15: 2019 | G15: 132853 | H15: 46178
A16: 15 | B16: ГАЗ 27322Е | C16: О0775/15 | D16: XUY27322EL0000276 | E16: 105-62 | F16: 2020 | G16: 159663 | H16: 46178 | K16: ГАЗ 27322Е | L16: О0775/15
A17: 16 | B17: ГАЗ 38406L | C17: М0629/15 | D17: Z8X38406LD0000147 | E17: 100-68 | F17: 2013 | G17: 201139 | H17: 46179
A18: 17 | B18: LADA GRANTA 219010 | C18: А722НА15 | D18: XTA219010M0770129 | E18: 105-89 | F18: 2021 | G18: 192073 | H18: 46179
A19: 18 | B19: HAVAL F7 CC6475UM09C | C19: Е985ЕН15 | D19: XZGEF04A4PA351278 | E19: 106-74 | F19: 2023 | G19: 22625 | H19: 46179 | K19: HAVAL F7 CC6475UM09C | L19: Е985ЕН15
A20: 19 | B20: LADA VESTA GFL110 | C20: Е154РА15 | D20: XTAGFL110LY443716 | E20: 105-53 | F20: 2020 | G20: 162007 | H20: 46179
A21: 20 | B21: ГАЗ 2705 | C21: В645ОТ15 | D21: X96270500H0824002 | E21: 103-68 | F21: 2016 | G21: 137401 | H21: 46181
A22: 21 | B22: TOYOTA CAMRY GSV70L-REZ | C22: Е301ОУ15 | D22: XW7BZYHK50S111563 | E22: 105-43 | F22: 2020 | G22: 35665 | H22: 46181 | L22: TOYOTA CAMRY GSV70L-REZ | M22: Е301ОУ15
A23: 22 | B23: РЕНО ДАСТЕР | C23: В391ОХ15 | D23: X7LHSRHGN59704684 | E23: 103-79 | F23: 2018 | G23: 142653 | H23: 46182 | K23: РЕНО ДАСТЕР | L23: В391ОХ15
A24: 23 | B24: ФОРД EXPLORER | C24: Е409РС15 | D24: Z6FBXXESWBES15416 | E24: 101-31 | F24: 2014 | G24: 344213 | H24: 46182 | K24: ФОРД EXPLORER | L24: Е409РС15
A25: 24 | B25: ЛАДА 213100 | C25: А678ХМ126 | D25: XTA213100F0171867 | E25: 106-62 | F25: 2015 | G25: 242508 | H25: 46182
A26: 25 | B26: KIA XM FL (SORENTO) | C26: О0774/15 | D26: XWEKU811DKC024995 | E26: 105-55 | F26: 2020 | G26: 21782 | H26: 46182
A27: 26 | B27: ТОЙОТА КАМРИ | C27: А333НА15 | D27: XW7BF4HK10S150796 | E27: 104-73 | F27: 2019 | G27: 232858 | H27: 46183
A28: 27 | B28: ХЕНДЭ СОЛЯРИС | C28: В201УВ15 | D28: Z94CU41DBFR426306 | E28: 102-63 | F28: 2015 | G28: 365954 | H28: 46183
A29: 28 | B29: LADA GRANTA 219010 | C29: Е559НТ15 | D29: XTA219010L0668690 | E29: 105-10 | F29: 2019 | G29: 230918 | H29: 46183
A30: 29 | B30: LADA VESTA GFL110 | C30: А725НА15 | D30: XTAGFL110MY545270 | E30: 106-01 | F30: 2021 | G30: 217051 | H30: 46184
A31: 30 | B31: УАЗ ПАТРИОТ | C31: В787ОХ15 | D31: XTT316300J1023444 | E31: 103-91 | F31: 2018 | G31: 232487 | H31: 46184
A32: 31 | B32: ЛАДА 213100 4х4 | C32: В473ЕР126 | D32: XTA213100G0177506 | E32: 106-63 | F32: 2015 | G32: 283293 | H32: 46184
A33: 32 | B33: VOLKSWAGEN MULTIVEN | C33: С488ВС15 | D33: XW8ZZZ7HZDG001346 | E33: 101-90 | F33: 2013 | G33: 302107 | H33: 46184
A34: 33 | B34: ЕСАУЛ 394511-03 | C34: Е368НТ15 | D34: X8939451CK0AK5323 | E34: 104-95 | F34: 2019 | G34: 139503 | H34: 46185
A35: 34 | B35: ЕСАУЛ 394511-03 | C35: Е499НТ15 | D35: X8939451CK0AK5363 | E35: 105-01 | F35: 2019 | G35: 103143 | H35: 46186
A36: 35 | B36: LADA VESTA GFL110 | C36: Е375ОУ15 | D36: XTAGFL110LY443723 | E36: 105-47 | F36: 2020 | G36: 231159 | H36: 46188
... A71: 70 | B71: ЕСАУЛ 394511-03 | C71: Е491НТ15 | D71: X8939451CK0AK5352 | E71: 105-00 | F71: 2019 | G71: 39309 | H71: 46203
A72: 71
A73: 72
A74: 73
A75: 74
A76: 75
A77: 76
A78: 77
A79: 78
A80: 79
A81: 80
A82: 81
A83: 82
... A119: 118

Sheet 645
B1: ПОСТАВЩИК: ООО ФИРМА "СИГНАЛ"
B2: адрес: 364031, Чеченская Республика, г.Грозный, ул. Жуковского, д. 18
C4: Заказ-наряд № 100550 от 09.06.2026
B6: Заказчик: Общество с ограниченной ответственностью «Концепт» | H6: адрес заказчика : 364024, ЧР г.Грозный, ул.Назарбаева, д.92, оф. 6-05
B7: Автомобиль : ГАЗ 2705 г/н В 645 ОТ/15
B9: Цена автомототранспортного средства, определяемая по соглашению сторон __________________
B11: Плательщик: Общество с ограниченной ответственностью «Концепт»
B12: ИНН 2014030866 адрес: телефоны: +7 (989) 9002252
N14: в валюте
N15: Руб
C17: Выполненные работы по заказ-наряду № 100550 от 09.06.2026
B19: № | C19: № кат. | D19: Наименование | I19: Кол. оп. | J19: Цена | K19: Норма | L19: н/ч | M19: Всего | N19: в т.ч. НДС
B20: 1 | C20: 2 | D20: 3 | I20: 4 | J20: 5 | K20: 6 | L20: 7 | M20: 8 | N20: 9
B21: 1 | D21: Диагностика ДВС | I21: 1 | J21: 1000 | K21: 1 | L21: Рубль | M21: =J21*I21 -> 1000 | N21: =M21*22/122 -> 180.32787
B22: 2 | D22: Замена компрессии в цилиндрах | I22: 1 | J22: 400 | K22: 1 | L22: Рубль | M22: =J22*I22 -> 400 | N22: =M22*22/122 -> 72.131148
B23: 3 | D23: Замена прокладки ГБЦ | I23: 1 | J23: 8000 | K23: 1 | L23: Рубль | M23: =J23*I23 -> 8000 | N23: =M23*22/122 -> 1442.623
B24: 4 | D24: Проверка ГБЦ на трещину | I24: 1 | J24: 1000 | K24: 1 | L24: Рубль | M24: =J24*I24 -> 1000 | N24: =M24*22/122 -> 180.32787
B25: 5 | D25: Шлифовка ГБЦ | I25: 1 | J25: 1500 | K25: 1 | L25: Рубль | M25: =J25*I25 -> 1500 | N25: =M25*22/122 -> 270.4918
B26: 6 | D26: Притирка клапанов | I26: 1 | J26: 4000 | K26: 1 | L26: Рубль | M26: =J26*I26 -> 4000 | N26: =M26*22/122 -> 721.31148
B27: 7 | D27: Токарные работы | I27: 1 | J27: 1000 | K27: 1 | L27: Рубль | M27: =J27*I27 -> 1000 | N27: =M27*22/122 -> 180.32787
B28: 8 | D28: Замена свечей зажигания | I28: 1 | J28: 400 | K28: 1 | L28: Рубль | M28: =J28*I28 -> 400 | N28: =M28*22/122 -> 72.131148
B29: Итого работ: | I29: 8 | J29: на сумму: | M29: =M21+M22+M23+M24+M25+M26+M27+M28 -> 17300 | N29: =M29*22/122 -> 3119.6721
B31: Семнадцать тысяч триста рублей 00 копеек.
C33: Расходная накладная к заказ-наряду № 100550 от 09.06.2026
B35: № | C35: № кат. | D35: Наименование | J35: Кол-во | K35: Ед.изм. | L35: Цена | M35: Всего | N35: в т.ч. НДС
B36: 1 | C36: 2 | D36: 3 | J36: 4 | K36: 5 | L36: 6 | M36: 7 | N36: 8
B37: 1 | C37: А17ДВРМ | D37: Свечи А17ДВРМ Стандарт "33" 8кл | J37: 1 | K37: кт | L37: 600 | M37: =L37*J37 -> 600 | N37: =M37*22/122 -> 108.19672
B38: 2 | C38: 4216.3707080-23 | D38: Провода высоковольтные ГАЗ-3302,2705 Бизнес дв.УМЗ-4216 ЕВРО-4 кт | J38: 1 | K38: кт | L38: 1150 | M38: =L38*J38 -> 1150 | N38: =M38*22/122 -> 207.37705
B39: 3 | D39: Шланг d=18 силикон 1 м оранж. внутри Technik | J39: 1 | K39: шт | L39: 300 | M39: =L39*J39 -> 300 | N39: =M39*22/122 -> 54.098361
B40: 4 | D40: Шланг d= 8 силикон (бухта 20м) оранж. внутри Technik | J40: 1 | K40: шт | L40: 150 | M40: =L40*J40 -> 150 | N40: =M40*22/122 -> 27.04918
B41: 5 | D41: Кольцо уплотнительное форсунок ВАЗ 106 л.с. (кт 8 шт) | J41: 1 | K41: кт | L41: 150 | M41: =L41*J41 -> 150 | N41: =M41*22/122 -> 27.04918
B42: 6 | C42: 4216.1008080 | D42: Прокладка УМЗ-4213,4216 коллектора УМЗ | J42: 1 | K42: шт | L42: 120 | M42: =L42*J42 -> 120 | N42: =M42*22/122 -> 21.639344
B43: 7 | C43: 24-1007036-01 | D43: Колпачки маслосъемные дв.402,523,513,511,УАЗ (к-т 8шт.) Кирово-Чепецк | J43: 1 | K43: кт | L43: 600 | M43: =L43*J43 -> 600 | N43: =M43*22/122 -> 108.19672
B44: 8 | D44: РК приемной трубы дв.421 ВАТИ-61 (гайки,шпильки,прокладки) "ЭССКО-НН" | J44: 1 | K44: кт | L44: 200 | M44: =L44*J44 -> 200 | N44: =M44*22/122 -> 36.065574
B45: 9 | C45: 103015 | D45: Антифриз Sintec Luxe G12+ red -40 3кг | J45: 1 | K45: кт | L45: 650 | M45: =L45*J45 -> 650 | N45: =M45*22/122 -> 117.21311
B46: 10 | C46: 421-1003020 | D46: Прокладка ГБЦ дв.421 (с герм.) БЦМ | J46: 1 | K46: шт | L46: 580 | M46: =L46*J46 -> 580 | N46: =M46*22/122 -> 104.59016
B47: Итого материалов: | J47: 10 | K47: на сумму: | M47: =M37+M38+M39+M40+M41+M42+M43+M44+M45+M46 -> 4500 | N47: =M47*22/122 -> 811.47541
B49: Четыре тысячи пятьсот рублей 00 копеек
L51: Итого по заказ-наряду : | M51: =M29+M47 -> 21800 | N51: =M51*22/122 -> 3931.1475
B53: Всего по заказ-наряду: Двадцать одна тысяча восемьсот рублей 00 копеек, в т.ч. НДС 22%.
J56: Мастер _____________________ | K56: Механик СТО/
C58: Гарантии: Гарантия на работы: слесарные - 30 дней, электрические - 30 дней, оригинальные з/ч - 30 дней, з/ч, связанные с электрооборудованием, подачей топлива и системой впрыска - гарантии нет, неоригинальные з/ч - гарантии нет. Гарантийные обязательства на работы выполняются фирмой только при предъявлении акта приемки автомобиля и техпаспорта (доверенности).
B62: Дата: 09.06.2026 | J62: Заказчик ______________________ | K62: /ООО «Концепт»/
J64: Плательщик ______________________ | K64: /ООО «Концепт»/
B66: Причина обращения:

Sheet 158
B1: ПОСТАВЩИК: ООО ФИРМА "СИГНАЛ"
B2: адрес: 364031, Чеченская Республика, г.Грозный, ул. Жуковского, д. 18
C4: Заказ-наряд № 100512 от 04.06.2026
B6: Заказчик: Общество с ограниченной ответственностью «Концепт» | H6: адрес заказчика : 364024, ЧР г.Грозный, ул.Назарбаева, д.92, оф. 6-05
B7: Автомобиль : Лада Приора гос. номер: Т158АЕ/15
B9: Цена автомототранспортного средства, определяемая по соглашению сторон __________________
B11: Плательщик: Общество с ограниченной ответственностью «Концепт»
B12: ИНН 2014030866 адрес: телефоны: +7 (989) 9002252
N14: в валюте
N15: Руб
C17: Выполненные работы по заказ-наряду № 100512 от 04.06.2026
B19: № | C19: № кат. | D19: Наименование | I19: Кол. оп. | J19: Цена | K19: Норма | L19: н/ч | M19: Всего | N19: в т.ч. НДС
B20: 1 | C20: 2 | D20: 3 | I20: 4 | J20: 5 | K20: 6 | L20: 7 | M20: 8 | N20: 9
B21: 1 | D21: Замена радиатора охлаждения | I21: 1 | J21: 4000 | K21: 1 | L21: Рубль | M21: =J21*I21 -> 4000 | N21: =M21*22/122 -> 721.31148
B22: 2 | D22: Замена троса капота | I22: 1 | J22: 2000 | K22: 1 | L22: Рубль | M22: =J22*I22 -> 2000 | N22: =M22*22/122 -> 360.65574
B23: 3 | D23: Замена опоры амортизатора | I23: 2 | J23: 1300 | K23: 1 | L23: Рубль | M23: =J23*I23 -> 2600 | N23: =M23*22/122 -> 468.85246
B24: 4 | D24: Замена рулевого наконечника | I24: 2 | J24: 350 | K24: 1 | L24: Рубль | M24: =J24*I24 -> 700 | N24: =M24*22/122 -> 126.22951
B25: 5 | D25: Ремонт свечей зажигания | I25: 1 | J25: 500 | K25: 1 | L25: Рубль | M25: =J25*I25 -> 500 | N25: =M25*22/122 -> 90.163934
B26: 6 | D26: Замена замка капота | I26: 1 | J26: 400 | K26: 1 | L26: Рубль | M26: =J26*I26 -> 400 | N26: =M26*22/122 -> 72.131148
B27: 7 | D27: Диагностика кондиционера с опрессовкой | I27: 1 | J27: 1300 | K27: 1 | L27: Рубль | M27: 1000 | N27: =M27*22/122 -> 180.32787
B28: 8 | D28: Заправка кондиционера | I28: 1 | J28: 4500 | K28: 1 | L28: Рубль | M28: =J28*I28 -> 4500 | N28: =M28*22/122 -> 811.47541
B29: 9 | D29: Ремонт колеса | I29: 1 | J29: 300 | K29: 1 | L29: Рубль | M29: =J29*I29 -> 300 | N29: =M29*22/122 -> 54.098361
B30: 10 | D30: Замена масла и масл фильтра | I30: 1 | J30: 600 | K30: 1 | L30: Рубль | M30: =J30*I30 -> 600 | N30: =M30*22/122 -> 108.19672
B31: 11 | D31: Замена воздушного фильтра | I31: 1 | J31: 200 | K31: 1 | L31: Рубль | M31: =J31*I31 -> 200 | N31: =M31*22/122 -> 36.065574
B32: 12 | D32: Замена топливного фильтра | I32: 1 | J32: 300 | K32: 1 | L32: Рубль | M32: =J32*I32 -> 300 | N32: =M32*22/122 -> 54.098361
B33: 13 | D33: Сход-развал (с рскруткой сход-разв. тяг) | I33: 1 | J33: 2000 | K33: 1 | L33: Рубль | M33: =J33*I33 -> 2000 | N33: =M33*22/122 -> 360.65574
B34: Итого работ: | I34: 15 | J34: на сумму: | M34: =M21+M22+M23+M24+M25+M26+M27+M28+M29+M30+M31+M32+M33 -> 19100 | N34: =M34*22/122 -> 3444.2623
B36: Девятнадцать тысяч сто рублей 00 копеек.
C38: Расходная накладная к заказ-наряду № 100512 от 04.06.2026
B40: № | C40: № кат. | D40: Наименование | J40: Кол-во | K40: Ед.изм. | L40: Цена | M40: Всего | N40: в т.ч. НДС
B41: 1 | C41: 2 | D41: 3 | J41: 4 | K41: 5 | L41: 6 | M41: 7 | N41: 8
B42: 1 | C42: HF708432 | D42: Радиатор охл ВАЗ 2170 алюм. 2-ряд. под кондиц. Halla сборный HOFER | J42: 1 | K42: шт | L42: 3900 | M42: =L42*J42 -> 3900 | N42: =M42*22/122 -> 703.27869
B43: 2 | C43: 614503 | D43: Антифриз Sintec LUXE G12+, 5 кг, красный | J43: 1 | K43: шт | L43: 1000 | M43: =L43*J43 -> 1000 | N43: =M43*22/122 -> 180.32787
B44: 3 | C44: 103015 | D44: Антифриз Sintec Luxe G12+ red -40 3кг | J44: 1 | K44: шт | L44: 650 | M44: =L44*J44 -> 650 | N44: =M44*22/122 -> 117.21311
B45: 4 | C45: 2110-8406010 | D45: Замок капота Приора, Ваз 2110, Нива Шевроле 2123 | J45: 1 | K45: шт | L45: 500 | M45: =L45*J45 -> 500 | N45: =M45*22/122 -> 90.163934
B46: 5 | C46: 21100-8406140-00 | D46: Трос капота ВАЗ 2110, 2111, 2112, 2170, Приора, Автопартнер | J46: 1 | K46: шт | L46: 200 | M46: =L46*J46 -> 200 | N46: =M46*22/122 -> 36.065574
B47: 6 | C47: 2170-2902821-01 11720 | D47: Опора верхняя передней стойки (без подшипника) усиленная 2170 | J47: 2 | K47: шт | L47: 650 | M47: =L47*J47 -> 1300 | N47: =M47*22/122 -> 234.42623
B48: 7 | C48: 11180-2902840-01 | D48: Подшипник опоры передней стойки 1118 Калина 2170 Priora 2190 Granta LADA Image | J48: 2 | K48: шт | L48: 950 | M48: =L48*J48 -> 1900 | N48: =M48*22/122 -> 342.62295
B49: 8 | C49: AP31-110 | D49: Отбойник амортизатора передний с пыльником Ваз 2110 HOLA | J49: 2 | K49: шт | L49: 350 | M49: =L49*J49 -> 700 | N49: =M49*22/122 -> 126.22951
B50: 9 | C50: LL0108 | D50: Крышка расширительного бачка для а/м Газель Бизнес, ВАЗ 2108/2110/Приора/Гранта LUZAR | J50: 1 | K50: шт | L50: 250 | M50: =L50*J50 -> 250 | N50: =M50*22/122 -> 45.081967
B51: 10 | C51: AC15C | D51: Фильтр салонный SIBTEK ВАЗ 2170 с кондиционером Halla угольный | J51: 1 | K51: шт | L51: 400 | M51: =L51*J51 -> 400 | N51: =M51*22/122 -> 72.131148
B52: 11 | C52: LF105 | D52: Фильтр масляный LADA 08-112 FINWHALE | J52: 1 | K52: шт | L52: 400 | M52: =L52*J52 -> 400 | N52: =M52*22/122 -> 72.131148
B53: 12 | C53: BM FA2108 | D53: Фильтр воздушный, плоский для LADA ВАЗ 2108-2112 (инж) BM | J53: 1 | K53: шт | L53: 350 | M53: =L53*J53 -> 350 | N53: =M53*22/122 -> 63.114754
B54: 13 | C54: 3705304 | D54: Масло моторное Лукойл Люкс 10W-40 (4л) | J54: 1 | K54: шт | L54: 1150 | M54: =L54*J54 -> 1150 | N54: =M54*22/122 -> 207.37705
B55: 14 | C55: 21230111701081 | D55: Фильтр топливный LADA 2101-07/Samara/110/Kalina/Granta/Priora/4x4 | J55: 1 | K55: шт | L55: 400 | M55: =L55*J55 -> 400 | N55: =M55*22/122 -> 72.131148
B56: 15 | C56: F01H7B0042-HZ6 | D56: Свечи АУ-17ДВРМ Стандарт "33" ВАЗ 2108-70, ЗМЗ 406-409. УМЗ 4216 | J56: 1 | K56: кт | L56: 600 | M56: =L56*J56 -> 600 | N56: =M56*22/122 -> 108.19672
B57: 16 | C57: 21100341410082 | D57: Наконечник рулевой Ваз 2110-70, 2190 лев/прав ОАО АВТОВАЗ | J57: 1 | K57: кт | L57: 1500 | M57: =L57*J57 -> 1500 | N57: =M57*22/122 -> 270.4918
B58: 17 | C58: 4008 | D58: Смазка многоцелевая RC-40, 210 мл BiBiCare | J58: 1 | K58: шт | L58: 250 | M58: =L58*J58 -> 250 | N58: =M58*22/122 -> 45.081967
B59: Итого материалов: | J59: 20 | K59: на сумму: | M59: =M42+M43+M44+M45+M46+M47+M48+M49+M50+M51+M52+M53+M54+M55+M56+M57+M58 -> 15450 | N59: =M59*22/122 -> 2786.0656
B61: Пятнадцать тысяча четыреста пятьдесят рублей 00 копеек
L63: Итого по заказ-наряду : | M63: =M34+M59 -> 34550 | N63: =M63*22/122 -> 6230.3279
B65: Всего по заказ-наряду: Тридцать четыре тысячи пятьсот пятьдесят рублей 00 копеек, в т.ч. НДС 22%.
J68: Мастер _____________________ | K68: Механик СТО/
C70: Гарантии: Гарантия на работы: слесарные - 30 дней, электрические - 30 дней, оригинальные з/ч - 30 дней, з/ч, связанные с электрооборудованием, подачей топлива и системой впрыска - гарантии нет, неоригинальные з/ч - гарантии нет. Гарантийные обязательства на работы выполняются фирмой только при предъявлении акта приемки автомобиля и техпаспорта (доверенности).
B75: Дата: 04.06.2026 | J75: Заказчик ______________________ | K75: /Общество с ограниченной ответственностью «Концепт»/
J77: Плательщик ______________________ | K77: /Общество с ограниченной ответственностью «Концепт»/
B79: Причина обращения:

Sheet TANK M083277
A1: Заказ-наряд № 100087 от 22.02.2026
A2: Заказчик: Общество с ограниченной ответственностью «Концепт» | B2: адрес заказчика : 364024, ЧР г.Грозный, ул.Назарбаева, д.92, оф. 6-05
A3: Автомобиль : TANK гос. номер: М 0832 77
A5: Выполненные работы по заказ-наряду № 100087 от 22.02.2026
A6: № | B6: № кат. | C6: Наименование | D6: Кол. оп. | E6: Цена | F6: Норма | G6: н/ч | H6: Всего | I6: в т.ч. НДС
A7: 1 | B7: 2 | C7: 3 | D7: 4 | E7: 5 | F7: 6 | G7: 7 | H7: 8 | I7: 9
A8: 1 | C8: Шиномонтаж колеса (снять колесо,сборка-разборка, балансировка, поставить колесо) 1 шт. | D8: 4 | E8: 1250,00 | F8: 1.000 | G8: Рубль | H8: 5 000.00 | I8: 901 64
A9: итого работ: | D9: 4 | E9: на сумму. | H9: 5 000,00 | I9: 901,64
A11: Расходная накладная к заказ-наряду № 100087 от 22.02.2026
A12: № | B12: № кат. | C12: Наименование | D12: Кол-во | E12: Ед.изм. | F12: Цена | G12: Всего | H12: в т.ч. НДС
A13: 1 | B13: 2 | C13: 3 | D13: 4 | E13: 5 | F13: 6 | G13: 7 | H13: 8
A15: итого материалов: | D15: 1 | E15: на сумму: | G15: 0,00 | H15: 0,00

Sheet 62
A1: Акт № 62 от 9 апреля 2026 г. Исполнитель: ООО ФИРМА "СИГНАЛ", ИНН 2014025023, КПП 201401001, 364037, Респ Чеченская, г Грозный, р-н АхматовскИй, ул нм Жуковского, двлд 18, р/с 40702810234120000061, в банке ЧЕЧЕНСКИЙ РФ АО "РОССЕЛЬХОЗБАНк" Г. Грозный, БИК 049690719, к/с 30101810600000000719 Заказчик: ООО "К0НЦЕПТ", ИНН 2014030866, КПП 201401001, 364024, Респ Чеченская, г Грозный, р-н АхматовскИй, ул Н.А.Назарбаева, дом 92, офнс 6-05, р/с 40702810910001078622, в банке АО "ТБанк" Г. Москва, БИК 044525974, к/с 30101810145250000974 Оенование: ДОГОВОР № 05/05-2025 от "27" мая 2025 г.
A2: № | B2: НаИменованИе работ, услуг | C2: Кол-во | D2: Ед. | E2: Цена | F2: Сумма
A3: 1 | B3: Шиномонтаж а/м HAVAL F7 г/н Е 985 ЕН 15 | C3: 1 | D3: шт | E3: 4 000,00 | F3: 4 000,00
A4: 2 | B4: Шиномонтаж а/м Тойота Камри г/н Е 898 НТ /15 | C4: 1 | D4: ШТ | E4: 2600 | F4: 2600
A5: 3 | B5: Ремонт а/м УАЗ Патриот Е312РА 15 | C5: 1 | D5: ШТ | E5: 3650 | F5: 3650
A6: 4 | B6: Ремонт а/м УАЗ Патриот г/н В782ОХ 15 | C6: 1 | D6: шт | E6: 62050 | F6: 62050
A7: 5 | B7: Ремонт а/м тойота Камри г/н АЗЗЗНА 15 | C7: 4 | D7: ШТ | E7: 7600 | F7: 30400
A8: 6 | B8: Ремонт а/м УАЗ Хантер г/н М 516 PT 15 | C8: 1 | D8: шт | E8: 13000 | F8: 13000
D9: в | E9: Итого: том ЧИсле НДС | F9: 115 700,00 20 863,93

Sheet 516
A1: Заказ-наряд № 100158 от 27.03.2026
A2: Заказчик: Общество с ограниченной ответственностью «Концепт» | B2: адрес заказчика : 364024, ЧР г.Грозный, ул.Назарбаева, д,92, оф. 6-05
A3: Автомобиль : УАЗ Хантер гос. номер: М 516 РТ 15
A5: Выполненные работы по заказ-наряду № 100158 от 27.03.2026
A6: № | B6: № кат. | C6: Наименование | D6: Кол. оп. | E6: Цена | F6: Норма | G6: н/ч | H6: Всего | I6: в т.ч. НДС
A7: 1 | B7: 2 | C7: 3 | D7: 4 | E7: 5 | F7: 6 | G7: 7 | H7: 8 | I7: 9
A8: 1 | C8: Замена муфты включения переднего моста | D8: 2 | E8: 500 | F8: 1 | G8: Рубль | H8: 1000 | I8: 180.33
A9: Итого работ: | D9: 2 | E9: на сумму: | H9: 1000 | I9: 180.33
A11: Расходная накладная к заказ-наряду № 100158 от 27.03.2026
A12: № | B12: № кат. | C12: Наименование | D12: Кол-во | E12: Ед.изм. | F12: Цена | G12: Всего | H12: в т.ч. НДС
A13: 1 | B13: 2 | C13: 3 | D13: 4 | E13: 5 | F13: 6 | G13: 7 | H13: 8
A14: 1 | B14: RB-31512-2304310- 10 | C14: Муфты включения переднего моста (хабы колесные) УАЗ 3163/Патриот469/452/Хантер Серия City "redBTR" кт 2 шт. | D14: 1 | E14: кт | F14: 12000 | G14: 12000 | H14: 2163.93
A15: Итого материалов: | D15: 1 | E15: на сумму: | G15: 12 000,00 | H15: 2163.93

Sheet 333
A1: Закаэ-наряд № 100167 от 04.04.2026
A2: Заказчик: Общество с отраниченной ответственностью «Концепт» | B2: адрес заказчика : 364024, ЧР г,Грозный, ул.назарбаева, д.92, оф. 6-05
A3: Автомобиль : тойота Камри гос. номер: А 333 НА 15
A5: Не | B5: Выполненные Nt хат. | C5: работы по заказ-наряду № 100167 от 04.04.202 Нвимвкив«мио | D5: 6 КОЛ. оп. | E5: цена | F5: Норме | G5: н/ч | H5: Всего | I5: в т.ч. НДС
A6: 1 | B6: 2 | C6: 3 | D6: 4 | E6: 5 | F6: в | G6: 7 | H6: 8 | I6: 9
A7: 1 | C7: Балансировка колеса (со с/у) | D7: 4 | E7: 450 | F7: 1 | G7: Рубль | H7: 1800 | I7: 324.59
A8: Итого работ: | D8: * | E8: на сумму: | H8: 1800 | I8: 324.59
A10: № | B10: Расходная наш №кат. | C10: ладная к заказ-наряду № 100167 от 04.04.2026 Наименование | D10: Кол-во | E10: Едизм, | F10: цена | G10: всего | H10: в т.ч. НДС
A11: 1 | B11: 2 | C11: 3 | D11: 4 | E11: 5 | F11: 6 | G11: 7 | H11: 8
A12: 1 | C12: колодки тормозные перед. Kashiyama Toyota Camry V70 17- /RAV 4 | D12: 1 | E12: кт | F12: 3500 | G12: 3500 | H12: 631.15
A13: 2 | C13: КОГОДки тормозные задние D2349H TOYOTA CAMRY (17-). RAV4 (18-). СН-R (18-). LEXUS RX (15-) KASHIYAMA | D13: 1 | E13: кт | F13: 2300 | G13: 2300 | H13: 414.75
A14: ИтоГО материалов: | D14: 2 | E14: на сумму: | G14: 5800 | H14: 1045.9

Sheet 312
A1: Заказ-наряд № 100164 от 01.04.2026
A2: Заказчик: Общество с ограниченной ответственностью «Концепт» | B2: адрес заказчика : 364024, ЧР г.Грозный, ул.назарбаева, д.92, оф. 6-05
A3: Автомобиль : УАЗ патриот гос. номер: Е312РА 15
A5: Выполненные работы по заказ-наряду № 100164 от 01.04.2026
A6: № | B6: №кат. | C6: наименование | D6: Кол. оп. | E6: Цена | F6: Норма | G6: н/ч | H6: всего | I6: в т.ч. ндс
A7: 1 | B7: 2 | C7: 3 | D7: 4 | E7: 8 | F7: 6 | G7: 7 | H7: 8 | I7: 9
A8: 1 | C8: Диагностика ДВС | D8: 1 | E8: 1000 | F8: 1 | G8: Рубль | H8: 1000 | I8: 180.33
A9: 2 | C9: Ремонт электрооборудования | D9: 1 | E9: 1150 | F9: 1 | G9: Рубль | H9: 1150 | I9: 207.38
A10: 3 | C10: сход-развал | D10: 1 | E10: 1500 | F10: 1 | G10: Рубль | H10: 1500 | I10: 270.49
A11: Итото работ: | D11: 3 | E11: на сумму: | H11: 3650 | I11: 658.2
A13: Расходная накладная к заказ-наряду № 100164 от 01.04,2026
A14: № | B14: № кат. | C14: Наименование | D14: Кол-во | E14: Ед.изм. | F14: Цена | G14: Всего | H14: в т.ч. НДС
A15: 1 | B15: 2 | C15: 3 | D15: 4 | E15: 5 | F15: 6 | G15: 7 | H15: 8
A17: Итото материалов: | D17: 0 | E17: на сумму:

Sheet 782
A1: Заказ-наряд № 100156 от 27.03.2026
A2: Заказчик: Общество с ограниченной ответственностью «Концепт» | B2: адрес заказчика : 364024, ЧР г.Грозный, ул.назарбаева, д.92, оф, 6-05
A3: Автомобиль : УАЗ Патриот гос, номер: В782ОХ 15
A5: Выполненные работы по заказ-наряду № 100156 от 27.03.2026
A6: № | B6: №кат. | C6: Наименование | D6: Кол, оп. | E6: Цена | F6: Норма | G6: н/ч | H6: Всего | I6: в т.ч. НДС
A7: 1 | B7: 2 | C7: 3 | D7: 4 | E7: 5 | F7: 6 | G7: 7 | H7: 8 | I7: 9
A8: 1 | C8: Замена масла и масл фильтра ГУР | D8: 1 | E8: 600 | F8: 1 | G8: Рубль | H8: 600 | I8: 108.2
A9: 2 | C9: Подтяжка шкворня | D9: 2 | E9: 800 | F9: 1 | G9: Рубль | H9: 1600 | I9: 288.52
A10: 3 | C10: Подтяжка хвостовика | D10: 1 | E10: 500 | F10: 1 | G10: Рубль | H10: 500 | I10: 90.16
A11: 4 | C11: Ремонт выхлопной системы | D11: 1 | E11: 500 | F11: 1 | G11: Рубль | H11: 500 | I11: 90.16
A12: 5 | C12: Замена рулевого механизма | D12: 1 | E12: 2500 | F12: 1 | G12: Рубль | H12: 2500 | I12: 450.82
A13: 6 | C13: Замена рулевого кардана | D13: 1 | E13: 500 | F13: 1 | G13: Рубль | H13: 500 | I13: 90.16
A14: 7 | C14: Замена подрулевого шлейфа | D14: 1 | E14: 1500 | F14: 1 | G14: Рубль | H14: 1500 | I14: 270.49
A15: 8 | C15: Диагностика и ремонт электрооборудования | D15: 1 | E15: 2500 | F15: 1 | G15: Рубль | H15: 2500 | I15: 450.82
A16: Итого работ: | D16: 9 | E16: на сумму: | H16: 10200 | I16: 1839.34
A18: Расходная накладная к заказ-наряду № 100156 от 27.03.2026
A19: № | B19: № кат. | C19: Наименование | D19: Кол-во | E19: Ед.изм. | F19: Цена | G19: Всего | H19: в т.ч. НДС
A20: 1 | B20: 2 | C20: 3 | D20: 4 | E20: 5 | F20: 6 | G20: 7 | H20: 8
A21: 1 | B21: ЕКО0262 | C21: Фильтр масляный в гидроусилитель ЕКО-02,62 (Камаз, ЗиЛ, Волга, ГАЗ) | D21: 1 | E21: шт | F21: 200 | G21: 200 | H21: 36.07
A22: 2 | B22: 30466 | C22: Масло трансмиссионное Kinetik Energy ATF Luxe Dexron III ч/с 1л | D22: 2 | E22: шт | F22: 400 | G22: 800 | H22: 144.26
A23: 3 | B23: 3163-3400500-10 | C23: Рулевое управление (механизмГУРа) для Патриот под мелкий шлиц YuBei | D23: 1 | E23: шт | F23: 40000 | G23: 40000 | H23: 7213.11
A24: 4 | B24: 316310-3401400-00 | C24: Вал карданный УАЗ-3163 (14-) рулевой в сборе под ГУР YB (ОАО УАЗ) | D24: 1 | E24: шт | F24: 6500 | G24: 6500 | H24: 1172.13
A25: 5 | B25: ORTRA185 | C25: Шлейф подрулевой для UAZ PATRIOT 2016-2025 , UAZ PICKUP 2016-2025 , UAZ PATRIOT 3163 20162025 | D25: 1 | E25: шт | F25: 4350 | G25: 4350 | H25: 784.43
A26: Итого материалов: | D26: 6 | E26: на сумму: | G26: 51850 | H26: 9350

Sheet 72
A1: Акт № 72 от 23 апреля 2026 Г.
A2: Исполнитель: ООО ФИРМА "СИГНАЛ", ИНН 2014025023, КПП 201401001, 364037, Респ Чеченская, г Грозный, р-н Ахматовский, ул нм Жуковского, двлд 18, р/с 40702810234120000061, в банке ЧЕЧЕНСКИЙ РФ АО "РОССЕЛЬХОЗБАНК" Г. Грозный, БИК 049690719, к/с 30101810600000000719 Заказчик: ООО "КОНЦЕПТ", ИНН 2014030866, КПП 201401001, 364024, Респ Чеченская, г Гроэный, р-н АхматовскИй, ул Н.А.Назарбаева, дом 92, офИс 6-05, р/с 40702810910001078622, в банке АО "ТБанк" Г. Москва, БИК 044525974, к/с 30101810145250000974 Основание: ДОГОВОР № 05/05-2025 от "27" мая 2025 г.
A3: № | B3: Наименование работ, услуг | C3: кол-во | D3: ЕД- | E3: Цена | F3: Сумма
A4: 1 | B4: Ремонт а/м УАЗ Патриот г/н X 459 КХ | C4: 1 | D4: ШТ | E4: 81600 | F4: 81600
A5: Итого: 81 600,00 В том ЧИсле НДС 14 714,75

Sheet 459
A1: Закаэ-наряд № 100160 от 27.03.2026
A2: Заказчик: Общество с ограниченной ответственностью «Концепт» | B2: адрес заказчика : 364024, ЧР г.Грозный, ул.назарбаева, д,92, оф. 6-05
A3: Автомобиль : УАЗ патриот гос. номер: X 459 КХ 15
A5: Выполненные работы по заказ-наряду № 100160 от 27.03.2026
A6: ГЛ | B6: № кат. | C6: наименование | D6: Кол. оп. | E6: цена | F6: норма | G6: н/ч | H6: Всего | I6: в т.ч. НДС
A7: 1 | B7: 2 | C7: 3 | D7: 4 | E7: 6 | G7: 7 | H7: 8 | I7: 9
A8: 1 | C8: диагностика ДВС | D8: 1 | E8: 1000 | F8: 1 | G8: Рубль | H8: 1000 | I8: 180.33
A9: 2 | C9: Замена катушки зажигания | D9: 2 | E9: 100 | F9: 1000 | G9: Рубль | H9: 200 | I9: 36.07
A10: 3 | C10: Замена свечей зажиГання | D10: 1 | E10: 60000 | F10: 1000 | G10: Рубль | H10: 600 | I10: 108.2
A11: 4 | C11: Замена радиатора охлаждения | D11: 1 | E11: 2500 | F11: 1000 | G11: Рубль | H11: 2500 | I11: 450.82
A12: 5 | C12: Замена термостата | D12: 1 | E12: 700 | F12: 1000 | G12: Рубль | H12: 700 | I12: 126.23
A13: 6 | C13: Замена радиатора отопителя | D13: 1 | E13: 15000 | F13: 1 | G13: Рубль | H13: 15000 | I13: 2704.92
A14: 7 | C14: Замена дополнительного насоса отопителя | D14: 1 | E14: 500 | F14: 1000 | G14: Рубль | H14: 500 | I14: 90.16
A15: 8 | C15: ДиагносТИка АБС | D15: 1 | E15: 1000 | F15: 1000 | G15: Рубль | H15: 1 ооо.оо | I15: 180.33
A16: 9 | C16: Ремонт тормозной системы | D16: 1 | E16: 250О.СО | F16: 1000 | G16: Рубль | H16: 2 500.00 | I16: 450.82
A17: 10 | C17: Замена вакуумного усилителя | D17: 1 | E17: 1700 СО | F17: 1000 | G17: Рубль | H17: 1700 | I17: 306.56
A18: 11 | C18: Замена заднего рабочего цилиндра | D18: 1 | E18: 500 СО | F18: 1000 | G18: Рубль | H18: 500 | I18: 90.16
A19: 12 | C19: Токарные работы | D19: 1 | E19: 1500,СО | F19: 1000 | G19: Рубль | H19: 1500 | I19: 270.49
A20: 13 | C20: Ремонт электропроводки | D20: 1 | E20: 2000, СО | F20: 1000 | G20: Рубль | H20: 2000 | I20: 360.66
A21: итого работ: | D21: 14 | E21: на сумму: | H21: 29700 | I21: 535574
A23: Расходная накладная к заказ-наряду № 100160 от 27.03.2026
A24: № | B24: №кат. | C24: Наименование | D24: Кол-во | E24: Ед.изм, | F24: цена | G24: Всего | H24: в т.ч, НДС
A25: 1 | B25: 2 | C25: 3 | D25: 4 | E25: 6 | F25: 6 | G25: 7 | H25: 8
A26: 1 | B26: F01H7B0C42-HZ6 | C26: Свечи АУ-17Д8РМ стандарт "33" BA3 2108-70, 3М3 406-409 УМ3 4216 | D26: 1 | E26: кт | F26: 600 | G26: 60000 | H26: 108.2
A27: 2 | B27: 4073/05 | C27: катушка зажигания 405 Евро-3 (модуль) СОАТЭ | D27: 2 | E27: шт | F27: 1900 | G27: 3800 | H27: 685.25
A28: 3 | B28: LRC0363B | C28: Радиатор УА3-3163 алюминиевый да ЗМЗ-409,40904 IVECO EBPO-2.3 LUZAR | D28: 1 | E28: шт | F28: 18500 | G28: 18 500,00 | H28: 3336.07
A29: 4 | B29: GP 10620016 | C29: Термостат ГА3-24.3102.3110,3302.2705, 3151,3160 402,406. КАМА3-5320.4310, КАМА3-7401=60 G-PART | D29: 1 | E29: шт | F29: 460 | G29: 460 | H29: 82.95
A30: 5 | B30: LRH03831B | C30: Радиатор отоп алюм для а/м УАЗ 3163 Патриот (05 2012-)А/С Sanden | D30: 1 | E30: шт | F30: 4000 | G30: 4 000 00 | H30: 721.31
A31: 6 | B31: 32378001 | C31: Электродвигатель отопителя 32.3780-01 АЕ с насосом 12В, 8=18мм ГА3 3110, УАЗ 3742 АвтоЭлектрика | D31: 1 | E31: шт | F31: 1200 | G31: 1200 | H31: 216.39
A32: 7 | C32: трубка тормозная 0=5 L= 460mm | D32: 3 | E32: шт | F32: 260 | G32: 780 | H32: 140.66
A33: 8 | B33: 316300-350500801 | C33: Усилитель вакуумный УА3-3163 Патриот с ГГЦ (Чехия) (ОАО УАЗ) | D33: 1 | E33: шт | F33: 19500 | G33: 19500 | H33: 351639
A34: 9 | B34: СМР9001 | C34: Цилиндр тормозной задний 3302 Campar-autoparts | D34: 1 | E34: шт | F34: 800 | G34: 800 | H34: 144.26
A35: ТО | B35: ET9121820BLKRW | C35: Изолента мерная ABRO 19мм х 18.2м ABRO | D35: 1 | E35: шт | F35: 100 | G35: 100 | H35: 18.03
A36: 11 | B36: 707613 | D36: 2 | E36: шт | F36: 130 | G36: 260 | H36: 46.89
A38: 12 | B38: 614503 | C38: Антифриз Sintec LUXE G12+, 5 кг, красный | D38: 4 2 | E38: шт | F38: 950 | G38: 1900 | H38: 342.62
A39: итого материалов: | D39: 17 | E39: на сумму: | G39: 51900 | H39: 9359.02

Sheet 778
B1: ПОСТАВЩИК: ООО ФИРМА "СИГНАЛ"
B2: адрес: 364031, Чеченская Республика, г.Грозный, ул. Жуковского, д. 18
C4: Заказ-наряд № 100507 от 03.06.2026
B6: Заказчик: Общество с ограниченной ответственностью «Концепт» | H6: адрес заказчика : 364024, ЧР г.Грозный, ул.Назарбаева, д.92, оф. 6-05
B7: Автомобиль : Toyota Camry г/н Е 778 РА /15
B9: Цена автомототранспортного средства, определяемая по соглашению сторон __________________
B11: Плательщик: Общество с ограниченной ответственностью «Концепт»
B12: ИНН 2014030866 адрес: телефоны: +7 (989) 9002252
N14: в валюте
N15: Руб
C17: Выполненные работы по заказ-наряду № 100507 от 03.06.2026
B19: № | C19: № кат. | D19: Наименование | I19: Кол. оп. | J19: Цена | K19: Норма | L19: н/ч | M19: Всего | N19: в т.ч. НДС
B20: 1 | C20: 2 | D20: 3 | I20: 4 | J20: 5 | K20: 6 | L20: 7 | M20: 8 | N20: 9
B21: 1 | D21: Замена масла и масл фильтра | I21: 1 | J21: 700 | K21: 1 | L21: Рубль | M21: =J21*I21 -> 700 | N21: =M21*22/122 -> 126.22951
B22: 2 | D22: Замена салонного фильтра | I22: 1 | J22: 150 | K22: 1 | L22: Рубль | M22: =J22*I22 -> 150 | N22: =M22*22/122 -> 27.04918
B23: 3 | D23: Замена воздушного фильтра | I23: 1 | J23: 150 | K23: 1 | L23: Рубль | M23: =J23*I23 -> 150 | N23: =M23*22/122 -> 27.04918
B24: Итого работ: | I24: 3 | J24: на сумму: | M24: =M21+M22+M23 -> 1000 | N24: =M24*22/122 -> 180.32787
B26: Одна тысяча рублей 00 копеек
C28: Расходная накладная к заказ-наряду № 100507 от 03.06.2026
B30: № | C30: № кат. | D30: Наименование | J30: Кол-во | K30: Ед.изм. | L30: Цена | M30: Всего | N30: в т.ч. НДС
B31: 1 | C31: 2 | D31: 3 | J31: 4 | K31: 5 | L31: 6 | M31: 7 | N31: 8
B32: 1 | C32: TO1191 | D32: Фильтр масляный Alphard Camry Rav4 rx350 highlander Lexus ES Totachi | J32: 1 | K32: шт | L32: 450 | M32: =L32*J32 -> 450 | N32: =M32*22/122 -> 81.147541
B33: 2 | C33: FAP4625C | D33: Фильтр салона угольный TO Camry VIII,RAV4 V 18- Pilenga | J33: 1 | K33: шт | L33: 650 | M33: =L33*J33 -> 650 | N33: =M33*22/122 -> 117.21311
B34: 3 | C34: 08880-86084 | D34: Моторное масло Toyota Synthetic 5W-40, 5л | J34: 1 | K34: шт | L34: 6500 | M34: =L34*J34 -> 6500 | N34: =M34*22/122 -> 1172.1311
B35: 4 | C35: MFA 233 | D35: Фильтр воздушный Camry V70 MASUMA | J35: 1 | K35: шт | L35: 800 | M35: =L35*J35 -> 800 | N35: =M35*22/122 -> 144.2623
B36: Итого материалов: | J36: 4 | K36: на сумму: | M36: =M32+M33+M34+M35 -> 8400 | N36: =M36*22/122 -> 1514.7541
B38: Восемь тысяч четыреста рублей 00 копеек
L40: Итого по заказ-наряду : | M40: =M24+M36 -> 9400 | N40: =M40*20/120 -> 1566.6667
B42: Всего по заказ-наряду: Девять тысяч четыреста рублей 00 копеек, в т.ч. НДС 22%.
J45: Мастер _____________________ | K45: Механик СТО/
C47: Гарантии: Гарантия на работы: слесарные - 30 дней, электрические - 30 дней, оригинальные з/ч - 30 дней, з/ч, связанные с электрооборудованием, подачей топлива и системой впрыска - гарантии нет, неоригинальные з/ч - гарантии нет. Гарантийные обязательства на работы выполняются фирмой только при предъявлении акта приемки автомобиля и техпаспорта (доверенности).
B52: Дата: 03.06.2026 | J52: Заказчик ______________________ | K52: /Общество с ограниченной ответственностью «Концепт»/
J54: Плательщик ______________________ | K54: /Общество с ограниченной ответственностью «Концепт»/
B56: Причина обращения:

Sheet 0629
B1: ПОСТАВЩИК: ООО ФИРМА "СИГНАЛ"
B2: адрес: 364031, Чеченская Республика, г.Грозный, ул. Жуковского, д. 18
C4: Заказ-наряд № 100504 от 02.06.2026
B6: Заказчик: Общество с ограниченной ответственностью «Концепт» | H6: адрес заказчика : 364024, ЧР г.Грозный, ул.Назарбаева, д.92, оф. 6-05
B7: Автомобиль : ГАЗ 384064 гос. номер: О 0629 15
B9: Цена автомототранспортного средства, определяемая по соглашению сторон __________________
B11: Плательщик: Общество с ограниченной ответственностью «Концепт»
B12: ИНН 2014030866 адрес: телефоны: +7 (989) 9002252
N14: в валюте
N15: Руб
C17: Выполненные работы по заказ-наряду № 100504 от 02.06.2026
B19: № | C19: № кат. | D19: Наименование | I19: Кол. оп. | J19: Цена | K19: Норма | L19: н/ч | M19: Всего | N19: в т.ч. НДС
B20: 1 | C20: 2 | D20: 3 | I20: 4 | J20: 5 | K20: 6 | L20: 7 | M20: 8 | N20: 9
B21: 1 | D21: Диагностика ДВС | I21: 1 | J21: 1000 | K21: 1 | L21: Рубль | M21: =J21*I21 -> 1000 | N21: =M21*22/122 -> 180.32787
B22: 2 | D22: Замена муфты электромагнитной | I22: 1 | J22: 1700 | K22: 1 | L22: Рубль | M22: =J22*I22 -> 1700 | N22: =M22*22/122 -> 306.55738
B23: 3 | D23: Замена охлаждающей жидкости | I23: 1 | J23: 800 | K23: 1 | L23: Рубль | M23: =J23*I23 -> 800 | N23: =M23*22/122 -> 144.2623
B24: Итого работ: | I24: 3 | J24: на сумму: | M24: =M21+M22+M23 -> 3500 | N24: =M24*22/122 -> 631.14754
B26: Три тысячи пятьсот рублей 00 копеек.
C28: Расходная накладная к заказ-наряду № 100504 от 02.06.2026
B30: № | C30: № кат. | D30: Наименование | J30: Кол-во | K30: Ед.изм. | L30: Цена | M30: Всего | N30: в т.ч. НДС
B31: 1 | C31: 2 | D31: 3 | J31: 4 | K31: 5 | L31: 6 | M31: 7 | N31: 8
B32: 1 | D32: Муфта электромагнитная дв.4216 Г-3302 Бизнес н/о Термокам (6рк) | J32: 1 | K32: шт | L32: 5300 | M32: =L32*J32 -> 5300 | N32: =M32*22/122 -> 955.7377
B33: 2 | C33: 614503 | D33: Антифриз Sintec LUXE G12+, 5 кг, красный | J33: 2 | K33: шт | L33: 1000 | M33: =L33*J33 -> 2000 | N33: =M33*22/122 -> 360.65574
B34: Итого материалов: | J34: 3 | K34: на сумму: | M34: =M32+M33 -> 7300 | N34: =M34*22/122 -> 1316.3934
B36: Семь тысяч триста рублей 00 копеек
L38: Итого по заказ-наряду : | M38: =M24+M34 -> 10800 | N38: =M38*22/122 -> 1947.541
B40: Всего по заказ-наряду: Десять тысяч восемьсот рублей 00 копеек, в т.ч. НДС 22%.
J43: Мастер _____________________ | K43: Механик СТО/
C45: Гарантии: Гарантия на работы: слесарные - 30 дней, электрические - 30 дней, оригинальные з/ч - 30 дней, з/ч, связанные с электрооборудованием, подачей топлива и системой впрыска - гарантии нет, неоригинальные з/ч - гарантии нет. Гарантийные обязательства на работы выполняются фирмой только при предъявлении акта приемки автомобиля и техпаспорта (доверенности).
B50: Дата: 02.06.2026 | J50: Заказчик ______________________ | K50: /Общество с ограниченной ответственностью «Концепт»/
J52: Плательщик ______________________ | K52: /Общество с ограниченной ответственностью «Концепт»/
B54: Причина обращения:

Sheet 0774
B1: ПОСТАВЩИК: ООО ФИРМА "СИГНАЛ"
B2: адрес: 364031, Чеченская Республика, г.Грозный, ул. Жуковского, д. 18
C4: Заказ-наряд № 100510 от 03.06.2026
B6: Заказчик: Общество с ограниченной ответственностью «Концепт» | H6: адрес заказчика : 364024, ЧР г.Грозный, ул.Назарбаева, д.92, оф. 6-05
B7: Автомобиль : КИА СОРЕНТО гос. номер: О 0774 15
B9: Цена автомототранспортного средства, определяемая по соглашению сторон __________________
B11: Плательщик: Общество с ограниченной ответственностью «Концепт»
B12: ИНН 2014030866 адрес: телефоны: +7 (989) 9002252
N14: в валюте
N15: Руб
C17: Выполненные работы по заказ-наряду № 100510 от 03.06.2026
B19: № | C19: № кат. | D19: Наименование | I19: Кол. оп. | J19: Цена | K19: Норма | L19: н/ч | M19: Всего | N19: в т.ч. НДС
B20: 1 | C20: 2 | D20: 3 | I20: 4 | J20: 5 | K20: 6 | L20: 7 | M20: 8 | N20: 9
B21: 1 | D21: Замена масла и масл. Фильтра | I21: 1 | J21: 700 | K21: 1 | L21: Рубль | M21: =J21*I21 -> 700 | N21: =M21*22/122 -> 126.22951
B22: 2 | D22: Замена воздушного фильтра | I22: 1 | J22: 200 | K22: 1 | L22: Рубль | M22: =J22*I22 -> 200 | N22: =M22*22/122 -> 36.065574
B23: 3 | D23: Замена салонного фильтра | I23: 1 | J23: 200 | K23: 1 | L23: Рубль | M23: =J23*I23 -> 200 | N23: =M23*22/122 -> 36.065574
B24: 4 | D24: Диагностика подвески | I24: 1 | J24: 300 | K24: 1 | L24: Рубль | M24: =J24*I24 -> 300 | N24: =M24*22/122 -> 54.098361
B25: 5 | D25: Диагностика кондиционера | I25: 1 | J25: 500 | K25: 1 | L25: Рубль | M25: =J25*I25 -> 500 | N25: =M25*22/122 -> 90.163934
B26: Итого работ: | I26: 5 | J26: на сумму: | M26: =M21+M22+M23+M24+M25 -> 1900 | N26: =M26*22/122 -> 342.62295
B28: Одна тысяча девятьсот рублей 00 копеек
C30: Расходная накладная к заказ-наряду № 100510 от 03.06.2026
B32: № | C32: № кат. | D32: Наименование | J32: Кол-во | K32: Ед.изм. | L32: Цена | M32: Всего | N32: в т.ч. НДС
B33: 1 | C33: 2 | D33: 3 | J33: 4 | K33: 5 | L33: 6 | M33: 7 | N33: 8
B34: 1 | C34: 2630035531 | D34: Фильтр масляный для Хендай, Киа HYUNDAI-KIA | J34: 1 | K34: шт | L34: 1100 | M34: =L34*J34 -> 1100 | N34: =M34*22/122 -> 198.36066
B35: 2 | C35: AC58C | D35: Фильтр салонный угольный KIA Carnival III/,Sorento II (XM). | J35: 1 | K35: шт | L35: 400 | M35: =L35*J35 -> 400 | N35: =M35*22/122 -> 72.131148
B36: 3 | C36: 281132W100 | D36: Фильтр воздушный двигателя для Hyundai Santa Fe III 2012-2018; KIA Sorento (XM) 2014-2021 | J36: 1 | K36: шт | L36: 750 | M36: =L36*J36 -> 750 | N36: =M36*22/122 -> 135.2459
B37: 4 | C37: 15595E | D37: Масло Ford Formula F 5W30 5л. | J37: 1 | K37: шт | L37: 5550 | M37: =L37*J37 -> 5550 | N37: =M37*22/122 -> 1000.8197
B38: Итого материалов: | J38: 4 | K38: на сумму: | M38: =M34+M35+M36+M37 -> 7800 | N38: =M38*22/122 -> 1406.5574
B40: Семь тысяч восемьсот рублей 00 копеек
L42: Итого по заказ-наряду : | M42: =M26+M38 -> 9700 | N42: =M42*22/122 -> 1749.1803
B44: Всего по заказ-наряду: Девять тысяч семьсот рублей 00 копеек
J47: Мастер _____________________ | K47: Механик СТО/
C49: Гарантии: Гарантия на работы: слесарные - 30 дней, электрические - 30 дней, оригинальные з/ч - 30 дней, з/ч, связанные с электрооборудованием, подачей топлива и системой впрыска - гарантии нет, неоригинальные з/ч - гарантии нет. Гарантийные обязательства на работы выполняются фирмой только при предъявлении акта приемки автомобиля и техпаспорта (доверенности).
B54: Дата: 03.06.2026 | J54: Заказчик ______________________ | K54: /Общество с ограниченной ответственностью «Концепт»/
J56: Плательщик ______________________ | K56: /Общество с ограниченной ответственностью «Концепт»/
B58: Причина обращения:

Sheet 153
B1: ПОСТАВЩИК: ООО ФИРМА "СИГНАЛ"
B2: адрес: 364031, Чеченская Республика, г.Грозный, ул. Жуковского, д. 18
C4: Заказ-наряд № 100094 от 28.02.2026
B6: Заказчик: Общество с ограниченной ответственностью «Концепт» | H6: адрес заказчика : 364024, ЧР г.Грозный, ул.Назарбаева, д.92, оф. 6-05
B7: Автомобиль :Лада Веста гос. номер: Е153РА15
B9: Цена автомототранспортного средства, определяемая по соглашению сторон __________________
B11: Плательщик: Общество с ограниченной ответственностью «Концепт»
B12: ИНН 2014030866 адрес: телефоны: +7 (989) 9002252
N14: в валюте
N15: Руб
C17: Выполненные работы по заказ-наряду № 100094 от 28.02.2026
B19: № | C19: № кат. | D19: Наименование | I19: Кол. оп. | J19: Цена | K19: Норма | L19: н/ч | M19: Всего | N19: в т.ч. НДС
B20: 1 | C20: 2 | D20: 3 | I20: 4 | J20: 5 | K20: 6 | L20: 7 | M20: 8 | N20: 9
B21: 1 | D21: Замена комплекта ГРМ | I21: 1 | J21: 4500 | K21: 1 | L21: Рубль | M21: =J21*I21 -> 4500 | N21: =M21*22/122 -> 811.47541
B22: 2 | D22: Замена ремня генератора | I22: 1 | J22: 1000 | K22: 1 | L22: Рубль | M22: =J22*I22 -> 1000 | N22: =M22*22/122 -> 180.32787
B23: 3 | D23: Замена прокладки бензонасоса | I23: 1 | J23: 1000 | K23: 1 | L23: Рубль | M23: =J23*I23 -> 1000 | N23: =M23*22/122 -> 180.32787
B24: 4 | D24: Замена масла и масл фильтра | I24: 1 | J24: 500 | K24: 1 | L24: Рубль | M24: =J24*I24 -> 500 | N24: =M24*22/122 -> 90.163934
B25: 5 | D25: Замена воздушного фильтра | I25: 1 | J25: 150 | K25: 1 | L25: Рубль | M25: =J25*I25 -> 150 | N25: =M25*22/122 -> 27.04918
B26: 6 | D26: Замена салонного фильтра | I26: 1 | J26: 150 | K26: 1 | L26: Рубль | M26: =J26*I26 -> 150 | N26: =M26*22/122 -> 27.04918
B27: Итого работ: | I27: 6 | J27: на сумму: | M27: =M21+M22+M23+M24+M25+M26 -> 7300 | N27: =M27*22/122 -> 1316.3934
B29: Семь тысяч триста рублей 00 копеек.
C31: Расходная накладная к заказ-наряду № 100094 от 28.02.2026
B33: № | C33: № кат. | D33: Наименование | J33: Кол-во | K33: Ед.изм. | L33: Цена | M33: Всего | N33: в т.ч. НДС
B34: 1 | C34: 2 | D34: 3 | J34: 4 | K34: 5 | L34: 6 | M34: 7 | N34: 8
B35: 1 | C35: 6PK1038 | D35: Ремень приводной Gates Лада Веста | J35: 1 | K35: шт | L35: 1800 | M35: =L35*J35 -> 1800 | N35: =M35*22/122 -> 324.59016
B36: 2 | C36: K015631XS | D36: Комплект ГРМ Лада Ларгус, Веста, Х Рей, GATES K015631XS (дв. ВАЗ, 16 клапанов) | J36: 1 | K36: кт | L36: 7250 | M36: =L36*J36 -> 7250 | N36: =M36*22/122 -> 1307.377
B37: 3 | C37: 21800-1101138-00 | D37: Прокладка бензонасоса Лада Веста, оригинал | J37: 1 | K37: шт | L37: 350 | M37: =L37*J37 -> 350 | N37: =M37*22/122 -> 63.114754
B38: 4 | C38: 322405 | D38: Моторное масло Rolf GT SAE 5W-40 4л. API SN/CF | J38: 1 | K38: шт | L38: 3000 | M38: =L38*J38 -> 3000 | N38: =M38*22/122 -> 540.98361
B39: 5 | C39: 77143 | D39: Фильтр воздушный ВАЗ 2180 Vesta н/образца 1.6 19- NAC | J39: 1 | K39: шт | L39: 450 | M39: =L39*J39 -> 450 | N39: =M39*22/122 -> 81.147541
B40: 6 | C40: LF105 | D40: Фильтр масляный LADA 08-112 FINWHALE | J40: 1 | K40: шт | L40: 400 | M40: =L40*J40 -> 400 | N40: =M40*22/122 -> 72.131148
B41: 7 | C41: AG448 CF | D41: Фильтр салона LADA Vesta, X-RAY Goodwill | J41: 1 | K41: шт | L41: 450 | M41: =L41*J41 -> 450 | N41: =M41*22/122 -> 81.147541
B42: Итого материалов: | J42: 8 | K42: на сумму: | M42: =M35+M36+M37+M38+M39+M40+M41 -> 13700 | N42: =M42*22/122 -> 2470.4918
B44: Тринадцать тысяч семьсот рублей 00 копеек
L46: Итого по заказ-наряду : | M46: =M27+M42 -> 21000 | N46: =M46*22/122 -> 3786.8852
B48: Всего по заказ-наряду: Двадцать одна тысяча рублей 00 копеек, в т.ч. НДС 22%.
J51: Мастер _____________________ | K51: Механик СТО/
C53: Гарантии: Гарантия на работы: слесарные - 30 дней, электрические - 30 дней, оригинальные з/ч - 30 дней, з/ч, связанные с электрооборудованием, подачей топлива и системой впрыска - гарантии нет, неоригинальные з/ч - гарантии нет. Гарантийные обязательства на работы выполняются фирмой только при предъявлении акта приемки автомобиля и техпаспорта (доверенности).
B58: Дата: 28.02.2026 | J58: Заказчик ______________________ | K58: /Общество с ограниченной ответственностью «Концепт»/
J60: Плательщик ______________________ | K60: /Общество с ограниченной ответственностью «Концепт»/
B62: Причина обращения:

Sheet 228
B1: ПОСТАВЩИК: ООО ФИРМА "СИГНАЛ"
B2: адрес: 364031, Чеченская Республика, г.Грозный, ул. Жуковского, д. 18
C4: Заказ-наряд № 100094 от 27.02.2026
B6: Заказчик: Общество с ограниченной ответственностью «Концепт» | H6: адрес заказчика : 364024, ЧР г.Грозный, ул.Назарбаева, д.92, оф. 6-05
B7: Автомобиль : ВАЗ 219010 г/н В228ОХ/15
B9: Цена автомототранспортного средства, определяемая по соглашению сторон __________________
B11: Плательщик: Общество с ограниченной ответственностью «Концепт»
B12: ИНН 2014030866 адрес: телефоны: +7 (989) 9002252
N14: в валюте
N15: Руб
C17: Выполненные работы по заказ-наряду № 100094 от 27.02.2026
B19: № | C19: № кат. | D19: Наименование | I19: Кол. оп. | J19: Цена | K19: Норма | L19: н/ч | M19: Всего | N19: в т.ч. НДС
B20: 1 | C20: 2 | D20: 3 | I20: 4 | J20: 5 | K20: 6 | L20: 7 | M20: 8 | N20: 9
B21: 1 | D21: Замена переднего амортизатора | I21: 2 | J21: 1000 | K21: 1 | L21: Рубль | M21: =J21*I21 -> 2000 | N21: =M21*22/122 -> 360.65574
B22: 2 | D22: Замена кронштейна растяжки | I22: 2 | J22: 400 | K22: 1 | L22: Рубль | M22: =J22*I22 -> 800 | N22: =M22*22/122 -> 144.2623
B23: 3 | D23: Замена пер-х торм-х колодок | I23: 1 | J23: 500 | K23: 1 | L23: Рубль | M23: =J23*I23 -> 500 | N23: =M23*22/122 -> 90.163934
B24: 4 | D24: Замена подшипника задней ступицы | I24: 1 | J24: 800 | K24: 1 | L24: Рубль | M24: =J24*I24 -> 800 | N24: =M24*22/122 -> 144.2623
B25: 5 | D25: Замена сайлентблоков нижних рычагов | I25: 1 | J25: 1600 | K25: 1 | L25: Рубль | M25: =J25*I25 -> 1600 | N25: =M25*22/122 -> 288.52459
B26: 6 | D26: Замена стойки стабилизатора | I26: 2 | J26: 250 | K26: 1 | L26: Рубль | M26: =J26*I26 -> 500 | N26: =M26*22/122 -> 90.163934
B27: 7 | D27: Замена масла и масл. Фильтра | I27: 1 | J27: 500 | K27: 1 | L27: Рубль | M27: =J27*I27 -> 500 | N27: =M27*22/122 -> 90.163934
B28: 8 | D28: Замена воздушного фильтра | I28: 1 | J28: 200 | K28: 1 | L28: Рубль | M28: =J28*I28 -> 200 | N28: =M28*22/122 -> 36.065574
B29: 9 | D29: Регулировка рулевой рейки | I29: 1 | J29: 300 | K29: 1 | L29: Рубль | M29: =J29*I29 -> 300 | N29: =M29*22/122 -> 54.098361
B30: 10 | D30: Сход-развал | I30: 1 | J30: 1500 | K30: 1 | L30: Рубль | M30: =J30*I30 -> 1500 | N30: =M30*22/122 -> 270.4918
B31: 11 | D31: Диагностика ДВС | I31: 1 | J31: 700 | K31: 1 | L31: Рубль | M31: =J31*I31 -> 700 | N31: =M31*22/122 -> 126.22951
B32: Итого работ: | I32: 14 | J32: на сумму: | M32: =M21+M22+M23+M24+M25+M26+M27+M28+M29+M30+M31 -> 9400 | N32: =M32*22/122 -> 1695.082
B34: Девять тысяч четыреста рублей 00 копеек.
C36: Расходная накладная к заказ-наряду № 100094 от 27.02.2026
B38: № | C38: № кат. | D38: Наименование | J38: Кол-во | K38: Ед.изм. | L38: Цена | M38: Всего | N38: в т.ч. НДС
B39: 1 | C39: 2 | D39: 3 | J39: 4 | K39: 5 | L39: 6 | M39: 7 | N39: 8
B40: 1 | C40: 2190-2904049 | D40: Кронштейн переднего шарнира растяжки (краб) (в сборе) Лада Гранта | J40: 2 | K40: шт | L40: 750 | M40: =L40*J40 -> 1500 | N40: =M40*22/122 -> 270.4918
B41: 2 | C41: HF 350 805 | D41: Колодка перед Ваз 2110-2170 HOFER | J41: 1 | K41: кт | L41: 600 | M41: =L41*J41 -> 600 | N41: =M41*22/122 -> 108.19672
B42: 3 | C42: HB321 | D42: Подшипник ступ.LADA 2108-09 99 2110-12 KALINA 86- зад. FINWHALE | J42: 1 | K42: шт | L42: 1100 | M42: =L42*J42 -> 1100 | N42: =M42*22/122 -> 198.36066
B43: 4 | C43: 10846 | D43: Шарнир растяжки задний сайлентблок ромашки переднего рычага - ваз 2108-2170 , 2190 гранта БМРТ | J43: 1 | K43: кт | L43: 550 | M43: =L43*J43 -> 550 | N43: =M43*22/122 -> 99.180328
B44: 5 | C44: 21100290419282 | D44: Шар опора Ваз 2108-10, 2170 усил ОАО АВТОВАЗ | J44: 1 | K44: шт | L44: 750 | M44: =L44*J44 -> 750 | N44: =M44*22/122 -> 135.2459
B45: 6 | C45: 88888R01040400 | D45: Масло LADA PROFESSIONAL 10W40 моторное полусинтетическое 4 л | J45: 1 | K45: шт | L45: 2000 | M45: =L45*J45 -> 2000 | N45: =M45*22/122 -> 360.65574
B46: 7 | C46: LF105 | D46: Фильтр масляный LADA 08-112 FINWHALE | J46: 1 | K46: шт | L46: 400 | M46: =L46*J46 -> 400 | N46: =M46*22/122 -> 72.131148
B47: 8 | C47: SO1029 | D47: Фильтр воздушный LADA 2108-099/2110-12/2113-15/GRANTA/KALINA/PRIORA SUFIX | J47: 1 | K47: шт | L47: 350 | M47: =L47*J47 -> 350 | N47: =M47*22/122 -> 63.114754
B48: 9 | C48: 10840 | D48: Сайлентблоки нижнего рычага передней подвески - ваз 2108, 2110, калина, приора, гранта БМРТ | J48: 1 | K48: кт | L48: 300 | M48: =L48*J48 -> 300 | N48: =M48*22/122 -> 54.098361
B49: 10 | C49: 4008 | D49: Смазка многоцелевая RC-40, 210 мл BiBiCare | J49: 1 | K49: шт | L49: 250 | M49: =L49*J49 -> 250 | N49: =M49*22/122 -> 45.081967
B50: 11 | C50: 19065 | D50: Стойка стабилизатора Ваз 2190 (серьги) БМРТ - Ломов | J50: 1 | K50: кт | L50: 500 | M50: =L50*J50 -> 500 | N50: =M50*22/122 -> 90.163934
B51: 12 | C51: EM20892 | D51: Амортизаторные стойки передней подвески для а/м ВАЗ 2190 (2190-2905002/3) (2шт) | J51: 1 | K51: кт | L51: 7600 | M51: =L51*J51 -> 7600 | N51: =M51*22/122 -> 1370.4918
B52: Итого материалов: | J52: 13 | K52: на сумму: | M52: =M40+M41+M42+M43+M44+M45+M46+M47+M48+M49+M50+M51 -> 15900 | N52: =M52*22/122 -> 2867.2131
B54: Пятнадцать тысяч девятьсот рублей 00 копеек
L56: Итого по заказ-наряду : | M56: =M32+M52 -> 25300 | N56: =M56*22/122 -> 4562.2951
B58: Всего по заказ-наряду: Двадцать пять тысяч триста рублей 00 копеек, в т.ч. НДС 22%.
J61: Мастер _____________________ | K61: Механик СТО/
C63: Гарантии: Гарантия на работы: слесарные - 30 дней, электрические - 30 дней, оригинальные з/ч - 30 дней, з/ч, связанные с электрооборудованием, подачей топлива и системой впрыска - гарантии нет, неоригинальные з/ч - гарантии нет. Гарантийные обязательства на работы выполняются фирмой только при предъявлении акта приемки автомобиля и техпаспорта (доверенности).
B68: Дата: 27.02.2026 | J68: Заказчик ______________________ | K68: /Общество с ограниченной ответственностью «Концепт»/
J70: Плательщик ______________________ | K70: /Общество с ограниченной ответственностью «Концепт»/
B72: Причина обращения:

Sheet 0629 (2)
B1: ПОСТАВЩИК: ООО ФИРМА "СИГНАЛ"
B2: адрес: 364031, Чеченская Республика, г.Грозный, ул. Жуковского, д. 18
C4: Заказ-наряд № 100093 от 27.02.2026
B6: Заказчик: Общество с ограниченной ответственностью «Концепт» | H6: адрес заказчика : 364024, ЧР г.Грозный, ул.Назарбаева, д.92, оф. 6-05
B7: Автомобиль : Газель гос. номер: О 0629 15
B9: Цена автомототранспортного средства, определяемая по соглашению сторон __________________
B11: Плательщик: Общество с ограниченной ответственностью «Концепт»
B12: ИНН 2014030866 адрес: телефоны: +7 (989) 9002252
N14: в валюте
N15: Руб
C17: Выполненные работы по заказ-наряду № 100093 от 27.02.2026
B19: № | C19: № кат. | D19: Наименование | I19: Кол. оп. | J19: Цена | K19: Норма | L19: н/ч | M19: Всего | N19: в т.ч. НДС
B20: 1 | C20: 2 | D20: 3 | I20: 4 | J20: 5 | K20: 6 | L20: 7 | M20: 8 | N20: 9
B21: 1 | D21: Замена сцепления | I21: 1 | J21: 4000 | K21: 1 | L21: Рубль | M21: =J21*I21 -> 4000 | N21: =M21*22/122 -> 721.31148
B22: 2 | D22: Смазка шкворней | I22: 1 | J22: 300 | K22: 1 | L22: Рубль | M22: =J22*I22 -> 300 | N22: =M22*22/122 -> 54.098361
B23: 3 | D23: Проверка и долив масла в силовые агрегаты | I23: 1 | J23: 500 | K23: 1 | L23: Рубль | M23: =J23*I23 -> 500 | N23: =M23*22/122 -> 90.163934
B24: Итого работ: | I24: 3 | J24: на сумму: | M24: =M21+M22+M23 -> 4800 | N24: =M24*22/122 -> 865.57377
B26: Четыре тысячи восемьсот рублей 00 копеек.
C28: Расходная накладная к заказ-наряду № 100093 от 27.02.2026
B30: № | C30: № кат. | D30: Наименование | J30: Кол-во | K30: Ед.изм. | L30: Цена | M30: Всего | N30: в т.ч. НДС
B31: 1 | C31: 2 | D31: 3 | J31: 4 | K31: 5 | L31: 6 | M31: 7 | N31: 8
B32: 1 | C32: 71455 | D32: Сцепление в сборе для а/м ГАЗ 3302 Бизнес "RD (ТАЯ)" | J32: 1 | K32: кт | L32: 9800 | M32: =L32*J32 -> 9800 | N32: =M32*22/122 -> 1767.2131
B33: 2 | C33: 2389901363 | D33: Масло трансмиссионное Gazpromneft Super Т-3 85W-90 1 л | J33: 1 | K33: шт | L33: 400 | M33: =L33*J33 -> 400 | N33: =M33*22/122 -> 72.131148
B34: Итого материалов: | J34: 2 | K34: на сумму: | M34: =M32+M33 -> 10200 | N34: =M34*22/122 -> 1839.3443
B36: Десять тысяч двести рублей 00 копеек
L38: Итого по заказ-наряду : | M38: =M24+M34 -> 15000 | N38: =M38*22/122 -> 2704.918
B40: Всего по заказ-наряду: Пятнадцать тысяч рублей 00 копеек, в т.ч. НДС 22%.
J43: Мастер _____________________ | K43: Механик СТО/
C45: Гарантии: Гарантия на работы: слесарные - 30 дней, электрические - 30 дней, оригинальные з/ч - 30 дней, з/ч, связанные с электрооборудованием, подачей топлива и системой впрыска - гарантии нет, неоригинальные з/ч - гарантии нет. Гарантийные обязательства на работы выполняются фирмой только при предъявлении акта приемки автомобиля и техпаспорта (доверенности).
B50: Дата: 27.02.2026 | J50: Заказчик ______________________ | K50: /Общество с ограниченной ответственностью «Концепт»/
J52: Плательщик ______________________ | K52: /Общество с ограниченной ответственностью «Концепт»/
B54: Причина обращения:

Sheet 531
B1: ПОСТАВЩИК: ООО ФИРМА "СИГНАЛ"
B2: адрес: 364031, Чеченская Республика, г.Грозный, ул. Жуковского, д. 18
C4: Заказ-наряд № 100092 от 27.02.2026
B6: Заказчик: Общество с ограниченной ответственностью «Концепт» | H6: адрес заказчика : 364024, ЧР г.Грозный, ул.Назарбаева, д.92, оф. 6-05
B7: Автомобиль : Форд Транзит гос. номер: В531НХ/15
B9: Цена автомототранспортного средства, определяемая по соглашению сторон __________________
B11: Плательщик: Общество с ограниченной ответственностью «Концепт»
B12: ИНН 2014030866 адрес: телефоны: +7 (989) 9002252
N14: в валюте
N15: Руб
C17: Выполненные работы по заказ-наряду № 100092 от 27.02.2026
B19: № | C19: № кат. | D19: Наименование | I19: Кол. оп. | J19: Цена | K19: Норма | L19: н/ч | M19: Всего | N19: в т.ч. НДС
B20: 1 | C20: 2 | D20: 3 | I20: 4 | J20: 5 | K20: 6 | L20: 7 | M20: 8 | N20: 9
B21: 1 | D21: Замена масла и масл фильтра | I21: 1 | J21: 700 | K21: 1 | L21: Рубль | M21: =J21*I21 -> 700 | N21: =M21*22/122 -> 126.22951
B22: 2 | D22: Замена воздушного фильтра | I22: 1 | J22: 200 | K22: 1 | L22: Рубль | M22: =J22*I22 -> 200 | N22: =M22*22/122 -> 36.065574
B23: 3 | D23: Замена масла в редукторе | I23: 1 | J23: 600 | K23: 1 | L23: Рубль | M23: =J23*I23 -> 600 | N23: =M23*22/122 -> 108.19672
B24: 4 | D24: Замена масла в КПП | I24: 1 | J24: 500 | K24: 1 | L24: Рубль | M24: =J24*I24 -> 500 | N24: =M24*22/122 -> 90.163934
B25: 5 | D25: Замена салонного фильтра | I25: 1 | J25: 200 | K25: 1 | L25: Рубль | M25: =J25*I25 -> 200 | N25: =M25*22/122 -> 36.065574
B26: 6 | D26: Замена топливного фильтра | I26: 1 | J26: 600 | K26: 1 | L26: Рубль | M26: =J26*I26 -> 600 | N26: =M26*22/122 -> 108.19672
B27: 7 | D27: Ремонт стабилизатора | I27: 1 | J27: 600 | K27: 1 | L27: Рубль | M27: =J27*I27 -> 600 | N27: =M27*22/122 -> 108.19672
B28: Итого работ: | I28: 7 | J28: на сумму: | M28: =M21+M22+M23+M24+M25+M26+M27 -> 3400 | N28: =M28*22/122 -> 613.11475
B30: Три тысячи четыреста рублей 00 копеек.
C32: Расходная накладная к заказ-наряду № 100092 от 27.02.2026
B34: № | C34: № кат. | D34: Наименование | J34: Кол-во | K34: Ед.изм. | L34: Цена | M34: Всего | N34: в т.ч. НДС
B35: 1 | C35: 2 | D35: 3 | J35: 4 | K35: 5 | L35: 6 | M35: 7 | N35: 8
B36: 1 | C36: AG484CF | D36: Фильтр салонный для а/м FORD Transit / Форд Транзит, Goodwill | J36: 1 | K36: шт | L36: 700 | M36: =L36*J36 -> 700 | N36: =M36*22/122 -> 126.22951
B37: 2 | C37: AG 227 | D37: Фильтр воздушный FORD TRANSIT GOODWILL | J37: 1 | K37: шт | L37: 700 | M37: =L37*J37 -> 700 | N37: =M37*22/122 -> 126.22951
B38: 3 | C38: OG142HQ | D38: Фильтр масляный CITROEN JumperIII, FORD Transi Goodwill | J38: 1 | K38: шт | L38: 550 | M38: =L38*J38 -> 550 | N38: =M38*22/122 -> 99.180328
B39: 4 | C39: 15595E | D39: Масло Ford Formula F 5W30 5л. | J39: 2 | K39: шт | L39: 5400 | M39: =L39*J39 -> 10800 | N39: =M39*22/122 -> 1947.541
B40: 5 | C40: 122110700101999 | D40: Масло трансмиссионное RAVENOL DGL LS GL-5 75W85 синт.1л | J40: 3 | K40: шт | L40: 3850 | M40: =L40*J40 -> 11550 | N40: =M40*22/122 -> 2082.7869
B41: 6 | C41: 122110400101999 | D41: Масло КПП трансмиссионное RAVENOL MTF-3 75W синт.1л | J41: 3 | K41: шт | L41: 3000 | M41: =L41*J41 -> 9000 | N41: =M41*22/122 -> 1622.9508
B42: 7 | C42: FG129 | D42: Фильтр топливный FORD Transit 2012 (2,2 Duratorg TDCi) GOODWILL | J42: 1 | K42: шт | L42: 1200 | M42: =L42*J42 -> 1200 | N42: =M42*22/122 -> 216.39344
B43: Итого материалов: | J43: 12 | K43: на сумму: | M43: =M36+M37+M38+M39+M40+M41+M42 -> 34500 | N43: =M43*22/122 -> 6221.3115
B45: Тридцать четыре тысячи пятьсот рублей 00 копеек
L47: Итого по заказ-наряду : | M47: =M28+M43 -> 37900 | N47: =M47*22/122 -> 6834.4262
B49: Всего по заказ-наряду: Тридцать семь тысяч девятьсот рублей 00 копеек, в т.ч. НДС 22%.
J52: Мастер _____________________ | K52: Механик СТО/
C54: Гарантии: Гарантия на работы: слесарные - 30 дней, электрические - 30 дней, оригинальные з/ч - 30 дней, з/ч, связанные с электрооборудованием, подачей топлива и системой впрыска - гарантии нет, неоригинальные з/ч - гарантии нет. Гарантийные обязательства на работы выполняются фирмой только при предъявлении акта приемки автомобиля и техпаспорта (доверенности).
B59: Дата: 27.02.2026 | J59: Заказчик ______________________ | K59: /Общество с ограниченной ответственностью «Концепт»/
J61: Плательщик ______________________ | K61: /Общество с ограниченной ответственностью «Концепт»/
B63: Причина обращения:

Sheet 678
B1: ПОСТАВЩИК: ООО ФИРМА "СИГНАЛ"
B2: адрес: 364031, Чеченская Республика, г.Грозный, ул. Жуковского, д. 18
C4: Заказ-наряд № 100091 от 25.02.2026
B6: Заказчик: Общество с ограниченной ответственностью «Концепт» | H6: адрес заказчика : 364024, ЧР г.Грозный, ул.Назарбаева, д.92, оф. 6-05
B7: Автомобиль : Лада Нива 2131 гос. номер: А 678 ХМ /126
B9: Цена автомототранспортного средства, определяемая по соглашению сторон __________________
B11: Плательщик: Общество с ограниченной ответственностью «Концепт»
B12: ИНН 2014030866 адрес: телефоны: +7 (989) 9002252
N14: в валюте
N15: Руб
C17: Выполненные работы по заказ-наряду № 100091 от 25.02.2026
B19: № | C19: № кат. | D19: Наименование | I19: Кол. оп. | J19: Цена | K19: Норма | L19: н/ч | M19: Всего | N19: в т.ч. НДС
B20: 1 | C20: 2 | D20: 3 | I20: 4 | J20: 5 | K20: 6 | L20: 7 | M20: 8 | N20: 9
B21: 1 | D21: Замена масла и масл фильтра | I21: 1 | J21: 500 | K21: 1 | L21: Рубль | M21: =J21*I21 -> 500 | N21: =M21*22/122 -> 90.163934
B22: 2 | D22: Замена воздушного фильтра | I22: 1 | J22: 200 | K22: 1 | L22: Рубль | M22: =J22*I22 -> 200 | N22: =M22*22/122 -> 36.065574
B23: Итого работ: | I23: 2 | J23: на сумму: | M23: =M21+M22 -> 700 | N23: =M23*22/122 -> 126.22951
B25: Семьсот рублей 00 копеек.
C27: Расходная накладная к заказ-наряду № 100091 от 25.02.2026
B29: № | C29: № кат. | D29: Наименование | J29: Кол-во | K29: Ед.изм. | L29: Цена | M29: Всего | N29: в т.ч. НДС
B30: 1 | C30: 2 | D30: 3 | J30: 4 | K30: 5 | L30: 6 | M30: 7 | N30: 8
B31: 1 | C31: LF105 | D31: Фильтр масляный LADA 08-112 FINWHALE | J31: 1 | K31: шт | L31: 400 | M31: =L31*J31 -> 400 | N31: =M31*22/122 -> 72.131148
B32: 2 | C32: SO1029 | D32: Фильтр воздушный LADA 2108-099/2110-12/2113-15/GRANTA/KALINA/PRIORA SUFIX | J32: 1 | K32: шт | L32: 350 | M32: =L32*J32 -> 350 | N32: =M32*22/122 -> 63.114754
B33: 3 | C33: 3705304 | D33: Масло моторное Лукойл Люкс 10W-40 (4л) | J33: 1 | K33: шт | L33: 1150 | M33: =L33*J33 -> 1150 | N33: =M33*22/122 -> 207.37705
B34: Итого материалов: | J34: 3 | K34: на сумму: | M34: =M31+M32+M33 -> 1900 | N34: =M34*22/122 -> 342.62295
B36: Одна тысяча девятьсот рублей 00 копеек
L38: Итого по заказ-наряду : | M38: =M23+M34 -> 2600 | N38: =M38*22/122 -> 468.85246
B40: Всего по заказ-наряду: Две тысячи шестьсот рублей 00 копеек, в т.ч. НДС 22%.
J43: Мастер _____________________ | K43: Механик СТО/
C45: Гарантии: Гарантия на работы: слесарные - 30 дней, электрические - 30 дней, оригинальные з/ч - 30 дней, з/ч, связанные с электрооборудованием, подачей топлива и системой впрыска - гарантии нет, неоригинальные з/ч - гарантии нет. Гарантийные обязательства на работы выполняются фирмой только при предъявлении акта приемки автомобиля и техпаспорта (доверенности).
B50: Дата: 25.02.2026 | J50: Заказчик ______________________ | K50: /Общество с ограниченной ответственностью «Концепт»/
J52: Плательщик ______________________ | K52: /Общество с ограниченной ответственностью «Концепт»/
B54: Причина обращения:

Sheet 261
B1: ПОСТАВЩИК: ООО ФИРМА "СИГНАЛ"
B2: адрес: 364031, Чеченская Республика, г.Грозный, ул. Жуковского, д. 18
C4: Заказ-наряд № 100090 от 24.02.2026
B6: Заказчик: Общество с ограниченной ответственностью «Концепт» | H6: адрес заказчика : 364024, ЧР г.Грозный, ул.Назарбаева, д.92, оф. 6-05
B7: Автомобиль : УАЗ Есаул гос. номер: С 261 ВС /126
B9: Цена автомототранспортного средства, определяемая по соглашению сторон __________________
B11: Плательщик: Общество с ограниченной ответственностью «Концепт»
B12: ИНН 2014030866 адрес: телефоны: +7 (989) 9002252
N14: в валюте
N15: Руб
C17: Выполненные работы по заказ-наряду № 100090 от 24.02.2026
B19: № | C19: № кат. | D19: Наименование | I19: Кол. оп. | J19: Цена | K19: Норма | L19: н/ч | M19: Всего | N19: в т.ч. НДС
B20: 1 | C20: 2 | D20: 3 | I20: 4 | J20: 5 | K20: 6 | L20: 7 | M20: 8 | N20: 9
B21: 1 | D21: Диагностика тормозной системы | I21: 1 | J21: 300 | K21: 1 | L21: Рубль | M21: =J21*I21 -> 300 | N21: =M21*22/122 -> 54.098361
B22: 2 | D22: Замена пер-х торм-х колодок | I22: 1 | J22: 700 | K22: 1 | L22: Рубль | M22: =J22*I22 -> 700 | N22: =M22*22/122 -> 126.22951
B23: 3 | D23: Замена правого торм суппорта | I23: 1 | J23: 600 | K23: 1 | L23: Рубль | M23: =J23*I23 -> 600 | N23: =M23*22/122 -> 108.19672
B24: 4 | D24: Прокачка тормозной системы | I24: 1 | J24: 400 | K24: 1 | L24: Рубль | M24: =J24*I24 -> 400 | N24: =M24*22/122 -> 72.131148
B25: 5 | D25: Проверка и долив масла в силовые агрегаты | I25: 1 | J25: 800 | K25: 1 | L25: Рубль | M25: =J25*I25 -> 800 | N25: =M25*22/122 -> 144.2623
B26: 6 | D26: Диагностика подвески | I26: 1 | J26: 300 | K26: 1 | L26: Рубль | M26: =J26*I26 -> 300 | N26: =M26*22/122 -> 54.098361
B27: 7 | D27: Замена нижних втулок амортизатора | I27: 2 | J27: 400 | K27: 1 | L27: Рубль | M27: =J27*I27 -> 800 | N27: =M27*22/122 -> 144.2623
B28: 8 | D28: Замена сальника хвостовика | I28: 1 | J28: 600 | K28: 1 | L28: Рубль | M28: =J28*I28 -> 600 | N28: =M28*22/122 -> 108.19672
B29: 9 | D29: Замена ремня генератора | I29: 1 | J29: 1000 | K29: 1 | L29: Рубль | M29: =J29*I29 -> 1000 | N29: =M29*22/122 -> 180.32787
B30: 10 | D30: Регулировка шкворня | I30: 2 | J30: 600 | K30: 1 | L30: Рубль | M30: =J30*I30 -> 1200 | N30: =M30*22/122 -> 216.39344
B31: 11 | D31: Замена радиатора отопителя | I31: 1 | J31: 15000 | K31: 1 | L31: Рубль | M31: =J31*I31 -> 15000 | N31: =M31*22/122 -> 2704.918
B32: 12 | D32: Замена электровентилятора отопителя | I32: 1 | J32: 1500 | K32: 1 | L32: Рубль | M32: =J32*I32 -> 1500 | N32: =M32*22/122 -> 270.4918
... B35: 15 | D35: Токарные работы | I35: 1 | J35: 600 | K35: 1 | L35: Рубль | M35: =J35*I35 -> 600 | N35: =M35*22/122 -> 108.19672
B36: Итого работ: | I36: 17 | J36: на сумму: | M36: =M21+M22+M23+M24+M25+M26+M27+M28+M29+M30+M31+M32+M33+M34+M35 -> 28500 | N36: =M36*22/122 -> 5139.3443
B38: Двадцать восемь тысяч пятьсот рублей 00 копеек.
C40: Расходная накладная к заказ-наряду № 100090 от 24.02.2026
B42: № | C42: № кат. | D42: Наименование | J42: Кол-во | K42: Ед.изм. | L42: Цена | M42: Всего | N42: в т.ч. НДС
B43: 1 | C43: 2 | D43: 3 | J43: 4 | K43: 5 | L43: 6 | M43: 7 | N43: 8
B44: 1 | C44: LFH03631 | D44: Э/вентилятор отоп. для а/м УАЗ 3163 Патриот (05.2012-) А/С Sanden Luzar | J44: 1 | K44: шт | L44: 4500 | M44: =L44*J44 -> 4500 | N44: =M44*22/122 -> 811.47541
B45: 2 | C45: 75.3780-01 | D45: Моторчик отопителя Г-2705 (d=18) дополнительный Truckman | J45: 1 | K45: шт | L45: 1200 | M45: =L45*J45 -> 1200 | N45: =M45*22/122 -> 216.39344
B46: 3 | C46: ХТД093-1/1627 | D46: Хомут 16-27 Диалуч на патрубки отопителя | J46: 2 | K46: шт | L46: 15 | M46: =L46*J46 -> 30 | N46: =M46*22/122 -> 5.4098361
B47: 4 | C47: 3160-3501090 | D47: Колодка тормозная УАЗ-3160 передняя (к-т 4шт.) Маркон | J47: 1 | K47: кт | L47: 800 | M47: =L47*J47 -> 800 | N47: =M47*22/122 -> 144.2623
B48: 5 | C48: LRH03631B | D48: Радиатор отоп. алюм. для а/м УАЗ 3163 Патриот (05.2012-) А/С Sanden | J48: 1 | K48: шт | L48: 4000 | M48: =L48*J48 -> 4000 | N48: =M48*22/122 -> 721.31148
B49: 6 | C49: 2389901364 | D49: Провод монтажный 2,50мм красный (ПГВА/ПВАМ) REXANT 1 m | J49: 1 | K49: шт | L49: 70 | M49: =L49*J49 -> 70 | N49: =M49*22/122 -> 12.622951
B50: 7 | C50: 614503 | D50: Втулка аморт Газель,Волга БМРТ -Ломов (к-т 4шт) (в упак) | J50: 1.5 | K50: шт | L50: 140 | M50: =L50*J50 -> 210 | N50: =M50*22/122 -> 37.868852
B51: 8 | D51: Сальник хвостовика 42х75-16,4 УАЗ ХАНТЕР, ПАТРИОТ, 3160, 3162 (чёрный, 2 пружины) NBR | J51: 1 | K51: шт | L51: 260 | M51: =L51*J51 -> 260 | N51: =M51*22/122 -> 46.885246
B52: 9 | C52: TKU-1308020-76 | D52: Ремень 2100 6PK TANAKI | J52: 1 | K52: шт | L52: 1100 | M52: =L52*J52 -> 1100 | N52: =M52*22/122 -> 198.36066
B53: 10 | C53: 707613 | D53: Тормозная жидкость Starex DOT-4 455г | J53: 1 | K53: шт | L53: 350 | M53: =L53*J53 -> 350 | N53: =M53*22/122 -> 63.114754
B54: 11 | C54: 162624 | D54: Масло трансмиссионное ZIC 75W85 GFT 4Л. | J54: 0.4 | K54: шт | L54: 1950 | M54: =L54*J54 -> 780 | N54: =M54*22/122 -> 140.65574
B55: 12 | C55: 2389901363 | D55: Масло трансмиссионное Gazpromneft Super Т-3 85W-90 1 л | J55: 2 | K55: шт | L55: 400 | M55: =L55*J55 -> 800 | N55: =M55*22/122 -> 144.2623
B56: 13 | D56: Суппорт УАЗ Патриот, Хантер с колодками правый ZF AUTO | J56: 1 | K56: шт | L56: 7200 | M56: =L56*J56 -> 7200 | N56: =M56*22/122 -> 1298.3607
B57: Итого материалов: | J57: 14.9 | K57: на сумму: | M57: =M44+M45+M46+M47+M48+M49+M50+M51+M52+M53+M54+M55+M56 -> 21300 | N57: =M57*22/122 -> 3840.9836
B59: Двадцать одна тысяча триста рублей 00 копеек
L61: Итого по заказ-наряду : | M61: =M36+M57 -> 49800 | N61: =M61*22/122 -> 8980.3279
B63: Всего по заказ-наряду: Сорок девять тысяч восемьсот рублей 00 копеек, в т.ч. НДС 22%.
J66: Мастер _____________________ | K66: Механик СТО/
C68: Гарантии: Гарантия на работы: слесарные - 30 дней, электрические - 30 дней, оригинальные з/ч - 30 дней, з/ч, связанные с электрооборудованием, подачей топлива и системой впрыска - гарантии нет, неоригинальные з/ч - гарантии нет. Гарантийные обязательства на работы выполняются фирмой только при предъявлении акта приемки автомобиля и техпаспорта (доверенности).
B73: Дата: 24.02.2026 | J73: Заказчик ______________________ | K73: /Общество с ограниченной ответственностью «Концепт»/
J75: Плательщик ______________________ | K75: /Общество с ограниченной ответственностью «Концепт»/
B77: Причина обращения:

Sheet 419
B1: ПОСТАВЩИК: ООО ФИРМА "СИГНАЛ"
B2: адрес: 364031, Чеченская Республика, г.Грозный, ул. Жуковского, д. 18
C4: Заказ-наряд № 100089 от 22.02.2026
B6: Заказчик: Общество с ограниченной ответственностью «Концепт» | H6: адрес заказчика : 364024, ЧР г.Грозный, ул.Назарбаева, д.92, оф. 6-05
B7: Автомобиль : УАЗ Есаул гос. номер: А 419 СТ /126
B9: Цена автомототранспортного средства, определяемая по соглашению сторон __________________
B11: Плательщик: Общество с ограниченной ответственностью «Концепт»
B12: ИНН 2014030866 адрес: телефоны: +7 (989) 9002252
N14: в валюте
N15: Руб
C17: Выполненные работы по заказ-наряду № 100089 от 22.02.2026
B19: № | C19: № кат. | D19: Наименование | I19: Кол. оп. | J19: Цена | K19: Норма | L19: н/ч | M19: Всего | N19: в т.ч. НДС
B20: 1 | C20: 2 | D20: 3 | I20: 4 | J20: 5 | K20: 6 | L20: 7 | M20: 8 | N20: 9
B21: 1 | D21: Диагностика ДВС | I21: 1 | J21: 1000 | K21: 1 | L21: Рубль | M21: =J21*I21 -> 1000 | N21: =M21*22/122 -> 180.32787
B22: 2 | D22: Замена свечей зажигания | I22: 1 | J22: 600 | K22: 1 | L22: Рубль | M22: =J22*I22 -> 600 | N22: =M22*22/122 -> 108.19672
B23: 3 | D23: Замена катушки зажигания | I23: 1 | J23: 150 | K23: 1 | L23: Рубль | M23: =J23*I23 -> 150 | N23: =M23*22/122 -> 27.04918
B24: 4 | D24: Замена масла и масл фильтра | I24: 1 | J24: 600 | K24: 1 | L24: Рубль | M24: =J24*I24 -> 600 | N24: =M24*22/122 -> 108.19672
B25: 5 | D25: Замена воздушного фильтра | I25: 1 | J25: 300 | K25: 1 | L25: Рубль | M25: =J25*I25 -> 300 | N25: =M25*22/122 -> 54.098361
B26: 6 | D26: Замена масла в редукторе | I26: 2 | J26: 350 | K26: 1 | L26: Рубль | M26: =J26*I26 -> 700 | N26: =M26*22/122 -> 126.22951
B27: 7 | D27: Замена масла в КПП | I27: 1 | J27: 500 | K27: 1 | L27: Рубль | M27: =J27*I27 -> 500 | N27: =M27*22/122 -> 90.163934
B28: 8 | D28: Замена масла в раздатке | I28: 1 | J28: 400 | K28: 1 | L28: Рубль | M28: =J28*I28 -> 400 | N28: =M28*22/122 -> 72.131148
B29: 9 | D29: Замена радиатора охлаждения | I29: 1 | J29: 2500 | K29: 1 | L29: Рубль | M29: =J29*I29 -> 2500 | N29: =M29*22/122 -> 450.81967
B30: 10 | D30: Замена ролика натяжного | I30: 1 | J30: 200 | K30: 1 | L30: Рубль | M30: =J30*I30 -> 200 | N30: =M30*22/122 -> 36.065574
B31: 11 | D31: Замена крышки пер. ГБЦ | I31: 1 | J31: 1500 | K31: 1 | L31: Рубль | M31: =J31*I31 -> 1500 | N31: =M31*22/122 -> 270.4918
B32: 12 | D32: Замена вентилятора охлаждения | I32: 1 | J32: 200 | K32: 1 | L32: Рубль | M32: =J32*I32 -> 200 | N32: =M32*22/122 -> 36.065574
... B35: 15 | D35: Замена дополнительного насоса | I35: 1 | J35: 600 | K35: 1 | L35: Рубль | M35: =J35*I35 -> 600 | N35: =M35*22/122 -> 108.19672
B36: Итого работ: | I36: 16 | J36: на сумму: | M36: =M21+M22+M23+M24+M25+M26+M27+M28+M29+M30+M31+M32+M33+M34+M35 -> 10450 | N36: =M36*22/122 -> 1884.4262
B38: Десять тысяч четыреста пятьдесят рублей 00 копеек.
C40: Расходная накладная к заказ-наряду № 100089 от 22.02.2026
B42: № | C42: № кат. | D42: Наименование | J42: Кол-во | K42: Ед.изм. | L42: Цена | M42: Всего | N42: в т.ч. НДС
B43: 1 | C43: 2 | D43: 3 | J43: 4 | K43: 5 | L43: 6 | M43: 7 | N43: 8
B44: 1 | C44: 3705307 | D44: Масло моторное полусинтетическое "Люкс 10W-40", 1л Лукойл | J44: 1 | K44: шт | L44: 350 | M44: =L44*J44 -> 350 | N44: =M44*22/122 -> 63.114754
B45: 2 | C45: 3705305 | D45: Моторное масло Лукойл Люкс SAE 10W-40, API SL/CF 5 л | J45: 1 | K45: шт | L45: 1250 | M45: =L45*J45 -> 1250 | N45: =M45*22/122 -> 225.40984
B46: 3 | C46: EKO104П | D46: Элемент воздушного фильтра дв.406 высокий, УАЗ Патриот Экофил | J46: 1 | K46: шт | L46: 600 | M46: =L46*J46 -> 600 | N46: =M46*22/122 -> 108.19672
B47: 4 | C47: NF100402 | D47: Фильтр масляный ГАЗель NEXT дв. А274 Evotech,4216 ГАЗ Оригинал | J47: 1 | K47: шт | L47: 400 | M47: =L47*J47 -> 400 | N47: =M47*22/122 -> 72.131148
B48: 5 | C48: 162624 | D48: Масло трансмиссионное ZIC 75W85 GFT 4Л. | J48: 0.5 | K48: шт | L48: 3800 | M48: =L48*J48 -> 1900 | N48: =M48*22/122 -> 342.62295
B49: 6 | C49: 2389901364 | D49: Масло трансм Gazpromneft 85W90 Super Т-3 4л | J49: 1 | K49: шт | L49: 1400 | M49: =L49*J49 -> 1400 | N49: =M49*22/122 -> 252.45902
B50: 7 | C50: 614503 | D50: Антифриз Sintec LUXE G12+, 5 кг, красный | J50: 2 | K50: шт | L50: 900 | M50: =L50*J50 -> 1800 | N50: =M50*22/122 -> 324.59016
B51: 8 | D51: Патрубки радиатора УАЗ "Patriot" с кондиционером ВПТ | J51: 1 | K51: кт | L51: 650 | M51: =L51*J51 -> 650 | N51: =M51*22/122 -> 117.21311
B52: 9 | C52: LRC0363b | D52: Радиатор УАЗ-3163 алюминиевый дв.ЗМЗ-409,40904,IVECO ЕВРО-2,3 LUZAR | J52: 1 | K52: шт | L52: 18500 | M52: =L52*J52 -> 18500 | N52: =M52*22/122 -> 3336.0656
B53: 10 | C53: П40524.1308080-303C-00-11 | D53: Ролик натяжной дв.405 Евро-3 усил. ДПК | J53: 1 | K53: шт | L53: 350 | M53: =L53*J53 -> 350 | N53: =M53*22/122 -> 63.114754
B54: 11 | C54: 3162-1308010 | D54: Вентилятор охлаждения (без гидромуфты) 7 лопастей / УАЗ Патриот | J54: 1 | K54: шт | L54: 1950 | M54: =L54*J54 -> 1950 | N54: =M54*22/122 -> 351.63934
B55: 12 | C55: 409.1003083-10 | D55: Крышка ГБЦ передняя ЗМЗ 409 УАЗ Патриот ЕВРО-3 ЗМЗ | J55: 1 | K55: шт | L55: 6500 | M55: =L55*J55 -> 6500 | N55: =M55*22/122 -> 1172.1311
B56: 13 | C56: 75.3780-01 | D56: Моторчик отопителя Г-2705 (d=18) дополнительный Truckman | J56: 1 | K56: шт | L56: 1180 | M56: =L56*J56 -> 1180 | N56: =M56*22/122 -> 212.78689
B57: 14 | C57: F01H7B0042-HZ6 | D57: Свечи АУ-17ДВРМ Стандарт "33" ВАЗ 2108-70, ЗМЗ 406-409. УМЗ 4216 | J57: 1 | K57: кт | L57: 600 | M57: =L57*J57 -> 600 | N57: =M57*22/122 -> 108.19672
B58: 15 | C58: 407.3705 | D58: Катушка зажигания 405 Евро-3 (модуль) СОАТЭ | J58: 1 | K58: шт | L58: 1900 | M58: =L58*J58 -> 1900 | N58: =M58*22/122 -> 342.62295
B59: 16 | C59: 6933709 | D59: Переключатель подрулевой УАЗ-3163 (13-) АВТОАРМАТУРА | J59: 1 | K59: шт | L59: 1120 | M59: =L59*J59 -> 1120 | N59: =M59*22/122 -> 201.96721
B60: Итого материалов: | J60: 16 | K60: на сумму: | M60: =M44+M45+M46+M47+M48+M49+M50+M51+M52+M53+M54+M55+M56+M57+M58+M59 -> 40450 | N60: =M60*22/122 -> 7294.2623
B62: Сорок тысяч четыреста пятьдесят рублей 00 копеек
L64: Итого по заказ-наряду : | M64: =M36+M60 -> 50900 | N64: =M64*22/122 -> 9178.6885
B66: Всего по заказ-наряду: Пятьдесят тысяч девятьсот рублей 00 копеек, в т.ч. НДС 22%.
J69: Мастер _____________________ | K69: Механик СТО/
C71: Гарантии: Гарантия на работы: слесарные - 30 дней, электрические - 30 дней, оригинальные з/ч - 30 дней, з/ч, связанные с электрооборудованием, подачей топлива и системой впрыска - гарантии нет, неоригинальные з/ч - гарантии нет. Гарантийные обязательства на работы выполняются фирмой только при предъявлении акта приемки автомобиля и техпаспорта (доверенности).
B76: Дата: 22.02.2026 | J76: Заказчик ______________________ | K76: /Общество с ограниченной ответственностью «Концепт»/
J78: Плательщик ______________________ | K78: /Общество с ограниченной ответственностью «Концепт»/
B80: Причина обращения:

Sheet 546
B1: ПОСТАВЩИК: ООО ФИРМА "СИГНАЛ"
B2: адрес: 364031, Чеченская Республика, г.Грозный, ул. Жуковского, д. 18
C4: Заказ-наряд № 100506 от 02.06.2026
B6: Заказчик: Общество с ограниченной ответственностью «Концепт» | H6: адрес заказчика : 364024, ЧР г.Грозный, ул.Назарбаева, д.92, оф. 6-05
B7: Автомобиль : УАЗ Патриот г/н Е546НТ /15
B9: Цена автомототранспортного средства, определяемая по соглашению сторон __________________
B11: Плательщик: Общество с ограниченной ответственностью «Концепт»
B12: ИНН 2014030866 адрес: телефоны: +7 (989) 9002252
N14: в валюте
N15: Руб
C17: Выполненные работы по заказ-наряду № 100506 от 02.06.2026
B19: № | C19: № кат. | D19: Наименование | I19: Кол. оп. | J19: Цена | K19: Норма | L19: н/ч | M19: Всего | N19: в т.ч. НДС
B20: 1 | C20: 2 | D20: 3 | I20: 4 | J20: 5 | K20: 6 | L20: 7 | M20: 8 | N20: 9
B21: 1 | D21: Замена пер крышки ГБЦ | I21: 1 | J21: 2500 | K21: 1 | L21: Рубль | M21: =J21*I21 -> 2500 | N21: =M21*22/122 -> 450.81967
B22: 2 | D22: Замена пер торм диска (с колодками) | I22: 2 | J22: 1000 | K22: 1 | L22: Рубль | M22: =J22*I22 -> 2000 | N22: =M22*22/122 -> 360.65574
B23: 3 | D23: Диагностика подвески | I23: 1 | J23: 300 | K23: 1 | L23: Рубль | M23: =J23*I23 -> 300 | N23: =M23*22/122 -> 54.098361
B24: 4 | D24: Замена пружины подвески | I24: 2 | J24: 2000 | K24: 1 | L24: Рубль | M24: =J24*I24 -> 4000 | N24: =M24*22/122 -> 721.31148
B25: 5 | D25: Замена втулок продольной тяги | I25: 4 | J25: 350 | K25: 1 | L25: Рубль | M25: =J25*I25 -> 1400 | N25: =M25*22/122 -> 252.45902
B26: 6 | D26: Регулировка подшипника ступицы | I26: 1 | J26: 700 | K26: 1 | L26: Рубль | M26: =J26*I26 -> 700 | N26: =M26*22/122 -> 126.22951
B27: 7 | D27: Подтяжка ходовой части | I27: 1 | J27: 300 | K27: 1 | L27: Рубль | M27: =J27*I27 -> 300 | N27: =M27*22/122 -> 54.098361
B28: Итого работ: | I28: 12 | J28: на сумму: | M28: =M21+M22+M23+M24+M25+M26+M27 -> 11200 | N28: =M28*22/122 -> 2019.6721
B30: Одиннадцать тысяч двести рублей 00 копеек
C32: Расходная накладная к заказ-наряду № 100506 от 02.06.2026
B34: № | C34: № кат. | D34: Наименование | J34: Кол-во | K34: Ед.изм. | L34: Цена | M34: Всего | N34: в т.ч. НДС
B35: 1 | C35: 2 | D35: 3 | J35: 4 | K35: 5 | L35: 6 | M35: 7 | N35: 8
B36: 1 | C36: 3160-3501090 | D36: Колодка тормозная УАЗ-3160 передняя (к-т 4шт.) Маркон | J36: 1 | K36: кт | L36: 850 | M36: =L36*J36 -> 850 | N36: =M36*22/122 -> 153.27869
B37: 2 | C37: 3160-3501076 | D37: Диск тормозной УАЗ-3160,Хантер,Патриот ТОРНАДО-НН | J37: 2 | K37: шт | L37: 2500 | M37: =L37*J37 -> 5000 | N37: =M37*22/122 -> 901.63934
B38: 3 | C38: 3160-2902712 (+50) | D38: Пружина УАЗ 31519 Хантер, 3163 Патриот передняя усиленная +50 мм (к-т 2 шт.) | J38: 1 | K38: кт | L38: 7200 | M38: =L38*J38 -> 7200 | N38: =M38*22/122 -> 1298.3607
B39: 4 | C39: 3160-2909033 | D39: Втулка (подушка) опорная продольной (штанги) тяги Уаз 3160, Хантер, Патриот | J39: 4 | K39: шт | L39: 200 | M39: =L39*J39 -> 800 | N39: =M39*22/122 -> 144.2623
B40: 5 | C40: 409.1003083-10 | D40: Крышка ГБЦ передняя ЗМЗ 409 УАЗ Патриот ЕВРО-3 ЗМЗ | J40: 1 | K40: шт | L40: 6800 | M40: =L40*J40 -> 6800 | N40: =M40*22/122 -> 1226.2295
B41: Итого материалов: | J41: 9 | K41: на сумму: | M41: =M36+M37+M38+M39+M40 -> 20650 | N41: =M41*22/122 -> 3723.7705
B43: Двадцать тысяч шестьсот пятьдесят рублей 00 копеек
L45: Итого по заказ-наряду : | M45: =M28+M41 -> 31850 | N45: =M45*20/120 -> 5308.3333
B47: Всего по заказ-наряду: Тридцать одна тысяча восемьсот пятьдесят рублей 00 копеек, в т.ч. НДС 22%.
J50: Мастер _____________________ | K50: Механик СТО/
C52: Гарантии: Гарантия на работы: слесарные - 30 дней, электрические - 30 дней, оригинальные з/ч - 30 дней, з/ч, связанные с электрооборудованием, подачей топлива и системой впрыска - гарантии нет, неоригинальные з/ч - гарантии нет. Гарантийные обязательства на работы выполняются фирмой только при предъявлении акта приемки автомобиля и техпаспорта (доверенности).
B57: Дата: 02.06.2026 | J57: Заказчик ______________________ | K57: /Общество с ограниченной ответственностью «Концепт»/
J59: Плательщик ______________________ | K59: /Общество с ограниченной ответственностью «Концепт»/
B61: Причина обращения:

Sheet 506
B1: ПОСТАВЩИК: ООО ФИРМА "СИГНАЛ"
B2: адрес: 364031, Чеченская Республика, г.Грозный, ул. Жуковского, д. 18
C4: Заказ-наряд № 100508 от 03.06.2026
B6: Заказчик: Общество с ограниченной ответственностью «Концепт» | H6: адрес заказчика : 364024, ЧР г.Грозный, ул.Назарбаева, д.92, оф. 6-05
B7: Автомобиль : УАЗ Патриот г/н Е506НТ /15
B9: Цена автомототранспортного средства, определяемая по соглашению сторон __________________
B11: Плательщик: Общество с ограниченной ответственностью «Концепт»
B12: ИНН 2014030866 адрес: телефоны: +7 (989) 9002252
N14: в валюте
N15: Руб
C17: Выполненные работы по заказ-наряду № 100508 от 03.06.2026
B19: № | C19: № кат. | D19: Наименование | I19: Кол. оп. | J19: Цена | K19: Норма | L19: н/ч | M19: Всего | N19: в т.ч. НДС
B20: 1 | C20: 2 | D20: 3 | I20: 4 | J20: 5 | K20: 6 | L20: 7 | M20: 8 | N20: 9
B21: 1 | D21: Диагностика и подтяжка подвески | I21: 1 | J21: 500 | K21: 1 | L21: Рубль | M21: =J21*I21 -> 500 | N21: =M21*22/122 -> 90.163934
B22: 2 | D22: Замена пер торм диска (с колодками) | I22: 2 | J22: 1000 | K22: 1 | L22: Рубль | M22: =J22*I22 -> 2000 | N22: =M22*22/122 -> 360.65574
B23: 3 | D23: Замена пружины подвески | I23: 2 | J23: 2000 | K23: 1 | L23: Рубль | M23: =J23*I23 -> 4000 | N23: =M23*22/122 -> 721.31148
B24: Итого работ: | I24: 5 | J24: на сумму: | M24: =M21+M22+M23 -> 6500 | N24: =M24*22/122 -> 1172.1311
B26: Шесть тысяч пятьсот рублей 00 копеек
C28: Расходная накладная к заказ-наряду № 100508 от 03.06.2026
B30: № | C30: № кат. | D30: Наименование | J30: Кол-во | K30: Ед.изм. | L30: Цена | M30: Всего | N30: в т.ч. НДС
B31: 1 | C31: 2 | D31: 3 | J31: 4 | K31: 5 | L31: 6 | M31: 7 | N31: 8
B32: 1 | C32: 3160-3501090 | D32: Колодка тормозная УАЗ-3160 передняя (к-т 4шт.) Маркон | J32: 1 | K32: кт | L32: 850 | M32: =L32*J32 -> 850 | N32: =M32*22/122 -> 153.27869
B33: 2 | C33: 3160-3501076 | D33: Диск тормозной УАЗ-3160,Хантер,Патриот ТОРНАДО-НН | J33: 2 | K33: шт | L33: 2500 | M33: =L33*J33 -> 5000 | N33: =M33*22/122 -> 901.63934
B34: 3 | C34: 636390 | D34: Пружины передние УАЗ Патриот, Хантер лифт +30 мм (2 шт) redBTR | J34: 1 | K34: кт | L34: 7200 | M34: =L34*J34 -> 7200 | N34: =M34*22/122 -> 1298.3607
B35: 4 | C35: 3160-2902735 | D35: Подушка пружины УАЗ Патриот., полиуретан синий ПромТехПласт | J35: 2 | K35: шт | L35: 325 | M35: =L35*J35 -> 650 | N35: =M35*22/122 -> 117.21311
B36: 5 | C36: 4008 | D36: Смазка многоцелевая RC-40, 210 мл BiBiCare | J36: 1 | K36: шт | L36: 250 | M36: =L36*J36 -> 250 | N36: =M36*22/122 -> 45.081967
B37: Итого материалов: | J37: 7 | K37: на сумму: | M37: =M32+M33+M34+M35+M36 -> 13950 | N37: =M37*22/122 -> 2515.5738
B39: Тринадцать тысяч девятьсот пятьдесят рублей 00 копеек
L41: Итого по заказ-наряду : | M41: =M24+M37 -> 20450 | N41: =M41*20/120 -> 3408.3333
B43: Всего по заказ-наряду: Двадцать тысяч четыреста пятьдесят рублей 00 копеек, в т.ч. НДС 22%.
J46: Мастер _____________________ | K46: Механик СТО/
C48: Гарантии: Гарантия на работы: слесарные - 30 дней, электрические - 30 дней, оригинальные з/ч - 30 дней, з/ч, связанные с электрооборудованием, подачей топлива и системой впрыска - гарантии нет, неоригинальные з/ч - гарантии нет. Гарантийные обязательства на работы выполняются фирмой только при предъявлении акта приемки автомобиля и техпаспорта (доверенности).
B53: Дата: 03.06.2026 | J53: Заказчик ______________________ | K53: /Общество с ограниченной ответственностью «Концепт»/
J55: Плательщик ______________________ | K55: /Общество с ограниченной ответственностью «Концепт»/
B57: Причина обращения:

Sheet 956
B1: ПОСТАВЩИК: ООО ФИРМА "СИГНАЛ"
B2: адрес: 364031, Чеченская Республика, г.Грозный, ул. Жуковского, д. 18
C4: Заказ-наряд № 100501 от 02.06.2026
B6: Заказчик: Общество с ограниченной ответственностью «Концепт» | H6: адрес заказчика : 364024, ЧР г.Грозный, ул.Назарбаева, д.92, оф. 6-05
B7: Автомобиль : Газель Некст г/н М 956 УМ 29 RUS
B9: Цена автомототранспортного средства, определяемая по соглашению сторон __________________
B11: Плательщик: Общество с ограниченной ответственностью «Концепт»
B12: ИНН 2014030866 адрес: телефоны: +7 (989) 9002252
N14: в валюте
N15: Руб
C17: Выполненные работы по заказ-наряду № 100501 от 02.06.2026
B19: № | C19: № кат. | D19: Наименование | I19: Кол. оп. | J19: Цена | K19: Норма | L19: н/ч | M19: Всего | N19: в т.ч. НДС
B20: 1 | C20: 2 | D20: 3 | I20: 4 | J20: 5 | K20: 6 | L20: 7 | M20: 8 | N20: 9
B21: 1 | D21: Замена масла и масл фильтра | I21: 1 | J21: 800 | K21: 1 | L21: Рубль | M21: =J21*I21 -> 800 | N21: =M21*22/122 -> 144.2623
B22: 2 | D22: Замена воздушного фильтра | I22: 1 | J22: 250 | K22: 1 | L22: Рубль | M22: =J22*I22 -> 250 | N22: =M22*22/122 -> 45.081967
B23: 3 | D23: Замена салонного фильтра | I23: 1 | J23: 500 | K23: 1 | L23: Рубль | M23: =J23*I23 -> 500 | N23: =M23*22/122 -> 90.163934
B24: 4 | D24: Подтяжка ходовой части | I24: 1 | J24: 500 | K24: 1 | L24: Рубль | M24: =J24*I24 -> 500 | N24: =M24*22/122 -> 90.163934
B25: 5 | D25: Токарные работы | I25: 1 | J25: 1500 | K25: 1 | L25: Рубль | M25: =J25*I25 -> 1500 | N25: =M25*22/122 -> 270.4918
B26: 6 | D26: Замена задних торм-х колодок | I26: 1 | J26: 2200 | K26: 1 | L26: Рубль | M26: =J26*I26 -> 2200 | N26: =M26*22/122 -> 396.72131
B27: 7 | D27: Замена сальника ступицы задней | I27: 1 | J27: 1200 | K27: 1 | L27: Рубль | M27: =J27*I27 -> 1200 | N27: =M27*22/122 -> 216.39344
B28: 8 | D28: Замена р/к наконечника троса КПП | I28: 2 | J28: 500 | K28: 1 | L28: Рубль | M28: =J28*I28 -> 1000 | N28: =M28*22/122 -> 180.32787
B29: 9 | D29: Замена опоры подвесной | I29: 1 | J29: 800 | K29: 1 | L29: Рубль | M29: =J29*I29 -> 800 | N29: =M29*22/122 -> 144.2623
B30: 10 | D30: Регулировка ручного тормоза, с разводкой колодок | I30: 1 | J30: 600 | K30: 1 | L30: Рубль | M30: =J30*I30 -> 600 | N30: =M30*22/122 -> 108.19672
B31: 11 | D31: Проверка и долив масла в силовых агрегатах | I31: 1 | J31: 400 | K31: 1 | L31: Рубль | M31: =J31*I31 -> 400 | N31: =M31*22/122 -> 72.131148
B32: 12 | D32: Сход-развал (с раскруткой с-р тяги) | I32: 1 | J32: 2000 | K32: 1 | L32: Рубль | M32: =J32*I32 -> 2000 | N32: =M32*22/122 -> 360.65574
B33: Итого работ: | I33: 13 | J33: на сумму: | M33: =M21+M22+M23+M24+M25+M26+M27+M28+M29+M30+M31+M32 -> 11750 | N33: =M33*22/122 -> 2118.8525
B35: Одиннадцать тысяч семьсот пятьдесят рублей 00 копеек.
C37: Расходная накладная к заказ-наряду № 100501 от 02.06.2026
B39: № | C39: № кат. | D39: Наименование | J39: Кол-во | K39: Ед.изм. | L39: Цена | M39: Всего | N39: в т.ч. НДС
B40: 1 | C40: 2 | D40: 3 | J40: 4 | K40: 5 | L40: 6 | M40: 7 | N40: 8
B41: 1 | C41: ЭС.А31R32.1707577 | D41: Рк наконечника троса КПП Г-3302 NEXT "ЭССКО-НН" | J41: 2 | K41: кт | L41: 150 | M41: =L41*J41 -> 300 | N41: =M41*22/122 -> 54.098361
B42: 2 | C42: ABS1802 | D42: Колодка тормозная 3302 задняя (к-т 4шт.) Allied Nippon | J42: 1 | K42: кт | L42: 2600 | M42: =L42*J42 -> 2600 | N42: =M42*22/122 -> 468.85246
B43: 3 | C43: ЭС.5435-2304130 | D43: Сальник ступицы Г-3302 задний (65х90х16) двубортный "ЭССКО-НН" | J43: 1 | K43: шт | L43: 450 | M43: =L43*J43 -> 450 | N43: =M43*22/122 -> 81.147541
B44: 4 | C44: ЭС.А31R32.1707577 | D44: Опора вала карданного ГАЗель Next (17-) в сборе (d=40мм) PRAVT | J44: 1 | K44: шт | L44: 2950 | M44: =L44*J44 -> 2950 | N44: =M44*22/122 -> 531.96721
B45: Итого материалов: | J45: 5 | K45: на сумму: | M45: =M41+M42+M43+M44 -> 6300 | N45: =M45*22/122 -> 1136.0656
B47: Шесть тысяч триста рублей 00 копеек
L49: Итого по заказ-наряду : | M49: =M33+M45 -> 18050 | N49: =M49*22/122 -> 3254.918
B51: Всего по заказ-наряду: Восемнадцать тысяч пятьдесят рублей 00 копеек, в т.ч. НДС 22%.
J54: Мастер _____________________ | K54: Механик СТО/
C56: Гарантии: Гарантия на работы: слесарные - 30 дней, электрические - 30 дней, оригинальные з/ч - 30 дней, з/ч, связанные с электрооборудованием, подачей топлива и системой впрыска - гарантии нет, неоригинальные з/ч - гарантии нет. Гарантийные обязательства на работы выполняются фирмой только при предъявлении акта приемки автомобиля и техпаспорта (доверенности).
B61: Дата: 02.06.2026 | J61: Заказчик ______________________ | K61: /Общество с ограниченной ответственностью «Концепт»/
J63: Плательщик ______________________ | K63: /Общество с ограниченной ответственностью «Концепт»/
B65: Причина обращения:

Sheet 091
B1: ПОСТАВЩИК: ООО ФИРМА "СИГНАЛ"
B2: адрес: 364031, Чеченская Республика, г.Грозный, ул. Жуковского, д. 18
C4: Заказ-наряд № 100502 от 02.06.2026
B6: Заказчик: Общество с ограниченной ответственностью «Концепт» | H6: адрес заказчика : 364024, ЧР г.Грозный, ул.Назарбаева, д.92, оф. 6-05
B7: Автомобиль : Лада Калина гос. номер: А091ХА 15
B9: Цена автомототранспортного средства, определяемая по соглашению сторон __________________
B11: Плательщик: Общество с ограниченной ответственностью «Концепт»
B12: ИНН 2014030866 адрес: телефоны: +7 (989) 9002252
N14: в валюте
N15: Руб
C17: Выполненные работы по заказ-наряду № 100502 от 02.06.2026
B19: № | C19: № кат. | D19: Наименование | I19: Кол. оп. | J19: Цена | K19: Норма | L19: н/ч | M19: Всего | N19: в т.ч. НДС
B20: 1 | C20: 2 | D20: 3 | I20: 4 | J20: 5 | K20: 6 | L20: 7 | M20: 8 | N20: 9
B21: 1 | D21: Диагностика тормозной системы | I21: 1 | J21: 300 | K21: 1 | L21: Рубль | M21: =J21*I21 -> 300 | N21: =M21*22/122 -> 54.098361
B22: 2 | D22: Замена задних торм-х колодок | I22: 1 | J22: 1400 | K22: 1 | L22: Рубль | M22: =J22*I22 -> 1400 | N22: =M22*22/122 -> 252.45902
B23: 3 | D23: Замена передних торм-х колодок | I23: 1 | J23: 600 | K23: 1 | L23: Рубль | M23: =J23*I23 -> 600 | N23: =M23*22/122 -> 108.19672
B24: 4 | D24: Замена масла и масл фильтра | I24: 1 | J24: 600 | K24: 1 | L24: Рубль | M24: =J24*I24 -> 600 | N24: =M24*22/122 -> 108.19672
B25: 5 | D25: Замена воздушного фильтра | I25: 1 | J25: 200 | K25: 1 | L25: Рубль | M25: =J25*I25 -> 200 | N25: =M25*22/122 -> 36.065574
B26: 6 | D26: Замена салонного фильтра | I26: 1 | J26: 150 | K26: 1 | L26: Рубль | M26: =J26*I26 -> 150 | N26: =M26*22/122 -> 27.04918
B27: 7 | D27: Замена топливного фильтра | I27: 1 | J27: 300 | K27: 1 | L27: Рубль | M27: =J27*I27 -> 300 | N27: =M27*22/122 -> 54.098361
B28: 8 | D28: Диагностика ДВС | I28: 1 | J28: 1000 | K28: 1 | L28: Рубль | M28: =J28*I28 -> 1000 | N28: =M28*22/122 -> 180.32787
B29: 9 | D29: Замена свечей зажигания | I29: 1 | J29: 500 | K29: 1 | L29: Рубль | M29: =J29*I29 -> 500 | N29: =M29*22/122 -> 90.163934
B30: 10 | D30: Замена проводов в/вольтных | I30: 1 | J30: 150 | K30: 1 | L30: Рубль | M30: =J30*I30 -> 150 | N30: =M30*22/122 -> 27.04918
B31: 11 | D31: Замена моторчика бензонасоса | I31: 1 | J31: 1200 | K31: 1 | L31: Рубль | M31: =J31*I31 -> 1200 | N31: =M31*22/122 -> 216.39344
B32: 12 | D32: Замена ремня ГРМ с помпой | I32: 1 | J32: 2000 | K32: 1 | L32: Рубль | M32: =J32*I32 -> 2000 | N32: =M32*22/122 -> 360.65574
... B40: 20 | D40: Сход-развал | I40: 1 | J40: 1500 | K40: 1 | L40: Рубль | M40: =J40*I40 -> 1500 | N40: =M40*22/122 -> 270.4918
B41: Итого работ: | I41: 26 | J41: на сумму: | M41: =M21+M22+M23+M24+M25+M26+M27+M28+M29+M30+M31+M32+M33+M34+M35+M36+M37+M38+M39+M40 -> 17000 | N41: =M41*22/122 -> 3065.5738
B43: Пять тысяч шестьсот рублей 00 копеек.
C45: Расходная накладная к заказ-наряду № 100502 от 02.06.2026
B47: № | C47: № кат. | D47: Наименование | J47: Кол-во | K47: Ед.изм. | L47: Цена | M47: Всего | N47: в т.ч. НДС
B48: 1 | C48: 2 | D48: 3 | J48: 4 | K48: 5 | L48: 6 | M48: 7 | N48: 8
B49: 1 | C49: SP1181 | D49: Колодки тормозные передние 2108-2110, Калина, Приора, Гранта Hi-Q (4шт) | J49: 1 | K49: кт | L49: 800 | M49: =L49*J49 -> 800 | N49: =M49*22/122 -> 144.2623
B50: 2 | C50: А17ДВРМ | D50: Свечи А17ДВРМ Стандарт "33" 8кл | J50: 1 | K50: кт | L50: 600 | M50: =L50*J50 -> 600 | N50: =M50*22/122 -> 108.19672
B51: 3 | C51: AB1118-3502070 | D51: Барабан торм Ваз 2108-2110-2170-2190-1118 чугун Автореал | J51: 2 | K51: шт | L51: 1400 | M51: =L51*J51 -> 2800 | N51: =M51*22/122 -> 504.91803
B52: 4 | C52: 19188 | D52: Масло моторное Лукойл Люкс 10W-40 (4л) | J52: 1 | K52: шт | L52: 1200 | M52: =L52*J52 -> 1200 | N52: =M52*22/122 -> 216.39344
B53: 5 | C53: 2108-1012005-08 | D53: Фильтр масляный Lada/Datsun/ВАЗ Ливны | J53: 1 | K53: шт | L53: 400 | M53: =L53*J53 -> 400 | N53: =M53*22/122 -> 72.131148
B54: 6 | C54: LECAR12020101 | D54: Фильтр воздушный ВАЗ 2108-12 LECAR | J54: 1 | K54: шт | L54: 350 | M54: =L54*J54 -> 350 | N54: =M54*22/122 -> 63.114754
B55: 7 | C55: 21-00083-SX | D55: фильтр топливный! Opel Astra/Corsa/Omega/Vectra, 1.2i-3.0 93>Stellox | J55: 1 | K55: шт | L55: 350 | M55: =L55*J55 -> 350 | N55: =M55*22/122 -> 63.114754
B56: 8 | C56: HB321 | D56: Подшипник ступ.LADA 2108-09 99 2110-12 KALINA 86- зад. FINWHALE | J56: 1 | K56: шт | L56: 1050 | M56: =L56*J56 -> 1050 | N56: =M56*22/122 -> 189.34426
B57: 9 | C57: Z-40 100 | D57: Смазка проникающая Z-40 (100 мл.) | J57: 1 | K57: шт | L57: 250 | M57: =L57*J57 -> 250 | N57: =M57*22/122 -> 45.081967
B58: 10 | C58: 2389901366 | D58: Масло трансмиссионное Gazpromneft 80/85 API GL-4 4 л. | J58: 1 | K58: шт | L58: 1600 | M58: =L58*J58 -> 1600 | N58: =M58*22/122 -> 288.52459
B59: 11 | C59: 11180812201082 | D59: Фильтр салона Ваз 1118, 2190, 2123 ОАО АВТОВАЗ | J59: 1 | K59: шт | L59: 400 | M59: =L59*J59 -> 400 | N59: =M59*22/122 -> 72.131148
B60: 12 | C60: FJ218 | D60: Шрус наруж (Граната) Ваз 2108-12 Finwhale | J60: 1 | K60: шт | L60: 1800 | M60: =L60*J60 -> 1800 | N60: =M60*22/122 -> 324.59016
B61: 13 | C61: DA140 | D61: Колодки барабан. тормоза задние для автомобилей VAZ 2108-2110 (без ABS) SM | J61: 1 | K61: кт | L61: 1000 | M61: =L61*J61 -> 1000 | N61: =M61*22/122 -> 180.32787
B62: 14 | C62: 2190 | D62: Провода свечные ВАЗ 2114-10,1118,2190 инж 8 кл 1,6 Милена | J62: 1 | K62: кт | L62: 700 | M62: =L62*J62 -> 700 | N62: =M62*22/122 -> 126.22951
B63: 15 | C63: 5521 | D63: Ремень ГРМ Gates 111х19 для ВАЗ 2108-21099, 2110-2112, 2113-2115, Лада Калина, Приора 8 кл. | J63: 1 | K63: шт | L63: 850 | M63: =L63*J63 -> 850 | N63: =M63*22/122 -> 153.27869
B64: 16 | C64: FP 453-453 | D64: Моторчик бензонасоса Weber | J64: 1 | K64: шт | L64: 850 | M64: =L64*J64 -> 850 | N64: =M64*22/122 -> 153.27869
B65: 17 | C65: WP108 | D65: Насос водяной Ваз 2108 Finwhale | J65: 1 | K65: шт | L65: 1500 | M65: =L65*J65 -> 1500 | N65: =M65*22/122 -> 270.4918
B66: 18 | C66: 813365310 | D66: Сальник распредвала/коленвала передний Lada/Лада Приора, 2170 Victor Reinz (28х42х7) | J66: 1 | K66: шт | L66: 150 | M66: =L66*J66 -> 150 | N66: =M66*22/122 -> 27.04918
B67: 19 | D67: Кольцо уплотнительное форсунки ВАЗ 2115,2110,Калина,2170,Приора | J67: 6 | K67: шт | L67: 10 | M67: =L67*J67 -> 60 | N67: =M67*22/122 -> 10.819672
B68: 20 | C68: 280158017 | D68: Форсунка топливная BOSCH оранжевая ВАЗ 2113-2115, Приора, Приора 2, Гранта, 8-кл. | J68: 1 | K68: шт | L68: 2500 | M68: =L68*J68 -> 2500 | N68: =M68*22/122 -> 450.81967
B69: 21 | C69: 4599ACL | D69: Лобовое стекло ВАЗ 1118 Лада Калина (KALINA) | J69: 1 | K69: шт | L69: 4240 | M69: =L69*J69 -> 4240 | N69: =M69*22/122 -> 764.59016
B70: Итого материалов: | J70: 20 | K70: на сумму: | M70: =M49+M50+M51+M52+M53+M54+M55+M56+M57+M58+M59+M60+M61+M62+M63+M64+M65+M66+M67+M68+M69 -> 23450 | N70: =M70*22/122 -> 4228.6885
B72: Десять тысяч шестьсот рублей 00 копеек
L74: Итого по заказ-наряду : | M74: =M41+M70 -> 40450 | N74: =M74*22/122 -> 7294.2623
B76: Всего по заказ-наряду: Шестнадцать тысяч двести рублей 00 копеек, в т.ч. НДС 22%.
J79: Мастер _____________________ | K79: Механик СТО/
C81: Гарантии: Гарантия на работы: слесарные - 30 дней, электрические - 30 дней, оригинальные з/ч - 30 дней, з/ч, связанные с электрооборудованием, подачей топлива и системой впрыска - гарантии нет, неоригинальные з/ч - гарантии нет. Гарантийные обязательства на работы выполняются фирмой только при предъявлении акта приемки автомобиля и техпаспорта (доверенности).
B86: Дата: 14.01.2026 | J86: Заказчик ______________________ | K86: /Общество с ограниченной ответственностью «Концепт»/
J88: Плательщик ______________________ | K88: /Общество с ограниченной ответственностью «Концепт»/
B90: Причина обращения:

Sheet 273
B1: ПОСТАВЩИК: ООО ФИРМА "СИГНАЛ"
B2: адрес: 364031, Чеченская Республика, г.Грозный, ул. Жуковского, д. 18
C4: Заказ-наряд № 100520 от 13.11.2025
B6: Заказчик: Общество с ограниченной ответственностью «Концепт» | H6: адрес заказчика : 364024, ЧР г.Грозный, ул.Назарбаева, д.92, оф. 6-05
B7: Автомобиль : Тойота Камри г/н А273ОА 15
B9: Цена автомототранспортного средства, определяемая по соглашению сторон __________________
B11: Плательщик: Общество с ограниченной ответственностью «Концепт»
B12: ИНН 2014030866 адрес: телефоны: +7 (989) 9002252
N14: в валюте
N15: Руб
C17: Выполненные работы по заказ-наряду № 100520 от 13.11.2025
B19: № | C19: № кат. | D19: Наименование | I19: Кол. оп. | J19: Цена | K19: Норма | L19: н/ч | M19: Всего | N19: в т.ч. НДС
B20: 1 | C20: 2 | D20: 3 | I20: 4 | J20: 5 | K20: 6 | L20: 7 | M20: 8 | N20: 9
B21: 1 | D21: Шиномонтаж колеса (снять колесо, балансировка, поставить колесо) 1 шт. | I21: 4 | J21: 350 | K21: 1 | L21: Рубль | M21: =J21*I21 -> 1400 | N21: =M21*20/120 -> 233.33333
B22: Итого работ: | I22: 4 | J22: на сумму: | M22: =M21 -> 1400 | N22: =M22*20/120 -> 233.33333
B24: Одна тысяча четыреста рублей 00 копеек
C26: Расходная накладная к заказ-наряду № 100520 от 13.11.2025
B28: № | C28: № кат. | D28: Наименование | J28: Кол-во | K28: Ед.изм. | L28: Цена | M28: Всего | N28: в т.ч. НДС
B29: 1 | C29: 2 | D29: 3 | J29: 4 | K29: 5 | L29: 6 | M29: 7 | N29: 8
B30: 1 | J30: 0 | K30: шт | L30: 0 | M30: =L30*J30 -> 0 | N30: =M30*20/120 -> 0
B31: Итого материалов: | J31: 0 | K31: на сумму: | M31: 0 | N31: =M31*20/120 -> 0
L35: Итого по заказ-наряду : | M35: =M22+M31 -> 1400 | N35: =N22+N31 -> 233.33333
B37: Всего по заказ-наряду: Одна тысяча четыреста рублей 00 копеек, в т.ч. НДС 20%
J40: Мастер _____________________ | K40: Механик СТО/
C42: Гарантии: Гарантия на работы: слесарные - 30 дней, электрические - 30 дней, оригинальные з/ч - 30 дней, з/ч, связанные с электрооборудованием, подачей топлива и системой впрыска - гарантии нет, неоригинальные з/ч - гарантии нет. Гарантийные обязательства на работы выполняются фирмой только при предъявлении акта приемки автомобиля и техпаспорта (доверенности).
B47: Дата: 13.11.2025 | J47: Заказчик ______________________ | K47: /Общество с ограниченной ответственностью «Концепт»/
J49: Плательщик ______________________ | K49: /Общество с ограниченной ответственностью «Концепт»/
B51: Причина обращения:

Sheet 301
B1: ПОСТАВЩИК: ООО ФИРМА "СИГНАЛ"
B2: адрес: 364031, Чеченская Республика, г.Грозный, ул. Жуковского, д. 18
C4: Заказ-наряд № 100517 от 12.11.2025
B6: Заказчик: Общество с ограниченной ответственностью «Концепт» | H6: адрес заказчика : 364024, ЧР г.Грозный, ул.Назарбаева, д.92, оф. 6-05
B7: Автомобиль : Тойота Камри г/н Е301ОУ 15
B9: Цена автомототранспортного средства, определяемая по соглашению сторон __________________
B11: Плательщик: Общество с ограниченной ответственностью «Концепт»
B12: ИНН 2014030866 адрес: телефоны: +7 (989) 9002252
N14: в валюте
N15: Руб
C17: Выполненные работы по заказ-наряду № 100517 от 12.11.2025
B19: № | C19: № кат. | D19: Наименование | I19: Кол. оп. | J19: Цена | K19: Норма | L19: н/ч | M19: Всего | N19: в т.ч. НДС
B20: 1 | C20: 2 | D20: 3 | I20: 4 | J20: 5 | K20: 6 | L20: 7 | M20: 8 | N20: 9
B21: 1 | D21: Шиномонтаж колеса (снять колесо, балансировка, поставить колесо) 1 шт. | I21: 4 | J21: 450 | K21: 1 | L21: Рубль | M21: =J21*I21 -> 1800 | N21: =M21*20/120 -> 300
B22: Итого работ: | I22: 4 | J22: на сумму: | M22: =M21 -> 1800 | N22: =M22*20/120 -> 300
B24: Одна тысяча восемьсот рублей 00 копеек
C26: Расходная накладная к заказ-наряду № 100517 от 12.11.2025
B28: № | C28: № кат. | D28: Наименование | J28: Кол-во | K28: Ед.изм. | L28: Цена | M28: Всего | N28: в т.ч. НДС
B29: 1 | C29: 2 | D29: 3 | J29: 4 | K29: 5 | L29: 6 | M29: 7 | N29: 8
B30: 1 | J30: 0 | K30: шт | L30: 0 | M30: =L30*J30 -> 0 | N30: =M30*20/120 -> 0
B31: Итого материалов: | J31: 0 | K31: на сумму: | M31: 0 | N31: =M31*20/120 -> 0
L35: Итого по заказ-наряду : | M35: =M22+M31 -> 1800 | N35: =N22+N31 -> 300
B37: Всего по заказ-наряду: Две тысячи четыреста рублей 00 копеек, в т.ч. НДС 20%
J40: Мастер _____________________ | K40: Механик СТО/
C42: Гарантии: Гарантия на работы: слесарные - 30 дней, электрические - 30 дней, оригинальные з/ч - 30 дней, з/ч, связанные с электрооборудованием, подачей топлива и системой впрыска - гарантии нет, неоригинальные з/ч - гарантии нет. Гарантийные обязательства на работы выполняются фирмой только при предъявлении акта приемки автомобиля и техпаспорта (доверенности).
B47: Дата: 12.11.2025 | J47: Заказчик ______________________ | K47: /Общество с ограниченной ответственностью «Концепт»/
J49: Плательщик ______________________ | K49: /Общество с ограниченной ответственностью «Концепт»/
B51: Причина обращения:

Sheet 488
B1: ПОСТАВЩИК: ООО ФИРМА "СИГНАЛ"
B2: адрес: 364031, Чеченская Республика, г.Грозный, ул. Жуковского, д. 18
C4: Заказ-наряд № 100516 от 12.11.2025
B6: Заказчик: Общество с ограниченной ответственностью «Концепт» | H6: адрес заказчика : 364024, ЧР г.Грозный, ул.Назарбаева, д.92, оф. 6-05
B7: Автомобиль : Volkswagen Multivan г/н С488ВС 15
B9: Цена автомототранспортного средства, определяемая по соглашению сторон __________________
B11: Плательщик: Общество с ограниченной ответственностью «Концепт»
B12: ИНН 2014030866 адрес: телефоны: +7 (989) 9002252
N14: в валюте
N15: Руб
C17: Выполненные работы по заказ-наряду № 100516 от 12.11.2025
B19: № | C19: № кат. | D19: Наименование | I19: Кол. оп. | J19: Цена | K19: Норма | L19: н/ч | M19: Всего | N19: в т.ч. НДС
B20: 1 | C20: 2 | D20: 3 | I20: 4 | J20: 5 | K20: 6 | L20: 7 | M20: 8 | N20: 9
B21: 1 | D21: Шиномонтаж колеса (снять колесо, балансировка, поставить колесо) 1 шт. | I21: 4 | J21: 650 | K21: 1 | L21: Рубль | M21: =J21*I21 -> 2600 | N21: =M21*20/120 -> 433.33333
B22: Итого работ: | I22: 4 | J22: на сумму: | M22: =M21 -> 2600 | N22: =M22*20/120 -> 433.33333
B24: Две тысячи шестьсот рублей 00 копеек
C26: Расходная накладная к заказ-наряду № 100516 от 12.11.2025
B28: № | C28: № кат. | D28: Наименование | J28: Кол-во | K28: Ед.изм. | L28: Цена | M28: Всего | N28: в т.ч. НДС
B29: 1 | C29: 2 | D29: 3 | J29: 4 | K29: 5 | L29: 6 | M29: 7 | N29: 8
B30: 1 | J30: 0 | K30: шт | L30: 0 | M30: =L30*J30 -> 0 | N30: =M30*20/120 -> 0
B31: Итого материалов: | J31: 0 | K31: на сумму: | M31: 0 | N31: =M31*20/120 -> 0
L35: Итого по заказ-наряду : | M35: =M22+M31 -> 2600 | N35: =N22+N31 -> 433.33333
B37: Всего по заказ-наряду: Две тысячи шестьсот рублей 00 копеек, в т.ч. НДС 20%
J40: Мастер _____________________ | K40: Механик СТО/
C42: Гарантии: Гарантия на работы: слесарные - 30 дней, электрические - 30 дней, оригинальные з/ч - 30 дней, з/ч, связанные с электрооборудованием, подачей топлива и системой впрыска - гарантии нет, неоригинальные з/ч - гарантии нет. Гарантийные обязательства на работы выполняются фирмой только при предъявлении акта приемки автомобиля и техпаспорта (доверенности).
B47: Дата: 12.11.2025 | J47: Заказчик ______________________ | K47: /Общество с ограниченной ответственностью «Концепт»/
J49: Плательщик ______________________ | K49: /Общество с ограниченной ответственностью «Концепт»/
B51: Причина обращения:

Sheet 560
B1: ПОСТАВЩИК: ООО ФИРМА "СИГНАЛ"
B2: адрес: 364031, Чеченская Республика, г.Грозный, ул. Жуковского, д. 18
C4: Заказ-наряд № 100512 от 11.11.2025
B6: Заказчик: Общество с ограниченной ответственностью «Концепт» | H6: адрес заказчика : 364024, ЧР г.Грозный, ул.Назарбаева, д.92, оф. 6-05
B7: Автомобиль : Тойота Камри гос. номер: А 560 ХС 15
B9: Цена автомототранспортного средства, определяемая по соглашению сторон __________________
B11: Плательщик: Общество с ограниченной ответственностью «Концепт»
B12: ИНН 2014030866 адрес: телефоны: +7 (989) 9002252
N14: в валюте
N15: Руб
C17: Выполненные работы по заказ-наряду № 100512 от 11.11.2025
B19: № | C19: № кат. | D19: Наименование | I19: Кол. оп. | J19: Цена | K19: Норма | L19: н/ч | M19: Всего | N19: в т.ч. НДС
B20: 1 | C20: 2 | D20: 3 | I20: 4 | J20: 5 | K20: 6 | L20: 7 | M20: 8 | N20: 9
B21: 1 | D21: Шиномонтаж колеса (снять колесо, балансировка, поставить колесо) 1 шт. | I21: 4 | J21: 450 | K21: 1 | L21: Рубль | M21: =J21*I21 -> 1800 | N21: =M21*20/120 -> 300
B22: Итого работ: | I22: 4 | J22: на сумму: | M22: =M21 -> 1800 | N22: =M22*20/120 -> 300
B24: Одна тысяча восемьсот рублей 00 копеек
C26: Расходная накладная к заказ-наряду № 100512 от 11.11.2025
B28: № | C28: № кат. | D28: Наименование | J28: Кол-во | K28: Ед.изм. | L28: Цена | M28: Всего | N28: в т.ч. НДС
B29: 1 | C29: 2 | D29: 3 | J29: 4 | K29: 5 | L29: 6 | M29: 7 | N29: 8
B30: 1 | J30: 0 | K30: шт | L30: 0 | M30: =L30*J30 -> 0 | N30: =M30*20/120 -> 0
B31: Итого материалов: | J31: 0 | K31: на сумму: | M31: 0 | N31: =M31*20/120 -> 0
L35: Итого по заказ-наряду : | M35: =M22+M31 -> 1800 | N35: =N22+N31 -> 300
B37: Всего по заказ-наряду: Одна тысяча восемьсот рублей 00 копеек, в т.ч. НДС 20%
J40: Мастер _____________________ | K40: Механик СТО/
C42: Гарантии: Гарантия на работы: слесарные - 30 дней, электрические - 30 дней, оригинальные з/ч - 30 дней, з/ч, связанные с электрооборудованием, подачей топлива и системой впрыска - гарантии нет, неоригинальные з/ч - гарантии нет. Гарантийные обязательства на работы выполняются фирмой только при предъявлении акта приемки автомобиля и техпаспорта (доверенности).
B47: Дата: 11.11.2025 | J47: Заказчик ______________________ | K47: /Общество с ограниченной ответственностью «Концепт»/
J49: Плательщик ______________________ | K49: /Общество с ограниченной ответственностью «Концепт»/
B51: Причина обращения:

Sheet 778 (2)
B1: ПОСТАВЩИК: ООО ФИРМА "СИГНАЛ"
B2: адрес: 364031, Чеченская Республика, г.Грозный, ул. Жуковского, д. 18
C4: Заказ-наряд № 100510 от 10.11.2025
B6: Заказчик: Общество с ограниченной ответственностью «Концепт» | H6: адрес заказчика : 364024, ЧР г.Грозный, ул.Назарбаева, д.92, оф. 6-05
B7: Автомобиль : Тойота Камри гос. номер: Е778РА 15
B9: Цена автомототранспортного средства, определяемая по соглашению сторон __________________
B11: Плательщик: Общество с ограниченной ответственностью «Концепт»
B12: ИНН 2014030866 адрес: телефоны: +7 (989) 9002252
N14: в валюте
N15: Руб
C17: Выполненные работы по заказ-наряду № 100510 от 10.11.2025
B19: № | C19: № кат. | D19: Наименование | I19: Кол. оп. | J19: Цена | K19: Норма | L19: н/ч | M19: Всего | N19: в т.ч. НДС
B20: 1 | C20: 2 | D20: 3 | I20: 4 | J20: 5 | K20: 6 | L20: 7 | M20: 8 | N20: 9
B21: 1 | D21: Шиномонтаж колеса (снять колесо,сборка-разборка, балансировка, поставить колесо) 1 шт. | I21: 4 | J21: 600 | K21: 1 | L21: Рубль | M21: =J21*I21 -> 2400 | N21: =M21*20/120 -> 400
B22: Итого работ: | I22: 4 | J22: на сумму: | M22: =M21 -> 2400 | N22: =M22*20/120 -> 400
B24: Две тысячи четыреста рублей 00 копеек
C26: Расходная накладная к заказ-наряду № 100510 от 10.11.2025
B28: № | C28: № кат. | D28: Наименование | J28: Кол-во | K28: Ед.изм. | L28: Цена | M28: Всего | N28: в т.ч. НДС
B29: 1 | C29: 2 | D29: 3 | J29: 4 | K29: 5 | L29: 6 | M29: 7 | N29: 8
B30: 1 | J30: 0 | K30: шт | L30: 0 | M30: =L30*J30 -> 0 | N30: =M30*20/120 -> 0
B31: Итого материалов: | J31: 0 | K31: на сумму: | M31: 0 | N31: =M31*20/120 -> 0
L35: Итого по заказ-наряду : | M35: =M22+M31 -> 2400 | N35: =N22+N31 -> 400
B37: Всего по заказ-наряду: Две тысячи четыреста рублей 00 копеек, в т.ч. НДС 20%
J40: Мастер _____________________ | K40: Механик СТО/
C42: Гарантии: Гарантия на работы: слесарные - 30 дней, электрические - 30 дней, оригинальные з/ч - 30 дней, з/ч, связанные с электрооборудованием, подачей топлива и системой впрыска - гарантии нет, неоригинальные з/ч - гарантии нет. Гарантийные обязательства на работы выполняются фирмой только при предъявлении акта приемки автомобиля и техпаспорта (доверенности).
B47: Дата: 10.11.2025 | J47: Заказчик ______________________ | K47: /Общество с ограниченной ответственностью «Концепт»/
J49: Плательщик ______________________ | K49: /Общество с ограниченной ответственностью «Концепт»/
B51: Причина обращения:

Sheet 488 (2)
B1: ПОСТАВЩИК: ООО ФИРМА "СИГНАЛ"
B2: адрес: 364031, Чеченская Республика, г.Грозный, ул. Жуковского, д. 18
C4: Заказ-наряд № 100503 от 02.06.2026
B6: Заказчик: Общество с ограниченной ответственностью «Концепт» | H6: адрес заказчика : 364024, ЧР г.Грозный, ул.Назарбаева, д.92, оф. 6-05
B7: Автомобиль : Volkswagen Multivan гос. номер: С488ВС 15
B9: Цена автомототранспортного средства, определяемая по соглашению сторон __________________
B11: Плательщик: Общество с ограниченной ответственностью «Концепт»
B12: ИНН 2014030866 адрес: телефоны: +7 (989) 9002252
N14: в валюте
N15: Руб
C17: Выполненные работы по заказ-наряду № 100503 от 02.06.2026
B19: № | C19: № кат. | D19: Наименование | I19: Кол. оп. | J19: Цена | K19: Норма | L19: н/ч | M19: Всего | N19: в т.ч. НДС
B20: 1 | C20: 2 | D20: 3 | I20: 4 | J20: 5 | K20: 6 | L20: 7 | M20: 8 | N20: 9
B21: 1 | D21: Замена масла и масл. Фильтра | I21: 1 | J21: 800 | K21: 1 | L21: Рубль | M21: =J21*I21 -> 800 | N21: =M21*22/122 -> 144.2623
B22: 2 | D22: Замена воздушного фильтра | I22: 1 | J22: 200 | K22: 1 | L22: Рубль | M22: =J22*I22 -> 200 | N22: =M22*22/122 -> 36.065574
B23: 3 | D23: Замена салонного фильтра | I23: 1 | J23: 200 | K23: 1 | L23: Рубль | M23: =J23*I23 -> 200 | N23: =M23*22/122 -> 36.065574
B24: 4 | D24: Диагностика подвески | I24: 1 | J24: 300 | K24: 1 | L24: Рубль | M24: =J24*I24 -> 300 | N24: =M24*22/122 -> 54.098361
B25: 5 | D25: Диагностика АКПП | I25: 1 | J25: 1500 | K25: 1 | L25: Рубль | M25: =J25*I25 -> 1500 | N25: =M25*22/122 -> 270.4918
B26: Итого работ: | I26: 5 | J26: на сумму: | M26: =M21+M22+M23+M24+M25 -> 3000 | N26: =M26*22/122 -> 540.98361
B28: Три тысячи рублей 00 копеек
C30: Расходная накладная к заказ-наряду № 100503 от 02.06.2026
B32: № | C32: № кат. | D32: Наименование | J32: Кол-во | K32: Ед.изм. | L32: Цена | M32: Всего | N32: в т.ч. НДС
B33: 1 | C33: 2 | D33: 3 | J33: 4 | K33: 5 | L33: 6 | M33: 7 | N33: 8
B34: 1 | C34: OP 526/7 | D34: Фильтр масляный vw tiguan 2008-, Multivan V Filtron | J34: 1 | K34: шт | L34: 1100 | M34: =L34*J34 -> 1100 | N34: =M34*22/122 -> 198.36066
B35: 2 | C35: AG 233 | D35: Фильтр воздушный GoodWill Volkswagen Multivan | J35: 1 | K35: шт | L35: 750 | M35: =L35*J35 -> 750 | N35: =M35*22/122 -> 135.2459
B36: 3 | C36: AG286CFC | D36: Фильтр салонный угольный Transporter (T5) GOODWILL | J36: 1 | K36: шт | L36: 750 | M36: =L36*J36 -> 750 | N36: =M36*22/122 -> 135.2459
B37: 4 | C37: 3149287 | D37: Масло моторное синт Лукойл 5W-30 GENESIS ARMORTECH НК, 4л | J37: 1.5 | K37: шт | L37: 3400 | M37: =L37*J37 -> 5100 | N37: =M37*22/122 -> 919.67213
B38: Итого материалов: | J38: 4,5 | K38: на сумму: | M38: =M34+M35+M36+M37 -> 7700 | N38: =M38*22/122 -> 1388.5246
B40: Семь тысяч семьсот рублей 00 копеек
L42: Итого по заказ-наряду : | M42: =M26+M38 -> 10700 | N42: =M42*22/122 -> 1929.5082
B44: Всего по заказ-наряду: Десять тысяч семьсот рублей 00 копеек
J47: Мастер _____________________ | K47: Механик СТО/
C49: Гарантии: Гарантия на работы: слесарные - 30 дней, электрические - 30 дней, оригинальные з/ч - 30 дней, з/ч, связанные с электрооборудованием, подачей топлива и системой впрыска - гарантии нет, неоригинальные з/ч - гарантии нет. Гарантийные обязательства на работы выполняются фирмой только при предъявлении акта приемки автомобиля и техпаспорта (доверенности).
B54: Дата: 02.06.2026 | J54: Заказчик ______________________ | K54: /Общество с ограниченной ответственностью «Концепт»/
J56: Плательщик ______________________ | K56: /Общество с ограниченной ответственностью «Концепт»/
B58: Причина обращения:

Sheet 301 (2)
B1: ПОСТАВЩИК: ООО ФИРМА "СИГНАЛ"
B2: адрес: 364031, Чеченская Республика, г.Грозный, ул. Жуковского, д. 18
C4: Заказ-наряд № 100511 от 03.06.2026
B6: Заказчик: Общество с ограниченной ответственностью «Концепт» | H6: адрес заказчика : 364024, ЧР г.Грозный, ул.Назарбаева, д.92, оф. 6-05
B7: Автомобиль : Toyota Camry г/н Е 301 ОУ /15
B9: Цена автомототранспортного средства, определяемая по соглашению сторон __________________
B11: Плательщик: Общество с ограниченной ответственностью «Концепт»
B12: ИНН 2014030866 адрес: телефоны: +7 (989) 9002252
N14: в валюте
N15: Руб
C17: Выполненные работы по заказ-наряду № 100511 от 03.06.2026
B19: № | C19: № кат. | D19: Наименование | I19: Кол. оп. | J19: Цена | K19: Норма | L19: н/ч | M19: Всего | N19: в т.ч. НДС
B20: 1 | C20: 2 | D20: 3 | I20: 4 | J20: 5 | K20: 6 | L20: 7 | M20: 8 | N20: 9
B21: 1 | D21: Замена масла и масл фильтра | I21: 1 | J21: 700 | K21: 1 | L21: Рубль | M21: =J21*I21 -> 700 | N21: =M21*22/122 -> 126.22951
B22: 2 | D22: Замена салонного фильтра | I22: 1 | J22: 150 | K22: 1 | L22: Рубль | M22: =J22*I22 -> 150 | N22: =M22*22/122 -> 27.04918
B23: 3 | D23: Замена воздушного фильтра | I23: 1 | J23: 150 | K23: 1 | L23: Рубль | M23: =J23*I23 -> 150 | N23: =M23*22/122 -> 27.04918
B24: Итого работ: | I24: 3 | J24: на сумму: | M24: =M21+M22+M23 -> 1000 | N24: =M24*22/122 -> 180.32787
B26: Одна тысяча рублей 00 копеек
C28: Расходная накладная к заказ-наряду № 100511 от 03.06.2026
B30: № | C30: № кат. | D30: Наименование | J30: Кол-во | K30: Ед.изм. | L30: Цена | M30: Всего | N30: в т.ч. НДС
B31: 1 | C31: 2 | D31: 3 | J31: 4 | K31: 5 | L31: 6 | M31: 7 | N31: 8
B32: 1 | C32: TO1191 | D32: Фильтр масляный Alphard Camry Rav4 rx350 highlander Lexus ES Totachi | J32: 1 | K32: шт | L32: 450 | M32: =L32*J32 -> 450 | N32: =M32*22/122 -> 81.147541
B33: 2 | C33: FAP4625C | D33: Фильтр салона угольный TO Camry VIII,RAV4 V 18- Pilenga | J33: 1 | K33: шт | L33: 650 | M33: =L33*J33 -> 650 | N33: =M33*22/122 -> 117.21311
B34: 3 | C34: 08880-86084 | D34: Моторное масло Toyota Synthetic 5W-40, 5л | J34: 1,1 | K34: шт | L34: 6500 | M34: =L34*J34 -> 7150 | N34: =M34*22/122 -> 1289.3443
B35: 4 | C35: MFA 233 | D35: Фильтр воздушный Camry V70 MASUMA | J35: 1 | K35: шт | L35: 800 | M35: =L35*J35 -> 800 | N35: =M35*22/122 -> 144.2623
B36: Итого материалов: | J36: 4,1 | K36: на сумму: | M36: =M32+M33+M34+M35 -> 9050 | N36: =M36*22/122 -> 1631.9672
B38: Девять тысяч пятьдесят рублей 00 копеек
L40: Итого по заказ-наряду : | M40: =M24+M36 -> 10050 | N40: =M40*20/120 -> 1675
B42: Всего по заказ-наряду: Десять тысяч пятьдесят рублей 00 копеек, в т.ч. НДС 22%.
J45: Мастер _____________________ | K45: Механик СТО/
C47: Гарантии: Гарантия на работы: слесарные - 30 дней, электрические - 30 дней, оригинальные з/ч - 30 дней, з/ч, связанные с электрооборудованием, подачей топлива и системой впрыска - гарантии нет, неоригинальные з/ч - гарантии нет. Гарантийные обязательства на работы выполняются фирмой только при предъявлении акта приемки автомобиля и техпаспорта (доверенности).
B52: Дата: 03.06.2026 | J52: Заказчик ______________________ | K52: /Общество с ограниченной ответственностью «Концепт»/
J54: Плательщик ______________________ | K54: /Общество с ограниченной ответственностью «Концепт»/
B56: Причина обращения:

Sheet 787
B1: ПОСТАВЩИК: ООО ФИРМА "СИГНАЛ"
B2: адрес: 364031, Чеченская Республика, г.Грозный, ул. Жуковского, д. 18
C4: Заказ-наряд № 100558 от 11.06.2026
B6: Заказчик: Общество с ограниченной ответственностью «Концепт» | H6: адрес заказчика : 364024, ЧР г.Грозный, ул.Назарбаева, д.92, оф. 6-05
B7: Автомобиль : УАЗ Патриот г/н В 787 ОХ/15
B9: Цена автомототранспортного средства, определяемая по соглашению сторон __________________
B11: Плательщик: Общество с ограниченной ответственностью «Концепт»
B12: ИНН 2014030866 адрес: телефоны: +7 (989) 9002252
N14: в валюте
N15: Руб
C17: Выполненные работы по заказ-наряду № 100558 от 11.06.2026
B19: № | C19: № кат. | D19: Наименование | I19: Кол. оп. | J19: Цена | K19: Норма | L19: н/ч | M19: Всего | N19: в т.ч. НДС
B20: 1 | C20: 2 | D20: 3 | I20: 4 | J20: 5 | K20: 6 | L20: 7 | M20: 8 | N20: 9
B21: 1 | D21: Диагностика ДВС | I21: 1 | J21: 1000 | K21: 1 | L21: Рубль | M21: =J21*I21 -> 1000 | N21: =M21*22/122 -> 180.32787
B22: 2 | D22: Диагностика АВС | I22: 1 | J22: 400 | K22: 1 | L22: Рубль | M22: =J22*I22 -> 400 | N22: =M22*22/122 -> 72.131148
B23: 3 | D23: Замена датчика АВС | I23: 1 | J23: 500 | K23: 1 | L23: Рубль | M23: =J23*I23 -> 500 | N23: =M23*22/122 -> 90.163934
B24: 4 | D24: Замена подшипника пер ступицы | I24: 1 | J24: 1000 | K24: 1 | L24: Рубль | M24: =J24*I24 -> 1000 | N24: =M24*22/122 -> 180.32787
B25: 5 | D25: Замена тормозного диска | I25: 1 | J25: 600 | K25: 1 | L25: Рубль | M25: =J25*I25 -> 600 | N25: =M25*22/122 -> 108.19672
B26: 6 | D26: Замена пер-х торм-х колодок | I26: 1 | J26: 600 | K26: 1 | L26: Рубль | M26: =J26*I26 -> 600 | N26: =M26*22/122 -> 108.19672
B27: 7 | D27: Регулировка подшипника ступицы | I27: 1 | J27: 700 | K27: 1 | L27: Рубль | M27: =J27*I27 -> 700 | N27: =M27*22/122 -> 126.22951
B28: Итого работ: | I28: 7 | J28: на сумму: | M28: =M21+M22+M23+M24+M25+M26+M27 -> 4800 | N28: =M28*22/122 -> 865.57377
B30: Четыре тысячи восемьсот рублей 00 копеек.
C32: Расходная накладная к заказ-наряду № 100558 от 11.06.2026
B34: № | C34: № кат. | D34: Наименование | J34: Кол-во | K34: Ед.изм. | L34: Цена | M34: Всего | N34: в т.ч. НДС
B35: 1 | C35: 2 | D35: 3 | J35: 4 | K35: 5 | L35: 6 | M35: 7 | N35: 8
B36: 1 | C36: 663322 | D36: Смазка Литол-24 250мл Sintec | J36: 1 | K36: шт | L36: 150 | M36: =L36*J36 -> 150 | N36: =M36*22/122 -> 27.04918
B37: 2 | C37: ADB0610 | D37: Колодки тормозные дисковые перед УАЗ Патриот кт NIPPON | J37: 1 | K37: шт | L37: 1260 | M37: =L37*J37 -> 1260 | N37: =M37*22/122 -> 227.21311
B38: 3 | C38: 3160-3501076 | D38: Диск тормозной УАЗ ХАНТЕР, ПАТРИОТ, 452 BAST | J38: 1 | K38: шт | L38: 2200 | M38: =L38*J38 -> 2200 | N38: =M38*22/122 -> 396.72131
B39: 4 | C39: CS751 | D39: Ремкомплект УАЗ 3151,3160 передней и задней ступицы (подшипники сальник)"TRIALLI" | J39: 1 | K39: кт | L39: 1800 | M39: =L39*J39 -> 1800 | N39: =M39*22/122 -> 324.59016
B40: 5 | C40: 69-3103024 | D40: Кольцо стопорное подшипника ступицы Уаз 469, 3163, 3741 (ОАО УАЗ) | J40: 1 | K40: шт | L40: 100 | M40: =L40*J40 -> 100 | N40: =M40*22/122 -> 18.032787
B41: 6 | C41: 265007799 | D41: Датчик АБС УАЗ Patriot,Hunter BOSCH | J41: 1 | K41: шт | L41: 2440 | M41: =L41*J41 -> 2440 | N41: =M41*22/122 -> 440
B42: Итого материалов: | J42: 7 | K42: на сумму: | M42: =M36+M37+M38+M39+M40+M41 -> 7950 | N42: =M42*22/122 -> 1433.6066
B44: Семь тысяч девятьсот пятьдесят рублей 00 копеек
L46: Итого по заказ-наряду : | M46: =M28+M42 -> 12750 | N46: =M46*22/122 -> 2299.1803
B48: Всего по заказ-наряду: Двенадцать тысяч семьсот пятьдесят рублей 00 копеек, в т.ч. НДС 22%.
J51: Мастер _____________________ | K51: Механик СТО/
C53: Гарантии: Гарантия на работы: слесарные - 30 дней, электрические - 30 дней, оригинальные з/ч - 30 дней, з/ч, связанные с электрооборудованием, подачей топлива и системой впрыска - гарантии нет, неоригинальные з/ч - гарантии нет. Гарантийные обязательства на работы выполняются фирмой только при предъявлении акта приемки автомобиля и техпаспорта (доверенности).
B57: Дата: 11.06.2026 | J57: Заказчик ______________________ | K57: /ООО «Концепт»/
J59: Плательщик ______________________ | K59: /ООО «Концепт»/
B61: Причина обращения:

Sheet 725
B1: ПОСТАВЩИК: ООО ФИРМА "СИГНАЛ"
B2: адрес: 364031, Чеченская Республика, г.Грозный, ул. Жуковского, д. 18
C4: Заказ-наряд № 100560 от 11.06.2026
B6: Заказчик: Общество с ограниченной ответственностью «Концепт» | H6: адрес заказчика : 364024, ЧР г.Грозный, ул.Назарбаева, д.92, оф. 6-05
B7: Автомобиль : Лада Веста г/н А 725 НА/15
B9: Цена автомототранспортного средства, определяемая по соглашению сторон __________________
B11: Плательщик: Общество с ограниченной ответственностью «Концепт»
B12: ИНН 2014030866 адрес: телефоны: +7 (989) 9002252
N14: в валюте
N15: Руб
C17: Выполненные работы по заказ-наряду № 100560 от 11.06.2026
B19: № | C19: № кат. | D19: Наименование | I19: Кол. оп. | J19: Цена | K19: Норма | L19: н/ч | M19: Всего | N19: в т.ч. НДС
B20: 1 | C20: 2 | D20: 3 | I20: 4 | J20: 5 | K20: 6 | L20: 7 | M20: 8 | N20: 9
B21: 1 | D21: Замена амортизатора заднего | I21: 2 | J21: 800 | K21: 1 | L21: Рубль | M21: =J21*I21 -> 1600 | N21: =M21*22/122 -> 288.52459
B22: 2 | D22: Замена пер. торм. диска с колодками | I22: 2 | J22: 650 | K22: 1 | L22: Рубль | M22: =J22*I22 -> 1300 | N22: =M22*22/122 -> 234.42623
B23: 3 | D23: Замена масла и масл. фильтра | I23: 1 | J23: 500 | K23: 1 | L23: Рубль | M23: =J23*I23 -> 500 | N23: =M23*22/122 -> 90.163934
B24: 4 | D24: Замена воздушного фильтра | I24: 1 | J24: 150 | K24: 1 | L24: Рубль | M24: =J24*I24 -> 150 | N24: =M24*22/122 -> 27.04918
B25: 5 | D25: Замена салонного фильтра | I25: 1 | J25: 150 | K25: 1 | L25: Рубль | M25: =J25*I25 -> 150 | N25: =M25*22/122 -> 27.04918
B26: 6 | D26: Замена стойки стабилизатора | I26: 1 | J26: 600 | K26: 1 | L26: Рубль | M26: =J26*I26 -> 600 | N26: =M26*22/122 -> 108.19672
B27: 7 | D27: Сварка глушителя | I27: 1 | J27: 600 | K27: 1 | L27: Рубль | M27: =J27*I27 -> 600 | N27: =M27*22/122 -> 108.19672
B28: 8 | D28: Диагностика кондиционера с опрессовкой | I28: 1 | J28: 1000 | K28: 1 | L28: Рубль | M28: =J28*I28 -> 1000 | N28: =M28*22/122 -> 180.32787
B29: 9 | D29: Замена радиатора охлаждения | I29: 1 | J29: 4500 | K29: 1 | L29: Рубль | M29: =J29*I29 -> 4500 | N29: =M29*22/122 -> 811.47541
B30: 10 | D30: Замена радиатора кондиционера | I30: 1 | J30: 2000 | K30: 1 | L30: Рубль | M30: =J30*I30 -> 2000 | N30: =M30*22/122 -> 360.65574
B31: 11 | D31: Ремонт электрооборудования | I31: 1 | J31: 1000 | K31: 1 | L31: Рубль | M31: =J31*I31 -> 1000 | N31: =M31*22/122 -> 180.32787
B32: 12 | D32: Заправка кондиционера | I32: 1 | J32: 4500 | K32: 1 | L32: Рубль | M32: =J32*I32 -> 4500 | N32: =M32*22/122 -> 811.47541
B33: 13 | D33: Замена насоса водяного | I33: 1 | J33: 4500 | K33: 1 | L33: Рубль | M33: =J33*I33 -> 4500 | N33: =M33*22/122 -> 811.47541
B34: Итого работ: | I34: 15 | J34: на сумму: | M34: =M21+M22+M23+M24+M25+M26+M27+M28+M29+M30+M31+M32+M33 -> 22400 | N34: =M34*22/122 -> 4039.3443
B36: Двадцать две тысячи четыреста рублей 00 копеек.
C38: Расходная накладная к заказ-наряду № 100560 от 11.06.2026
B40: № | C40: № кат. | D40: Наименование | J40: Кол-во | K40: Ед.изм. | L40: Цена | M40: Всего | N40: в т.ч. НДС
B41: 1 | C41: 2 | D41: 3 | J41: 4 | K41: 5 | L41: 6 | M41: 7 | N41: 8
B42: 1 | C42: 3148646 | D42: Масло Лукойл GENESIS UNIVERSAL 10W40, 4 л | J42: 1 | K42: шт | L42: 1850 | M42: =L42*J42 -> 1850 | N42: =M42*22/122 -> 333.60656
B43: 2 | C43: LF105 | D43: Фильтр масляный LADA 08-112 FINWHALE | J43: 1 | K43: шт | L43: 400 | M43: =L43*J43 -> 400 | N43: =M43*22/122 -> 72.131148
B44: 3 | C44: AG448 CF | D44: Фильтр салона LADA Vesta, X-RAY Goodwill | J44: 1 | K44: шт | L44: 450 | M44: =L44*J44 -> 450 | N44: =M44*22/122 -> 81.147541
B45: 4 | C45: 77143 | D45: Фильтр воздушный ВАЗ 2180 Vesta н/образца 1.6 19- NAC | J45: 1 | K45: шт | L45: 400 | M45: =L45*J45 -> 400 | N45: =M45*22/122 -> 72.131148
B46: 5 | C46: AB8450031577 | D46: Диск тормозной LADA Vesta SW/SW Cross LADA Vesta SW/SW Cross AVTOREAL | J46: 2 | K46: шт | L46: 2300 | M46: =L46*J46 -> 4600 | N46: =M46*22/122 -> 829.5082
B47: 6 | C47: SP1564 | D47: Колодки тормозные передние Lada Vesta SANGSIN (HI-Q) | J47: 1 | K47: кт | L47: 1650 | M47: =L47*J47 -> 1650 | N47: =M47*22/122 -> 297.54098
B48: 7 | C48: 8450006786 | D48: Амортизатор задний ВАЗ LADA Vesta левый/правый газомасляный LADA (СААЗ) | J48: 2 | K48: шт | L48: 3200 | M48: =L48*J48 -> 6400 | N48: =M48*22/122 -> 1154.0984
B49: 8 | C49: SP0102 | D49: Стойка стабилизатора TRIALLI ВАЗ Лада Vesta переднего | J49: 1 | K49: шт | L49: 900 | M49: =L49*J49 -> 900 | N49: =M49*22/122 -> 162.29508
B50: 9 | C50: AB-8-100-R | D50: Смазка универсальная проникающая Abro Masters (100 мл) аналог WD-40 | J50: 1 | K50: шт | L50: 250 | M50: =L50*J50 -> 250 | N50: =M50*22/122 -> 45.081967
B51: 10 | C51: GMRCL18589 | D51: Радиатор охлаждения LADA Vesta/Веста GAMMA | J51: 1 | K51: шт | L51: 5300 | M51: =L51*J51 -> 5300 | N51: =M51*22/122 -> 955.7377
B52: 11 | C52: ST-DC02-394-0 | D52: Радиатор кондиционера Lada Vesta, X-ray, Renault Logan 2 SAT | J52: 1 | K52: шт | L52: 5600 | M52: =L52*J52 -> 5600 | N52: =M52*22/122 -> 1009.8361
B53: 12 | C53: 614503 | D53: Антифриз Sintec LUXE G12+, 5 кг, красный | J53: 1 | K53: кт | L53: 1000 | M53: =L53*J53 -> 1000 | N53: =M53*22/122 -> 180.32787
B54: 13 | C54: 990550 | D54: Антифриз Sintec красный -40С 1кг | J54: 1 | K54: шт | L54: 250 | M54: =L54*J54 -> 250 | N54: =M54*22/122 -> 45.081967
B55: 14 | C55: LWP0127 | D55: Насос водяной LADA KALINA PRIORA VESTA X-RAY LUZAR | J55: 1 | K55: шт | L55: 1750 | M55: =L55*J55 -> 1750 | N55: =M55*22/122 -> 315.57377
B56: Итого материалов: | J56: 16 | K56: на сумму: | M56: =M42+M43+M44+M45+M46+M47+M48+M49+M50+M51+M52+M53+M54+M55 -> 30800 | N56: =M56*22/122 -> 5554.0984
B58: Тридцать тысяч восемьсот рублей 00 копеек
L60: Итого по заказ-наряду : | M60: =M34+M56 -> 53200 | N60: =M60*22/122 -> 9593.4426
B62: Всего по заказ-наряду: Пятьдесят три тысячи двести рублей 00 копеек, в т.ч. НДС 22%.
J65: Мастер _____________________ | K65: Механик СТО/
C67: Гарантии: Гарантия на работы: слесарные - 30 дней, электрические - 30 дней, оригинальные з/ч - 30 дней, з/ч, связанные с электрооборудованием, подачей топлива и системой впрыска - гарантии нет, неоригинальные з/ч - гарантии нет. Гарантийные обязательства на работы выполняются фирмой только при предъявлении акта приемки автомобиля и техпаспорта (доверенности).
B71: Дата: 11.06.2026 | J71: Заказчик ______________________ | K71: /Общество с ограниченной ответственностью «Концепт»/
J73: Плательщик ______________________ | K73: /Общество с ограниченной ответственностью «Концепт»/
B75: Причина обращения:

Sheet 722
B1: ПОСТАВЩИК: ООО ФИРМА "СИГНАЛ"
B2: адрес: 364031, Чеченская Республика, г.Грозный, ул. Жуковского, д. 18
C4: Заказ-наряд № 100555 от 10.06.2026
B6: Заказчик: Общество с ограниченной ответственностью «Концепт» | H6: адрес заказчика : 364024, ЧР г.Грозный, ул.Назарбаева, д.92, оф. 6-05
B7: Автомобиль : Лада Гранта г/н А722НА 15
B9: Цена автомототранспортного средства, определяемая по соглашению сторон __________________
B11: Плательщик: Общество с ограниченной ответственностью «Концепт»
B12: ИНН 2014030866 адрес: телефоны: +7 (989) 9002252
N14: в валюте
N15: Руб
C17: Выполненные работы по заказ-наряду № 100555 от 10.06.2026
B19: № | C19: № кат. | D19: Наименование | I19: Кол. оп. | J19: Цена | K19: Норма | L19: н/ч | M19: Всего | N19: в т.ч. НДС
B20: 1 | C20: 2 | D20: 3 | I20: 4 | J20: 5 | K20: 6 | L20: 7 | M20: 8 | N20: 9
B21: 1 | D21: Замена масла и масл. фильтра | I21: 1 | J21: 500 | K21: 1 | L21: Рубль | M21: =J21*I21 -> 500 | N21: =M21*22/122 -> 90.163934
B22: 2 | D22: Замена воздушного фильтра | I22: 1 | J22: 200 | K22: 1 | L22: Рубль | M22: =J22*I22 -> 200 | N22: =M22*22/122 -> 36.065574
B23: 3 | D23: Замена салонного фильтра | I23: 1 | J23: 300 | K23: 1 | L23: Рубль | M23: =J23*I23 -> 300 | N23: =M23*22/122 -> 54.098361
B24: 4 | D24: Замена свечей зажигания | I24: 1 | J24: 400 | K24: 1 | L24: Рубль | M24: =J24*I24 -> 400 | N24: =M24*22/122 -> 72.131148
B25: 5 | D25: Диагностика подвески | I25: 1 | J25: 300 | K25: 1 | L25: Рубль | M25: =J25*I25 -> 300 | N25: =M25*22/122 -> 54.098361
B26: 6 | D26: Замена шаровой опоры | I26: 2 | J26: 350 | K26: 1 | L26: Рубль | M26: =J26*I26 -> 700 | N26: =M26*22/122 -> 126.22951
B27: 7 | D27: Замена рулевого наконечника | I27: 2 | J27: 300 | K27: 1 | L27: Рубль | M27: =J27*I27 -> 600 | N27: =M27*22/122 -> 108.19672
B28: 8 | D28: Ремонт рулевой рейки | I28: 1 | J28: 5000 | K28: 1 | L28: Рубль | M28: =J28*I28 -> 5000 | N28: =M28*22/122 -> 901.63934
B29: 9 | D29: Ремонт ЭУР со снятием и установкой | I29: 1 | J29: 7500 | K29: 1 | L29: Рубль | M29: =J29*I29 -> 7500 | N29: =M29*22/122 -> 1352.459
B30: 10 | D30: Балансировка колеса | I30: 2 | J30: 350 | K30: 1 | L30: Рубль | M30: =J30*I30 -> 700 | N30: =M30*22/122 -> 126.22951
B31: 11 | D31: Сход-развал | I31: 1 | J31: 1500 | K31: 1 | L31: Рубль | M31: =J31*I31 -> 1500 | N31: =M31*22/122 -> 270.4918
B32: Итого работ: | I32: 14 | J32: на сумму: | M32: =M21+M22+M23+M24+M25+M26+M27+M28+M29+M30+M31 -> 17700 | N32: =M32*22/122 -> 3191.8033
B34: Семнадцать тысяч семьсот рублей 00 копеек.
C36: Расходная накладная к заказ-наряду № 100555 от 10.06.2026
B38: № | C38: № кат. | D38: Наименование | J38: Кол-во | K38: Ед.изм. | L38: Цена | M38: Всего | N38: в т.ч. НДС
B39: 1 | C39: 2 | D39: 3 | J39: 4 | K39: 5 | L39: 6 | M39: 7 | N39: 8
B40: 1 | C40: LF105 | D40: Фильтр масляный LADA 08-112 FINWHALE | J40: 1 | K40: шт | L40: 400 | M40: =L40*J40 -> 400 | N40: =M40*22/122 -> 72.131148
B41: 2 | C41: 3705307 | D41: Масло моторное "Люкс 10W-40", 1л Лукойл | J41: 1 | K41: шт | L41: 500 | M41: =L41*J41 -> 500 | N41: =M41*22/122 -> 90.163934
B42: 3 | C42: 3705304 | D42: Масло моторное Лукойл Люкс 10W-40 (4л) | J42: 1 | K42: шт | L42: 1600 | M42: =L42*J42 -> 1600 | N42: =M42*22/122 -> 288.52459
B43: 4 | C43: BM FA2108 | D43: Фильтр воздушный, плоский для LADA ВАЗ 2108-2112 (инж) BM | J43: 1 | K43: шт | L43: 350 | M43: =L43*J43 -> 350 | N43: =M43*22/122 -> 63.114754
B44: 5 | C44: А17ДВРМ | D44: Свечи А17ДВРМ Стандарт "33" 8кл | J44: 1 | K44: кт | L44: 600 | M44: =L44*J44 -> 600 | N44: =M44*22/122 -> 108.19672
B45: 6 | C45: 1481 | D45: Пыльник рулевой рейки 2110-12 2170 Priora Балаково ОАО БРТ | J45: 1 | K45: шт | L45: 450 | M45: =L45*J45 -> 450 | N45: =M45*22/122 -> 81.147541
B46: 7 | C46: 631031 | D46: Смазка Литол-24 SINTEC 100 г желтая | J46: 2 | K46: шт | L46: 100 | M46: =L46*J46 -> 200 | N46: =M46*22/122 -> 36.065574
B47: 8 | C47: RK01010 | D47: Ремкомплект рулевой рейки ВАЗ-2110-2112 РемКом | J47: 1 | K47: кт | L47: 450 | M47: =L47*J47 -> 450 | N47: =M47*22/122 -> 81.147541
B48: 9 | C48: 21900341410086 | D48: Наконечник рулевой Ваз 2110-70, 2190 лев/прав ОАО АВТОВАЗ | J48: 1 | K48: кт | L48: 1900 | M48: =L48*J48 -> 1900 | N48: =M48*22/122 -> 342.62295
B49: 10 | C49: BM0033 | D49: Шаровая опора БелМаг Оригинал ВАЗ 2108-2170, Приора, Приора 2, Гранта FL | J49: 2 | K49: шт | L49: 650 | M49: =L49*J49 -> 1300 | N49: =M49*22/122 -> 234.42623
B50: 11 | C50: 11180812201082 | D50: Фильтр салона Ваз 1118, 2190, 2123 ОАО АВТОВАЗ | J50: 1 | K50: шт | L50: 400 | M50: =L50*J50 -> 400 | N50: =M50*22/122 -> 72.131148
B51: Итого материалов: | J51: 13 | K51: на сумму: | M51: =M40+M41+M42+M43+M44+M45+M46+M47+M48+M49+M50 -> 8150 | N51: =M51*22/122 -> 1469.6721
B53: Восемь тысяч сто пятьдесят рублей 00 копеек
L55: Итого по заказ-наряду : | M55: =M32+M51 -> 25850 | N55: =M55*22/122 -> 4661.4754
B57: Всего по заказ-наряду: Двадцать пять тысяч восемьсот пятьдесят рублей 00 копеек, в т.ч. НДС 22%.
J60: Мастер _____________________ | K60: Механик СТО/
C62: Гарантии: Гарантия на работы: слесарные - 30 дней, электрические - 30 дней, оригинальные з/ч - 30 дней, з/ч, связанные с электрооборудованием, подачей топлива и системой впрыска - гарантии нет, неоригинальные з/ч - гарантии нет. Гарантийные обязательства на работы выполняются фирмой только при предъявлении акта приемки автомобиля и техпаспорта (доверенности).
B66: Дата: 10.06.2026 | J66: Заказчик ______________________ | K66: /Общество с ограниченной ответственностью «Концепт»/
J68: Плательщик ______________________ | K68: /Общество с ограниченной ответственностью «Концепт»/
B70: Причина обращения:

Sheet 678 (2)
B1: ПОСТАВЩИК: ООО ФИРМА "СИГНАЛ"
B2: адрес: 364031, Чеченская Республика, г.Грозный, ул. Жуковского, д. 18
C4: Заказ-наряд № 100551 от 09.06.2026
B6: Заказчик: Общество с ограниченной ответственностью «Концепт» | H6: адрес заказчика : 364024, ЧР г.Грозный, ул.Назарбаева, д.92, оф. 6-05
B7: Автомобиль : Лада 213100 г/н А678ХМ 126
B9: Цена автомототранспортного средства, определяемая по соглашению сторон __________________
B11: Плательщик: Общество с ограниченной ответственностью «Концепт»
B12: ИНН 2014030866 адрес: телефоны: +7 (989) 9002252
N14: в валюте
N15: Руб
C17: Выполненные работы по заказ-наряду № 100551 от 09.06.2026
B19: № | C19: № кат. | D19: Наименование | I19: Кол. оп. | J19: Цена | K19: Норма | L19: н/ч | M19: Всего | N19: в т.ч. НДС
B20: 1 | C20: 2 | D20: 3 | I20: 4 | J20: 5 | K20: 6 | L20: 7 | M20: 8 | N20: 9
B21: 1 | D21: Диагностика генератора | I21: 1 | J21: 400 | K21: 1 | L21: Рубль | M21: =J21*I21 -> 400 | N21: =M21*22/122 -> 72.131148
B22: 2 | D22: Замена генератора | I22: 1 | J22: 1200 | K22: 1 | L22: Рубль | M22: =J22*I22 -> 1200 | N22: =M22*22/122 -> 216.39344
B23: 3 | D23: Замена крана отопителя | I23: 1 | J23: 600 | K23: 1 | L23: Рубль | M23: =J23*I23 -> 600 | N23: =M23*22/122 -> 108.19672
B24: 4 | D24: Диагностика тормозной системы | I24: 1 | J24: 400 | K24: 1 | L24: Рубль | M24: =J24*I24 -> 400 | N24: =M24*22/122 -> 72.131148
B25: 5 | D25: Замена задних торм-х колодок | I25: 1 | J25: 1300 | K25: 1 | L25: Рубль | M25: =J25*I25 -> 1300 | N25: =M25*22/122 -> 234.42623
B26: Итого работ: | I26: 5 | J26: на сумму: | M26: =M21+M22+M23+M24+M25 -> 3900 | N26: =M26*22/122 -> 703.27869
B28: Три тысячи девятьсот рублей 00 копеек.
C30: Расходная накладная к заказ-наряду № 100551 от 09.06.2026
B32: № | C32: № кат. | D32: Наименование | J32: Кол-во | K32: Ед.изм. | L32: Цена | M32: Всего | N32: в т.ч. НДС
B33: 1 | C33: 2 | D33: 3 | J33: 4 | K33: 5 | L33: 6 | M33: 7 | N33: 8
B34: 1 | C34: 2101350209090 | D34: Колодки задние комплект ВАЗ 2101-07 2121-213 2123 АВТОВАЗ кт | J34: 1 | K34: кт | L34: 1600 | M34: =L34*J34 -> 1600 | N34: =M34*22/122 -> 288.52459
B35: 2 | C35: LV0101 | D35: Кран ВАЗ-2101-2107 отопителя LUZAR | J35: 1 | K35: кт | L35: 600 | M35: =L35*J35 -> 600 | N35: =M35*22/122 -> 108.19672
B36: 3 | C36: 94123701С | D36: Генератор 14В, 140А ВАЗ-2123 (до окт. 2003г.) ВАЗ-21214 Нива АвтоЭлектрика) | J36: 1 | K36: шт | L36: 7200 | M36: =L36*J36 -> 7200 | N36: =M36*22/122 -> 1298.3607
B37: Итого материалов: | J37: 3 | K37: на сумму: | M37: =M34+M35+M36 -> 9400 | N37: =M37*22/122 -> 1695.082
B39: Девять тысяч четыреста рублей 00 копеек
L41: Итого по заказ-наряду : | M41: =M26+M37 -> 13300 | N41: =M41*22/122 -> 2398.3607
B43: Всего по заказ-наряду: Тринадцать тысяч триста рублей 00 копеек, в т.ч. НДС 22%.
J46: Мастер _____________________ | K46: Механик СТО/
C48: Гарантии: Гарантия на работы: слесарные - 30 дней, электрические - 30 дней, оригинальные з/ч - 30 дней, з/ч, связанные с электрооборудованием, подачей топлива и системой впрыска - гарантии нет, неоригинальные з/ч - гарантии нет. Гарантийные обязательства на работы выполняются фирмой только при предъявлении акта приемки автомобиля и техпаспорта (доверенности).
B52: Дата: 09.06.2026 | J52: Заказчик ______________________ | K52: /ООО «Концепт»/
J54: Плательщик ______________________ | K54: /ООО «Концепт»/
B56: Причина обращения:

Sheet 723
B1: ПОСТАВЩИК: ООО ФИРМА "СИГНАЛ"
B2: адрес: 364031, Чеченская Республика, г.Грозный, ул. Жуковского, д. 18
C4: Заказ-наряд № 100516 от 05.06.2026
B6: Заказчик: Общество с ограниченной ответственностью «Концепт» | H6: адрес заказчика : 364024, ЧР г.Грозный, ул.Назарбаева, д.92, оф. 6-05
B7: Автомобиль : УАЗ Есаул 394511-03 г/н В723УУ 15
B9: Цена автомототранспортного средства, определяемая по соглашению сторон __________________
B11: Плательщик: Общество с ограниченной ответственностью «Концепт»
B12: ИНН 2014030866 адрес: телефоны: +7 (989) 9002252
N14: в валюте
N15: Руб
C17: Выполненные работы по заказ-наряду № 100516 от 05.06.2026
B19: № | C19: № кат. | D19: Наименование | I19: Кол. оп. | J19: Цена | K19: Норма | L19: н/ч | M19: Всего | N19: в т.ч. НДС
B20: 1 | C20: 2 | D20: 3 | I20: 4 | J20: 5 | K20: 6 | L20: 7 | M20: 8 | N20: 9
B21: 1 | D21: Диагностика кондиционера | I21: 1 | J21: 800 | K21: 1 | L21: Рубль | M21: =J21*I21 -> 800 | N21: =M21*22/122 -> 144.2623
B22: 2 | D22: Замена ремня генератора | I22: 1 | J22: 1200 | K22: 1 | L22: Рубль | M22: =J22*I22 -> 1200 | N22: =M22*22/122 -> 216.39344
B23: 3 | D23: Заправка кондиционера | I23: 1 | J23: 4500 | K23: 1 | L23: Рубль | M23: =J23*I23 -> 4500 | N23: =M23*22/122 -> 811.47541
B24: Итого работ: | I24: 3 | J24: на сумму: | M24: =M21+M22+M23 -> 6500 | N24: =M24*22/122 -> 1172.1311
B26: Шесть тысяч пятьсот рублей 00 копеек.
C28: Расходная накладная к заказ-наряду № 100516 от 05.06.2026
B30: № | C30: № кат. | D30: Наименование | J30: Кол-во | K30: Ед.изм. | L30: Цена | M30: Всего | N30: в т.ч. НДС
B31: 1 | C31: 2 | D31: 3 | J31: 4 | K31: 5 | L31: 6 | M31: 7 | N31: 8
B32: 1 | C32: 1987947833 | D32: Ремень 2100 привода агрегатов (6/РК-2100) поликлин.Патриот с кондиц.BOSCH | J32: 1 | K32: шт | L32: 1400 | M32: =L32*J32 -> 1400 | N32: =M32*22/122 -> 252.45902
B33: Итого материалов: | J33: 1 | K33: на сумму: | M33: =M32 -> 1400 | N33: =M33*22/122 -> 252.45902
B35: Одна тысяча четыреста рублей 00 копеек
L37: Итого по заказ-наряду : | M37: =M24+M33 -> 7900 | N37: =M37*22/122 -> 1424.5902
B39: Всего по заказ-наряду: Семь тысяч девятьсот рублей 00 копеек, в т.ч. НДС 22%.
J42: Мастер _____________________ | K42: Механик СТО/
C44: Гарантии: Гарантия на работы: слесарные - 30 дней, электрические - 30 дней, оригинальные з/ч - 30 дней, з/ч, связанные с электрооборудованием, подачей топлива и системой впрыска - гарантии нет, неоригинальные з/ч - гарантии нет. Гарантийные обязательства на работы выполняются фирмой только при предъявлении акта приемки автомобиля и техпаспорта (доверенности).
B48: Дата: 05.06.2026 | J48: Заказчик ______________________ | K48: /Общество с ограниченной ответственностью «Концепт»/
J50: Плательщик ______________________ | K50: /Общество с ограниченной ответственностью «Концепт»/
B52: Причина обращения:

Sheet 0708
B1: ПОСТАВЩИК: ООО ФИРМА "СИГНАЛ"
B2: адрес: 364031, Чеченская Республика, г.Грозный, ул. Жуковского, д. 18
C4: Заказ-наряд № 100515 от 05.06.2026
B6: Заказчик: Общество с ограниченной ответственностью «Концепт» | H6: адрес заказчика : 364024, ЧР г.Грозный, ул.Назарбаева, д.92, оф. 6-05
B7: Автомобиль : Лада 213100 г/н О 0708/15
B9: Цена автомототранспортного средства, определяемая по соглашению сторон __________________
B11: Плательщик: Общество с ограниченной ответственностью «Концепт»
B12: ИНН 2014030866 адрес: телефоны: +7 (989) 9002252
N14: в валюте
N15: Руб
C17: Выполненные работы по заказ-наряду № 100515 от 05.06.2026
B19: № | C19: № кат. | D19: Наименование | I19: Кол. оп. | J19: Цена | K19: Норма | L19: н/ч | M19: Всего | N19: в т.ч. НДС
B20: 1 | C20: 2 | D20: 3 | I20: 4 | J20: 5 | K20: 6 | L20: 7 | M20: 8 | N20: 9
B21: 1 | D21: Замена масла и масл фильтра | I21: 1 | J21: 600 | K21: 1 | L21: Рубль | M21: =J21*I21 -> 600 | N21: =M21*22/122 -> 108.19672
B22: 2 | D22: Замена топливного фильтра | I22: 1 | J22: 200 | K22: 1 | L22: Рубль | M22: =J22*I22 -> 200 | N22: =M22*22/122 -> 36.065574
B23: 3 | D23: Замена воздушного фильтра | I23: 1 | J23: 300 | K23: 1 | L23: Рубль | M23: =J23*I23 -> 300 | N23: =M23*22/122 -> 54.098361
B24: 4 | D24: Диагностика торм системы | I24: 1 | J24: 300 | K24: 1 | L24: Рубль | M24: =J24*I24 -> 300 | N24: =M24*22/122 -> 54.098361
B25: 5 | D25: Замена пер-х торм-х колодок | I25: 1 | J25: 700 | K25: 1 | L25: Рубль | M25: =J25*I25 -> 700 | N25: =M25*22/122 -> 126.22951
B26: 6 | D26: Замена задних торм-х колодок | I26: 1 | J26: 1500 | K26: 1 | L26: Рубль | M26: =J26*I26 -> 1500 | N26: =M26*22/122 -> 270.4918
B27: 7 | D27: Регулировка ручного тормоза | I27: 1 | J27: 300 | K27: 1 | L27: Рубль | M27: =J27*I27 -> 300 | N27: =M27*22/122 -> 54.098361
B28: Итого работ: | I28: 7 | J28: на сумму: | M28: =M21+M22+M23+M24+M25+M26+M27 -> 3900 | N28: =M28*22/122 -> 703.27869
B30: Три тысячи девятьсот рублей 00 копеек.
C32: Расходная накладная к заказ-наряду № 100515 от 05.06.2026
B34: № | C34: № кат. | D34: Наименование | J34: Кол-во | K34: Ед.изм. | L34: Цена | M34: Всего | N34: в т.ч. НДС
B35: 1 | C35: 2 | D35: 3 | J35: 4 | K35: 5 | L35: 6 | M35: 7 | N35: 8
B36: 1 | C36: LF105 | D36: Фильтр масляный LADA 08-112 FINWHALE | J36: 1 | K36: шт | L36: 400 | M36: =L36*J36 -> 400 | N36: =M36*22/122 -> 72.131148
B37: 2 | C37: BM FA2108 | D37: Фильтр воздушный, плоский для LADA ВАЗ 2108-2112 (инж) BM | J37: 1 | K37: шт | L37: 350 | M37: =L37*J37 -> 350 | N37: =M37*22/122 -> 63.114754
B38: 3 | C38: Z004 | D38: Фильтр топливный ВАЗ-2108-10 с о (на гайке) металл ZOLLEX | J38: 1 | K38: шт | L38: 350 | M38: =L38*J38 -> 350 | N38: =M38*22/122 -> 63.114754
B39: 4 | C39: 3705304 | D39: Масло моторное Лукойл Люкс 10W-40 (4л) | J39: 1 | K39: шт | L39: 1150 | M39: =L39*J39 -> 1150 | N39: =M39*22/122 -> 207.37705
B40: 5 | C40: V221 | D40: Колодка тормозная передняя для а м ВАЗ 2121 (к-кт 4шт) FINWHALE | J40: 1 | K40: кт | L40: 800 | M40: =L40*J40 -> 800 | N40: =M40*22/122 -> 144.2623
B41: 6 | C41: 2101-3502090 | D41: Колодка задн Ваз 2101-07-21-23 НАЧАЛО (4шт) | J41: 1 | K41: кт | L41: 1000 | M41: =L41*J41 -> 1000 | N41: =M41*22/122 -> 180.32787
B42: 7 | C42: 4008 | D42: Смазка многоцелевая RC-40, 210 мл BiBiCare | J42: 1 | K42: шт | L42: 250 | M42: =L42*J42 -> 250 | N42: =M42*22/122 -> 45.081967
B43: Итого материалов: | J43: 7 | K43: на сумму: | M43: =M36+M37+M38+M39+M40+M41+M42 -> 4300 | N43: =M43*22/122 -> 775.40984
B45: Четыре тысячи триста рублей 00 копеек
L47: Итого по заказ-наряду : | M47: =M28+M43 -> 8200 | N47: =M47*22/122 -> 1478.6885
B49: Всего по заказ-наряду: Восемь тысяч двести рублей 00 копеек, в т.ч. НДС 22%.
J52: Мастер _____________________ | K52: Механик СТО/
C54: Гарантии: Гарантия на работы: слесарные - 30 дней, электрические - 30 дней, оригинальные з/ч - 30 дней, з/ч, связанные с электрооборудованием, подачей топлива и системой впрыска - гарантии нет, неоригинальные з/ч - гарантии нет. Гарантийные обязательства на работы выполняются фирмой только при предъявлении акта приемки автомобиля и техпаспорта (доверенности).
B58: Дата: 05.06.2026 | J58: Заказчик ______________________ | K58: /Общество с ограниченной ответственностью «Концепт»/
J60: Плательщик ______________________ | K60: /Общество с ограниченной ответственностью «Концепт»/
B62: Причина обращения:

Sheet 154
B1: ПОСТАВЩИК: ООО ФИРМА "СИГНАЛ"
B2: адрес: 364031, Чеченская Республика, г.Грозный, ул. Жуковского, д. 18
C4: Заказ-наряд № 100529 от 08.06.2026
B6: Заказчик: Общество с ограниченной ответственностью «Концепт» | H6: адрес заказчика : 364024, ЧР г.Грозный, ул.Назарбаева, д.92, оф. 6-05
B7: Автомобиль : Лада Веста г/н Е154РА 15
B9: Цена автомототранспортного средства, определяемая по соглашению сторон __________________
B11: Плательщик: Общество с ограниченной ответственностью «Концепт»
B12: ИНН 2014030866 адрес: телефоны: +7 (989) 9002252
N14: в валюте
N15: Руб
Y16: 3
C17: Выполненные работы по заказ-наряду № 100529 от 08.06.2026
B19: № | C19: № кат. | D19: Наименование | I19: Кол. оп. | J19: Цена | K19: Норма | L19: н/ч | M19: Всего | N19: в т.ч. НДС
B20: 1 | C20: 2 | D20: 3 | I20: 4 | J20: 5 | K20: 6 | L20: 7 | M20: 8 | N20: 9
B21: 1 | D21: Замена масла и масл фильтра | I21: 1 | J21: 500 | K21: 1 | L21: Рубль | M21: =J21*I21 -> 500 | N21: =M21*22/122 -> 90.163934
B22: 2 | D22: Замена воздушного фильтра | I22: 1 | J22: 150 | K22: 1 | L22: Рубль | M22: =J22*I22 -> 150 | N22: =M22*22/122 -> 27.04918
B23: 3 | D23: Замена салонного фильтра | I23: 1 | J23: 150 | K23: 1 | L23: Рубль | M23: =J23*I23 -> 150 | N23: =M23*22/122 -> 27.04918
B24: 4 | D24: Ремонт дверного замка | I24: 1 | J24: 1300 | K24: 1 | L24: Рубль | M24: =J24*I24 -> 1300 | N24: =M24*22/122 -> 234.42623
B25: Итого работ: | I25: 4 | J25: на сумму: | M25: =M21+M22+M23+M24 -> 2100 | N25: =M25*22/122 -> 378.68852
B27: Две тысячи сто рублей 00 копеек.
C29: Расходная накладная к заказ-наряду № 100529 от 08.06.2026
B31: № | C31: № кат. | D31: Наименование | J31: Кол-во | K31: Ед.изм. | L31: Цена | M31: Всего | N31: в т.ч. НДС
B32: 1 | C32: 2 | D32: 3 | J32: 4 | K32: 5 | L32: 6 | M32: 7 | N32: 8
B33: 1 | C33: LF105 | D33: Фильтр масляный LADA 08-112 FINWHALE | J33: 1 | K33: шт | L33: 400 | M33: =L33*J33 -> 400 | N33: =M33*22/122 -> 72.131148
B34: 2 | C34: 77143 | D34: Фильтр воздушный ВАЗ 2180 Vesta н/образца 1.6 19- NAC | J34: 1 | K34: шт | L34: 400 | M34: =L34*J34 -> 400 | N34: =M34*22/122 -> 72.131148
B35: 3 | C35: AG448 CF | D35: Фильтр салона LADA Vesta, X-RAY Goodwill | J35: 1 | K35: шт | L35: 450 | M35: =L35*J35 -> 450 | N35: =M35*22/122 -> 81.147541
B36: 4 | C36: 3705304 | D36: Масло моторное Лукойл Люкс 10W-40 (4л) | J36: 1 | K36: шт | L36: 1600 | M36: =L36*J36 -> 1600 | N36: =M36*22/122 -> 288.52459
B37: Итого материалов: | J37: 4 | K37: на сумму: | M37: =M33+M34+M35+M36 -> 2850 | N37: =M37*22/122 -> 513.93443
B39: Две тысячи восемьсот пятьдесят рублей 00 копеек
L41: Итого по заказ-наряду : | M41: =M25+M37 -> 4950 | N41: =M41*22/122 -> 892.62295
B43: Всего по заказ-наряду: Четыре тысячи девятьсот пятьдесят рублей 00 копеек, в т.ч. НДС 22%.
J46: Мастер _____________________ | K46: Механик СТО/
C48: Гарантии: Гарантия на работы: слесарные - 30 дней, электрические - 30 дней, оригинальные з/ч - 30 дней, з/ч, связанные с электрооборудованием, подачей топлива и системой впрыска - гарантии нет, неоригинальные з/ч - гарантии нет. Гарантийные обязательства на работы выполняются фирмой только при предъявлении акта приемки автомобиля и техпаспорта (доверенности).
B52: Дата: 08.06.2026 | J52: Заказчик ______________________ | K52: /ООО «Концепт»/
J54: Плательщик ______________________ | K54: /ООО «Концепт»/
B56: Причина обращения:

Sheet 312 (2)
B1: ПОСТАВЩИК: ООО ФИРМА "СИГНАЛ"
B2: адрес: 364031, Чеченская Республика, г.Грозный, ул. Жуковского, д. 18
C4: Заказ-наряд № 100535 от 09.06.2026
B6: Заказчик: Общество с ограниченной ответственностью «Концепт» | H6: адрес заказчика : 364024, ЧР г.Грозный, ул.Назарбаева, д.92, оф. 6-05
B7: Автомобиль : УАЗ Патриот г/н Е 312 РА/15
B9: Цена автомототранспортного средства, определяемая по соглашению сторон __________________
B11: Плательщик: Общество с ограниченной ответственностью «Концепт»
B12: ИНН 2014030866 адрес: телефоны: +7 (989) 9002252
N14: в валюте
N15: Руб
C17: Выполненные работы по заказ-наряду № 100535 от 09.06.2026
B19: № | C19: № кат. | D19: Наименование | I19: Кол. оп. | J19: Цена | K19: Норма | L19: н/ч | M19: Всего | N19: в т.ч. НДС
B20: 1 | C20: 2 | D20: 3 | I20: 4 | J20: 5 | K20: 6 | L20: 7 | M20: 8 | N20: 9
B21: 1 | D21: Диагностика ходовой | I21: 1 | J21: 400 | K21: 1 | L21: Рубль | M21: =J21*I21 -> 400 | N21: =M21*22/122 -> 72.131148
B22: 2 | D22: Замена рулевого кардана | I22: 1 | J22: 1000 | K22: 1 | L22: Рубль | M22: =J22*I22 -> 1000 | N22: =M22*22/122 -> 180.32787
B23: 3 | D23: Замена салонного фильтра | I23: 1 | J23: 200 | K23: 1 | L23: Рубль | M23: =J23*I23 -> 200 | N23: =M23*22/122 -> 36.065574
B24: 4 | D24: Замена масла и масл фильтра | I24: 1 | J24: 700 | K24: 1 | L24: Рубль | M24: =J24*I24 -> 700 | N24: =M24*22/122 -> 126.22951
B25: 5 | D25: Замена топливного фильтра | I25: 1 | J25: 400 | K25: 1 | L25: Рубль | M25: =J25*I25 -> 400 | N25: =M25*22/122 -> 72.131148
B26: 6 | D26: Замена воздушного фильтра | I26: 1 | J26: 400 | K26: 1 | L26: Рубль | M26: =J26*I26 -> 400 | N26: =M26*22/122 -> 72.131148
B27: 7 | D27: Замена пер-х торм-х колодок | I27: 1 | J27: 800 | K27: 1 | L27: Рубль | M27: =J27*I27 -> 800 | N27: =M27*22/122 -> 144.2623
B28: 8 | D28: Замена свечей зажигания | I28: 1 | J28: 500 | K28: 1 | L28: Рубль | M28: =J28*I28 -> 500 | N28: =M28*22/122 -> 90.163934
B29: 9 | D29: Ремонт и регулировка ручного тормоза | I29: 1 | J29: 600 | K29: 1 | L29: Рубль | M29: =J29*I29 -> 600 | N29: =M29*22/122 -> 108.19672
B30: Итого работ: | I30: 9 | J30: на сумму: | M30: =M21+M22+M23+M24+M25+M26+M27+M28+M29 -> 5000 | N30: =M30*22/122 -> 901.63934
B32: Пять тысяч рублей 00 копеек.
C34: Расходная накладная к заказ-наряду № 100535 от 09.06.2026
B36: № | C36: № кат. | D36: Наименование | J36: Кол-во | K36: Ед.изм. | L36: Цена | M36: Всего | N36: в т.ч. НДС
B37: 1 | C37: 2 | D37: 3 | J37: 4 | K37: 5 | L37: 6 | M37: 7 | N37: 8
B38: 1 | C38: 316310-3401400-00 | D38: Вал карданный УАЗ-3163 (14-) рулевой в сборе под ГУР YB (ОАО УАЗ) | J38: 1 | K38: шт | L38: 6500 | M38: =L38*J38 -> 6500 | N38: =M38*22/122 -> 1172.1311
B39: 2 | C39: ADB0610 | D39: Колодки тормозные дисковые перед УАЗ Патриот кт NIPPON | J39: 1 | K39: шт | L39: 1260 | M39: =L39*J39 -> 1260 | N39: =M39*22/122 -> 227.21311
B40: 3 | C40: SL102 | D40: Фильтр масляный Газель 406 дв Hola | J40: 1 | K40: шт | L40: 400 | M40: =L40*J40 -> 400 | N40: =M40*22/122 -> 72.131148
B41: 4 | C41: 3705305 | D41: Моторное масло Лукойл Люкс SAE 10W-40, API SL/CF 5 л | J41: 1,2 | K41: шт | L41: 1700 | M41: =L41*J41 -> 2040 | N41: =M41*22/122 -> 367.86885
B42: 5 | C42: GLF11 | D42: Фильтр топливный Gallant ВАЗ 2123, 1118 штуцер | J42: 1 | K42: шт | L42: 250 | M42: =L42*J42 -> 250 | N42: =M42*22/122 -> 45.081967
B43: 6 | C43: FA 2201 | D43: Фильтр воздушный BM для UAZ Patriot | J43: 1 | K43: шт | L43: 600 | M43: =L43*J43 -> 600 | N43: =M43*22/122 -> 108.19672
B44: 7 | C44: F01H7B0042-HZ6 | D44: Свечи АУ-17ДВРМ Стандарт "33" ВАЗ 2108-70, ЗМЗ 406-409. УМЗ 4216 | J44: 1 | K44: кт | L44: 600 | M44: =L44*J44 -> 600 | N44: =M44*22/122 -> 108.19672
B45: 8 | C45: 614503 | D45: Фильтр салона УАЗ Патриот с 11.2016г.в. угольный (MetalPart) | J45: 1 | K45: шт | L45: 350 | M45: =L45*J45 -> 350 | N45: =M45*22/122 -> 63.114754
B46: Итого материалов: | J46: 9 | K46: на сумму: | M46: =M38+M39+M40+M41+M42+M43+M44+M45 -> 12000 | N46: =M46*22/122 -> 2163.9344
B48: Двенадцать тысяч рублей 00 копеек
L50: Итого по заказ-наряду : | M50: =M30+M46 -> 17000 | N50: =M50*22/122 -> 3065.5738
B52: Всего по заказ-наряду: Семнадцать тысяч рублей 00 копеек, в т.ч. НДС 22%.
J55: Мастер _____________________ | K55: Механик СТО/
C57: Гарантии: Гарантия на работы: слесарные - 30 дней, электрические - 30 дней, оригинальные з/ч - 30 дней, з/ч, связанные с электрооборудованием, подачей топлива и системой впрыска - гарантии нет, неоригинальные з/ч - гарантии нет. Гарантийные обязательства на работы выполняются фирмой только при предъявлении акта приемки автомобиля и техпаспорта (доверенности).
B61: Дата: 09.06.2026 | J61: Заказчик ______________________ | K61: /ООО «Концепт»/
J63: Плательщик ______________________ | K63: /ООО «Концепт»/
B65: Причина обращения:

Sheet 833 (2)
B1: ПОСТАВЩИК: ООО ФИРМА "СИГНАЛ"
B2: адрес: 364031, Чеченская Республика, г.Грозный, ул. Жуковского, д. 18
C4: Заказ-наряд № 100525 от 08.06.2026
B6: Заказчик: Общество с ограниченной ответственностью «Концепт» | H6: адрес заказчика : 364024, ЧР г.Грозный, ул.Назарбаева, д.92, оф. 6-05
B7: Автомобиль : Лада Веста г/н Е 833 ОЕ/15
B9: Цена автомототранспортного средства, определяемая по соглашению сторон __________________
B11: Плательщик: Общество с ограниченной ответственностью «Концепт»
B12: ИНН 2014030866 адрес: телефоны: +7 (989) 9002252
N14: в валюте
N15: Руб
C17: Выполненные работы по заказ-наряду № 100525 от 08.06.2026
B19: № | C19: № кат. | D19: Наименование | I19: Кол. оп. | J19: Цена | K19: Норма | L19: н/ч | M19: Всего | N19: в т.ч. НДС
B20: 1 | C20: 2 | D20: 3 | I20: 4 | J20: 5 | K20: 6 | L20: 7 | M20: 8 | N20: 9
B21: 1 | D21: Замена масла и масл. фильтра | I21: 1 | J21: 500 | K21: 1 | L21: Рубль | M21: =J21*I21 -> 500 | N21: =M21*22/122 -> 90.163934
B22: 2 | D22: Замена воздушного фильтра | I22: 1 | J22: 200 | K22: 1 | L22: Рубль | M22: =J22*I22 -> 200 | N22: =M22*22/122 -> 36.065574
B23: 3 | D23: Замена салонного фильтра | I23: 1 | J23: 200 | K23: 1 | L23: Рубль | M23: =J23*I23 -> 200 | N23: =M23*22/122 -> 36.065574
B24: 4 | D24: Диагностика кондиционера с опрессовкой | I24: 1 | J24: 1500 | K24: 1 | L24: Рубль | M24: =J24*I24 -> 1500 | N24: =M24*22/122 -> 270.4918
B25: 5 | D25: Заправка кондиционера | I25: 1 | J25: 4500 | K25: 1 | L25: Рубль | M25: =J25*I25 -> 4500 | N25: =M25*22/122 -> 811.47541
B26: 6 | D26: Замена радиатора охлаждения | I26: 1 | J26: 4500 | K26: 1 | L26: Рубль | M26: =J26*I26 -> 4500 | N26: =M26*22/122 -> 811.47541
B27: 7 | D27: Замена радиатора кондиционера | I27: 1 | J27: 2500 | K27: 1 | L27: Рубль | M27: =J27*I27 -> 2500 | N27: =M27*22/122 -> 450.81967
B28: Итого работ: | I28: 7 | J28: на сумму: | M28: =M21+M22+M23+M24+M25+M26+M27 -> 13900 | N28: =M28*22/122 -> 2506.5574
B30: Тринадцать тысяч девятьсот рублей 00 копеек.
C32: Расходная накладная к заказ-наряду № 100525 от 08.06.2026
B34: № | C34: № кат. | D34: Наименование | J34: Кол-во | K34: Ед.изм. | L34: Цена | M34: Всего | N34: в т.ч. НДС
B35: 1 | C35: 2 | D35: 3 | J35: 4 | K35: 5 | L35: 6 | M35: 7 | N35: 8
B36: 1 | C36: LF105 | D36: Фильтр масляный LADA 08-112 FINWHALE | J36: 1 | K36: шт | L36: 400 | M36: =L36*J36 -> 400 | N36: =M36*22/122 -> 72.131148
B37: 2 | C37: 3705304 | D37: Масло моторное Лукойл Люкс 10W-40 (4л) | J37: 1 | K37: шт | L37: 1150 | M37: =L37*J37 -> 1150 | N37: =M37*22/122 -> 207.37705
B38: 3 | C38: AG448 CF | D38: Фильтр салона LADA Vesta, X-RAY Goodwill | J38: 1 | K38: шт | L38: 450 | M38: =L38*J38 -> 450 | N38: =M38*22/122 -> 81.147541
B39: 4 | C39: 77143 | D39: Фильтр воздушный ВАЗ 2180 Vesta н/образца 1.6 19- NAC | J39: 1 | K39: шт | L39: 400 | M39: =L39*J39 -> 400 | N39: =M39*22/122 -> 72.131148
B40: 5 | C40: 8450006932 | D40: Блок переключателей стеклоподъемников передних и зеркал Vesta LADA | J40: 1 | K40: шт | L40: 3000 | M40: =L40*J40 -> 3000 | N40: =M40*22/122 -> 540.98361
B41: 6 | C41: GMRCL18589 | D41: Радиатор охлаждения LADA Vesta/Веста GAMMA | J41: 1 | K41: шт | L41: 5600 | M41: =L41*J41 -> 5600 | N41: =M41*22/122 -> 1009.8361
B42: 7 | C42: ST-DC02-394-0 | D42: Радиатор кондиционера Lada Vesta, X-ray, Renault Logan 2 SAT | J42: 1 | K42: кт | L42: 5500 | M42: =L42*J42 -> 5500 | N42: =M42*22/122 -> 991.80328
B43: 8 | C43: 614503 | D43: Антифриз Sintec LUXE G12+, 5 кг, красный | J43: 1 | K43: кт | L43: 1000 | M43: =L43*J43 -> 1000 | N43: =M43*22/122 -> 180.32787
B44: 9 | C44: 990550 | D44: Антифриз Sintec красный -40С 1кг | J44: 1 | K44: шт | L44: 250 | M44: =L44*J44 -> 250 | N44: =M44*22/122 -> 45.081967
B45: Итого материалов: | J45: 9 | K45: на сумму: | M45: =M36+M37+M38+M39+M40+M41+M42+M43+M44 -> 17750 | N45: =M45*22/122 -> 3200.8197
B47: Семнадцать тысяч семьсот пятьдесят рублей 00 копеек
L49: Итого по заказ-наряду : | M49: =M28+M45 -> 31650 | N49: =M49*22/122 -> 5707.377
B51: Всего по заказ-наряду: Тридцать одна тысяча шестьсот пятьдесят рублей 00 копеек, в т.ч. НДС 22%.
J54: Мастер _____________________ | K54: Механик СТО/
C56: Гарантии: Гарантия на работы: слесарные - 30 дней, электрические - 30 дней, оригинальные з/ч - 30 дней, з/ч, связанные с электрооборудованием, подачей топлива и системой впрыска - гарантии нет, неоригинальные з/ч - гарантии нет. Гарантийные обязательства на работы выполняются фирмой только при предъявлении акта приемки автомобиля и техпаспорта (доверенности).
B60: Дата: 08.06.2026 | J60: Заказчик ______________________ | K60: /Общество с ограниченной ответственностью «Концепт»/
J62: Плательщик ______________________ | K62: /Общество с ограниченной ответственностью «Концепт»/
B64: Причина обращения:

Sheet 211
B1: ПОСТАВЩИК: ООО ФИРМА "СИГНАЛ"
B2: адрес: 364031, Чеченская Республика, г.Грозный, ул. Жуковского, д. 18
C4: Заказ-наряд № 100526 от 08.06.2026
B6: Заказчик: Общество с ограниченной ответственностью «Концепт» | H6: адрес заказчика : 364024, ЧР г.Грозный, ул.Назарбаева, д.92, оф. 6-05
B7: Автомобиль : Лада Веста г/н В 211 ОХ/15
B9: Цена автомототранспортного средства, определяемая по соглашению сторон __________________
B11: Плательщик: Общество с ограниченной ответственностью «Концепт»
B12: ИНН 2014030866 адрес: телефоны: +7 (989) 9002252
N14: в валюте
N15: Руб
C17: Выполненные работы по заказ-наряду № 100526 от 08.06.2026
B19: № | C19: № кат. | D19: Наименование | I19: Кол. оп. | J19: Цена | K19: Норма | L19: н/ч | M19: Всего | N19: в т.ч. НДС
B20: 1 | C20: 2 | D20: 3 | I20: 4 | J20: 5 | K20: 6 | L20: 7 | M20: 8 | N20: 9
B21: 1 | D21: Диагностика подвески | I21: 1 | J21: 300 | K21: 1 | L21: Рубль | M21: =J21*I21 -> 300 | N21: =M21*22/122 -> 54.098361
B22: 2 | D22: Замена стойки стабилизатора | I22: 2 | J22: 500 | K22: 1 | L22: Рубль | M22: =J22*I22 -> 1000 | N22: =M22*22/122 -> 180.32787
B23: 3 | D23: Диагностика ДВС | I23: 1 | J23: 1000 | K23: 1 | L23: Рубль | M23: =J23*I23 -> 1000 | N23: =M23*22/122 -> 180.32787
B24: 4 | D24: Замена датчика детонации | I24: 1 | J24: 500 | K24: 1 | L24: Рубль | M24: =J24*I24 -> 500 | N24: =M24*22/122 -> 90.163934
B25: 5 | D25: Замена ручки стеклоподъемника | I25: 2 | J25: 125 | K25: 1 | L25: Рубль | M25: =J25*I25 -> 250 | N25: =M25*22/122 -> 45.081967
B26: 6 | D26: Замена ремня генератора | I26: 1 | J26: 700 | K26: 1 | L26: Рубль | M26: =J26*I26 -> 700 | N26: =M26*22/122 -> 126.22951
B27: 7 | D27: Диагностика кондиционера с опрессовкой | I27: 1 | J27: 1250 | K27: 1 | L27: Рубль | M27: =J27*I27 -> 1250 | N27: =M27*22/122 -> 225.40984
B28: 8 | D28: Замена втулок задней балки | I28: 2 | J28: 1800 | K28: 1 | L28: Рубль | M28: =J28*I28 -> 3600 | N28: =M28*22/122 -> 649.18033
B29: 9 | D29: Ремонт и балансировка колеса | I29: 1 | J29: 500 | K29: 1 | L29: Рубль | M29: =J29*I29 -> 500 | N29: =M29*22/122 -> 90.163934
B30: Итого работ: | I30: 12 | J30: на сумму: | M30: =M21+M22+M23+M24+M25+M26+M27+M28+M29 -> 9100 | N30: =M30*22/122 -> 1640.9836
B32: Девять тысяч сто рублей 00 копеек.
C34: Расходная накладная к заказ-наряду № 100526 от 08.06.2026
B36: № | C36: № кат. | D36: Наименование | J36: Кол-во | K36: Ед.изм. | L36: Цена | M36: Всего | N36: в т.ч. НДС
B37: 1 | C37: 2 | D37: 3 | J37: 4 | K37: 5 | L37: 6 | M37: 7 | N37: 8
B38: 1 | C38: SP0102 | D38: Стойка стабилизатора TRIALLI ВАЗ Лада Vesta переднего | J38: 2 | K38: шт | L38: 900 | M38: =L38*J38 -> 1800 | N38: =M38*22/122 -> 324.59016
B39: 2 | C39: 18.3855 | D39: Датчик детонации 18.3855 ВАЗ, ГАЗ (дв.405-406) Калуга | J39: 1 | K39: шт | L39: 700 | M39: =L39*J39 -> 700 | N39: =M39*22/122 -> 126.22951
B40: 3 | C40: 210806104064 | D40: Ручка стеклоподъемника ВАЗ-2108 … -2112, Priora, Kalina, Granta и 4x4 с фиксатором | J40: 2 | K40: шт | L40: 30 | M40: =L40*J40 -> 60 | N40: =M40*22/122 -> 10.819672
B41: 4 | C41: 6PK1018 | D41: Ремень генератора GATES 6PK1018 | J41: 1 | K41: шт | L41: 1200 | M41: =L41*J41 -> 1200 | N41: =M41*22/122 -> 216.39344
B42: 5 | C42: 18476 | D42: Втулка задней балки Веста БМРТ - Ломов | J42: 2 | K42: шт | L42: 570 | M42: =L42*J42 -> 1140 | N42: =M42*22/122 -> 205.57377
B43: Итого материалов: | J43: 8 | K43: на сумму: | M43: =M38+M39+M40+M41+M42 -> 4900 | N43: =M43*22/122 -> 883.60656
B45: Четыре тысячи девятьсот рублей 00 копеек
L47: Итого по заказ-наряду : | M47: =M30+M43 -> 14000 | N47: =M47*22/122 -> 2524.5902
B49: Всего по заказ-наряду: Четырнадцать тысяч рублей 00 копеек, в т.ч. НДС 22%.
J52: Мастер _____________________ | K52: Механик СТО/
C54: Гарантии: Гарантия на работы: слесарные - 30 дней, электрические - 30 дней, оригинальные з/ч - 30 дней, з/ч, связанные с электрооборудованием, подачей топлива и системой впрыска - гарантии нет, неоригинальные з/ч - гарантии нет. Гарантийные обязательства на работы выполняются фирмой только при предъявлении акта приемки автомобиля и техпаспорта (доверенности).
B58: Дата: 08.06.2026 | J58: Заказчик ______________________ | K58: /ООО «Концепт»/
J60: Плательщик ______________________ | K60: /ООО «Концепт»/
B62: Причина обращения:
